Workbook

Sheet 0. Mã Supplier
A1: SUPPLIER MANAGEMENT 2025
A3: Date: | B3: 45857
K4: NHÓM SẢN PHẨM
A5: Stt | B5: Supplier Name (Tên nhà cung cấp) | C5: Supplier Code (Mã nhà cung cấp) | D5: Lead time (days) (Thời gian giao hàng) | E5: MOQ | F5: Payment Terms (Phương thức thanh toán) | G5: Delivery Terms (Giao hàng) | H5: Location (Địa điểm) | I5: Key Strengths (Ưu điểm) | J5: Supply Score | K5: Mattress | L5: Gối | M5: Bộ chăn ga | N5: Chăn
A6: 1 | B6: HUY HOÀNG NAM | C6: SUVN0001 | G6: Nội địa | M6: x | N6: x
A7: 2 | B7: HAPPYTOWN SLEEPTECH | C7: SUVN0002 | D7: 15-20 | F7: 30 | G7: Nội địa | K7: x | L7: x
A8: 3 | B8: EVERHOME | C8: SUVN0003 | F8: 60 | G8: Nội địa
A9: 4 | B9: TEXNAM | C9: SUVN0004 | F9: 60 | G9: Nội địa | M9: x
A10: 5 | B10: AP WOOD | C10: SUVN0005 | F10: 60 | G10: Nội địa | N10: x
A11: 6 | B11: POWER X | C11: SUCN0001 | F11: 180 | G11: Quốc tế | K11: x

Sheet 1. Master Data
C1: MASTER LIST PRODUCT CODE
C3: Date update: | D3: 45857 | P3: Tỷ giá usd | R3: 26020 | S3: vnd
C4: Revision: | D4: 1 | E4: Cập nhật lại code của nhóm phụ kiện
B7: Mã sản phẩm | C7: SKU | D7: Category | E7: Ngành hàng | F7: Subcategory code | G7: Subcategory name | H7: ID mã sản phẩm shopee | I7: Variation code | J7: Variation name | K7: Tên Sản Phẩm & kích thước (Cao x Rộng x Dài - cm) | L7: Supplier Code | M7: Brand | N7: Vật liệu chính | O7: Cao | P7: Rộng | Q7: Dài | R7: Net weight | S7: Gross Weight | T7: Đóng gói | U7: Packaget Length (cm) | V7: Packaget Width (cm) | W7: Package height (cm) | X7: Màu | Y7: Min. Order | Z7: Leadtime | AA7: Unit Cost (usd) | AB7: Unit Cost (vnd) | AC7: Giá Vốn (+VAT) | AD7: Sales Price (vnd) | AE7: ABC Class. | AF7: M3
B8: =D8&F8 -> MAT001 | C8: =_xlfn.CONCAT(D8,F8,I8) -> MAT001001 | D8: MAT | E8: Nệm | F8: 001 | G8: T&N Foam | H8: 24893009852 | I8: 001 | J8: =P8&" x "&Q8&" x "&O8&" cm" -> 80 x 200 x 10 cm | K8: =_xlfn.CONCAT(E8," ",G8," ",J8) -> Nệm T&N Foam 80 x 200 x 10 cm | L8: =_xlfn.XLOOKUP(M8,'0. Mã Supplier'!$B:$B,'0. Mã Supplier'!$C:$C,0) -> SUVN0002 | M8: HAPPYTOWN SLEEPTECH | O8: 10 | P8: 80 | Q8: 200 | R8: 0 | S8: 0 | T8: Roll Carton Box | U8: =P8*10+80 -> 880 | V8: 250 | W8: 250 | Y8: 5 | AA8: 0 | AB8: 0 | AC8: =AB8*1.08 -> 0 | AE8: A | AF8: =U8*V8*W8/10^9 -> 0.055
B9: =D9&F9 -> MAT001 | C9: =_xlfn.CONCAT(D9,F9,I9) -> MAT001002 | D9: MAT | E9: Nệm | F9: 001 | G9: T&N Foam | H9: 24893009852 | I9: 002 | J9: =P9&" x "&Q9&" x "&O9&" cm" -> 100 x 200 x 10 cm | K9: =_xlfn.CONCAT(E9," ",G9," ",J9) -> Nệm T&N Foam 100 x 200 x 10 cm | L9: =_xlfn.XLOOKUP(M9,'0. Mã Supplier'!$B:$B,'0. Mã Supplier'!$C:$C,0) -> SUVN0002 | M9: HAPPYTOWN SLEEPTECH | O9: 10 | P9: 100 | Q9: 200 | R9: 0 | S9: 0 | T9: Roll Carton Box | U9: =P9*10+80 -> 1080 | V9: 250 | W9: 250 | Y9: 5 | AA9: 0 | AB9: 0 | AC9: =AB9*1.08 -> 0 | AE9: A | AF9: =U9*V9*W9/10^9 -> 0.0675
B10: =D10&F10 -> MAT001 | C10: =_xlfn.CONCAT(D10,F10,I10) -> MAT001003 | D10: MAT | E10: Nệm | F10: 001 | G10: T&N Foam | H10: 24893009852 | I10: 003 | J10: =P10&" x "&Q10&" x "&O10&" cm" -> 120 x 200 x 10 cm | K10: =_xlfn.CONCAT(E10," ",G10," ",J10) -> Nệm T&N Foam 120 x 200 x 10 cm | L10: =_xlfn.XLOOKUP(M10,'0. Mã Supplier'!$B:$B,'0. Mã Supplier'!$C:$C,0) -> SUVN0002 | M10: HAPPYTOWN SLEEPTECH | O10: 10 | P10: 120 | Q10: 200 | R10: 0 | S10: 0 | T10: Roll Carton Box | U10: =P10*10+80 -> 1280 | V10: 250 | W10: 250 | Y10: 5 | Z10: 15 | AA10: 0 | AB10: 1073100 | AC10: =AB10*1.08 -> 1158948 | AE10: A | AF10: =U10*V10*W10/10^9 -> 0.08
B11: =D11&F11 -> MAT001 | C11: =_xlfn.CONCAT(D11,F11,I11) -> MAT001004 | D11: MAT | E11: Nệm | F11: 001 | G11: T&N Foam | H11: 24893009852 | I11: 004 | J11: =P11&" x "&Q11&" x "&O11&" cm" -> 140 x 200 x 10 cm | K11: =_xlfn.CONCAT(E11," ",G11," ",J11) -> Nệm T&N Foam 140 x 200 x 10 cm | L11: =_xlfn.XLOOKUP(M11,'0. Mã Supplier'!$B:$B,'0. Mã Supplier'!$C:$C,0) -> SUVN0002 | M11: HAPPYTOWN SLEEPTECH | O11: 10 | P11: 140 | Q11: 200 | R11: 0 | S11: 0 | T11: Roll Carton Box | U11: =P11*10+80 -> 1480 | V11: 250 | W11: 250 | Y11: 5 | AA11: 0 | AB11: 0 | AC11: =AB11*1.08 -> 0 | AE11: A | AF11: =U11*V11*W11/10^9 -> 0.0925
B12: =D12&F12 -> MAT001 | C12: =_xlfn.CONCAT(D12,F12,I12) -> MAT001005 | D12: MAT | E12: Nệm | F12: 001 | G12: T&N Foam | H12: 24893009852 | I12: 005 | J12: =P12&" x "&Q12&" x "&O12&" cm" -> 160 x 200 x 10 cm | K12: =_xlfn.CONCAT(E12," ",G12," ",J12) -> Nệm T&N Foam 160 x 200 x 10 cm | L12: =_xlfn.XLOOKUP(M12,'0. Mã Supplier'!$B:$B,'0. Mã Supplier'!$C:$C,0) -> SUVN0002 | M12: HAPPYTOWN SLEEPTECH | O12: 10 | P12: 160 | Q12: 200 | R12: 0 | S12: 0 | T12: Roll Carton Box | U12: =P12*10+80 -> 1680 | V12: 250 | W12: 250 | Y12: 5 | AA12: 0 | AB12: 1421300 | AC12: =AB12*1.08 -> 1535004 | AE12: A | AF12: =U12*V12*W12/10^9 -> 0.105
B13: =D13&F13 -> MAT001 | C13: =_xlfn.CONCAT(D13,F13,I13) -> MAT001006 | D13: MAT | E13: Nệm | F13: 001 | G13: T&N Foam | H13: 24893009852 | I13: 006 | J13: =P13&" x "&Q13&" x "&O13&" cm" -> 180 x 200 x 10 cm | K13: =_xlfn.CONCAT(E13," ",G13," ",J13) -> Nệm T&N Foam 180 x 200 x 10 cm | L13: =_xlfn.XLOOKUP(M13,'0. Mã Supplier'!$B:$B,'0. Mã Supplier'!$C:$C,0) -> SUVN0002 | M13: HAPPYTOWN SLEEPTECH | O13: 10 | P13: 180 | Q13: 200 | R13: 0 | S13: 0 | T13: Roll Carton Box | U13: =P13*10+80 -> 1880 | V13: 250 | W13: 250 | Y13: 5 | AA13: 0 | AB13: 1585400 | AC13: =AB13*1.08 -> 1712232 | AE13: A | AF13: =U13*V13*W13/10^9 -> 0.1175
B14: =D14&F14 -> MAT001 | C14: =_xlfn.CONCAT(D14,F14,I14) -> MAT001007 | D14: MAT | E14: Nệm | F14: 001 | G14: T&N Foam | H14: 24893009852 | I14: 007 | J14: =P14&" x "&Q14&" x "&O14&" cm" -> 200 x 200 x 10 cm | K14: =_xlfn.CONCAT(E14," ",G14," ",J14) -> Nệm T&N Foam 200 x 200 x 10 cm | L14: =_xlfn.XLOOKUP(M14,'0. Mã Supplier'!$B:$B,'0. Mã Supplier'!$C:$C,0) -> SUVN0002 | M14: HAPPYTOWN SLEEPTECH | O14: 10 | P14: 200 | Q14: 200 | R14: 0 | S14: 0 | T14: Roll Carton Box | U14: =P14*10+80 -> 2080 | V14: 250 | W14: 250 | Y14: 5 | AA14: 0 | AB14: 0 | AC14: =AB14*1.08 -> 0 | AE14: A | AF14: =U14*V14*W14/10^9 -> 0.13
B15: =D15&F15 -> MAT001 | C15: =_xlfn.CONCAT(D15,F15,I15) -> MAT001008 | D15: MAT | E15: Nệm | F15: 001 | G15: T&N Foam | H15: 24893009852 | I15: 008 | J15: =P15&" x "&Q15&" x "&O15&" cm" -> 200 x 220 x 10 cm | K15: =_xlfn.CONCAT(E15," ",G15," ",J15) -> Nệm T&N Foam 200 x 220 x 10 cm | L15: =_xlfn.XLOOKUP(M15,'0. Mã Supplier'!$B:$B,'0. Mã Supplier'!$C:$C,0) -> SUVN0002 | M15: HAPPYTOWN SLEEPTECH | O15: 10 | P15: 200 | Q15: 220 | R15: 0 | S15: 0 | T15: Roll Carton Box | U15: =P15*10+80 -> 2080 | V15: 250 | W15: 250 | Y15: 5 | AA15: 0 | AB15: 0 | AC15: =AB15*1.08 -> 0 | AE15: A | AF15: =U15*V15*W15/10^9 -> 0.13
B16: =D16&F16 -> MAT001 | C16: =_xlfn.CONCAT(D16,F16,I16) -> MAT001009 | D16: MAT | E16: Nệm | F16: 001 | G16: T&N Foam | H16: 24893009852 | I16: 009 | J16: =P16&" x "&Q16&" x "&O16&" cm" -> 80 x 200 x 15 cm | K16: =_xlfn.CONCAT(E16," ",G16," ",J16) -> Nệm T&N Foam 80 x 200 x 15 cm | L16: =_xlfn.XLOOKUP(M16,'0. Mã Supplier'!$B:$B,'0. Mã Supplier'!$C:$C,0) -> SUVN0002 | M16: HAPPYTOWN SLEEPTECH | O16: 15 | P16: 80 | Q16: 200 | R16: 0 | S16: 0 | T16: Roll Carton Box | U16: =P16*10+80 -> 880 | V16: 370 | W16: 370 | Y16: 5 | AA16: 0 | AB16: 0 | AC16: =AB16*1.08 -> 0 | AE16: A | AF16: =U16*V16*W16/10^9 -> 0.120472
B17: =D17&F17 -> MAT001 | C17: =_xlfn.CONCAT(D17,F17,I17) -> MAT001010 | D17: MAT | E17: Nệm | F17: 001 | G17: T&N Foam | H17: 24893009852 | I17: 010 | J17: =P17&" x "&Q17&" x "&O17&" cm" -> 100 x 200 x 15 cm | K17: =_xlfn.CONCAT(E17," ",G17," ",J17) -> Nệm T&N Foam 100 x 200 x 15 cm | L17: =_xlfn.XLOOKUP(M17,'0. Mã Supplier'!$B:$B,'0. Mã Supplier'!$C:$C,0) -> SUVN0002 | M17: HAPPYTOWN SLEEPTECH | O17: 15 | P17: 100 | Q17: 200 | R17: 0 | S17: 0 | T17: Roll Carton Box | U17: =P17*10+80 -> 1080 | V17: 370 | W17: 370 | Y17: 5 | AA17: 0 | AB17: 0 | AC17: =AB17*1.08 -> 0 | AE17: A | AF17: =U17*V17*W17/10^9 -> 0.147852
B18: =D18&F18 -> MAT001 | C18: =_xlfn.CONCAT(D18,F18,I18) -> MAT001011 | D18: MAT | E18: Nệm | F18: 001 | G18: T&N Foam | H18: 24893009852 | I18: 011 | J18: =P18&" x "&Q18&" x "&O18&" cm" -> 120 x 200 x 15 cm | K18: =_xlfn.CONCAT(E18," ",G18," ",J18) -> Nệm T&N Foam 120 x 200 x 15 cm | L18: =_xlfn.XLOOKUP(M18,'0. Mã Supplier'!$B:$B,'0. Mã Supplier'!$C:$C,0) -> SUVN0002 | M18: HAPPYTOWN SLEEPTECH | O18: 15 | P18: 120 | Q18: 200 | R18: 0 | S18: 0 | T18: Roll Carton Box | U18: =P18*10+80 -> 1280 | V18: 370 | W18: 370 | Y18: 5 | AA18: 0 | AB18: 0 | AC18: =AB18*1.08 -> 0 | AE18: A | AF18: =U18*V18*W18/10^9 -> 0.175232
B19: =D19&F19 -> MAT001 | C19: =_xlfn.CONCAT(D19,F19,I19) -> MAT001012 | D19: MAT | E19: Nệm | F19: 001 | G19: T&N Foam | H19: 24893009852 | I19: 012 | J19: =P19&" x "&Q19&" x "&O19&" cm" -> 140 x 200 x 15 cm | K19: =_xlfn.CONCAT(E19," ",G19," ",J19) -> Nệm T&N Foam 140 x 200 x 15 cm | L19: =_xlfn.XLOOKUP(M19,'0. Mã Supplier'!$B:$B,'0. Mã Supplier'!$C:$C,0) -> SUVN0002 | M19: HAPPYTOWN SLEEPTECH | O19: 15 | P19: 140 | Q19: 200 | R19: 0 | S19: 0 | T19: Roll Carton Box | U19: =P19*10+80 -> 1480 | V19: 370 | W19: 370 | Y19: 5 | AA19: 0 | AB19: 0 | AC19: =AB19*1.08 -> 0 | AE19: A | AF19: =U19*V19*W19/10^9 -> 0.202612
B20: =D20&F20 -> MAT001 | C20: =_xlfn.CONCAT(D20,F20,I20) -> MAT001013 | D20: MAT | E20: Nệm | F20: 001 | G20: T&N Foam | H20: 24893009852 | I20: 013 | J20: =P20&" x "&Q20&" x "&O20&" cm" -> 160 x 200 x 15 cm | K20: =_xlfn.CONCAT(E20," ",G20," ",J20) -> Nệm T&N Foam 160 x 200 x 15 cm | L20: =_xlfn.XLOOKUP(M20,'0. Mã Supplier'!$B:$B,'0. Mã Supplier'!$C:$C,0) -> SUVN0002 | M20: HAPPYTOWN SLEEPTECH | O20: 15 | P20: 160 | Q20: 200 | R20: 0 | S20: 0 | T20: Roll Carton Box | U20: =P20*10+80 -> 1680 | V20: 370 | W20: 370 | Y20: 5 | AA20: 0 | AB20: 1772300 | AC20: =AB20*1.08 -> 1914084 | AE20: A | AF20: =U20*V20*W20/10^9 -> 0.229992
B21: =D21&F21 -> MAT001 | C21: =_xlfn.CONCAT(D21,F21,I21) -> MAT001014 | D21: MAT | E21: Nệm | F21: 001 | G21: T&N Foam | H21: 24893009852 | I21: 014 | J21: =P21&" x "&Q21&" x "&O21&" cm" -> 180 x 200 x 15 cm | K21: =_xlfn.CONCAT(E21," ",G21," ",J21) -> Nệm T&N Foam 180 x 200 x 15 cm | L21: =_xlfn.XLOOKUP(M21,'0. Mã Supplier'!$B:$B,'0. Mã Supplier'!$C:$C,0) -> SUVN0002 | M21: HAPPYTOWN SLEEPTECH | O21: 15 | P21: 180 | Q21: 200 | R21: 0 | S21: 0 | T21: Roll Carton Box | U21: =P21*10+80 -> 1880 | V21: 370 | W21: 370 | Y21: 5 | AA21: 0 | AB21: 1979600 | AC21: =AB21*1.08 -> 2137968 | AE21: A | AF21: =U21*V21*W21/10^9 -> 0.257372
B22: =D22&F22 -> MAT001 | C22: =_xlfn.CONCAT(D22,F22,I22) -> MAT001015 | D22: MAT | E22: Nệm | F22: 001 | G22: T&N Foam | H22: 24893009852 | I22: 015 | J22: =P22&" x "&Q22&" x "&O22&" cm" -> 200 x 200 x 15 cm | K22: =_xlfn.CONCAT(E22," ",G22," ",J22) -> Nệm T&N Foam 200 x 200 x 15 cm | L22: =_xlfn.XLOOKUP(M22,'0. Mã Supplier'!$B:$B,'0. Mã Supplier'!$C:$C,0) -> SUVN0002 | M22: HAPPYTOWN SLEEPTECH | O22: 15 | P22: 200 | Q22: 200 | R22: 0 | S22: 0 | T22: Roll Carton Box | U22: =P22*10+80 -> 2080 | V22: 370 | W22: 370 | Y22: 5 | AA22: 0 | AB22: 0 | AC22: =AB22*1.08 -> 0 | AE22: A | AF22: =U22*V22*W22/10^9 -> 0.284752
... B31: =D31&F31 -> MAT001 | C31: =_xlfn.CONCAT(D31,F31,I31) -> MAT001024 | D31: MAT | E31: Nệm | F31: 001 | G31: T&N Foam | H31: 24893009852 | I31: 024 | J31: =P31&" x "&Q31&" x "&O31&" cm" -> 200 x 220 x 20 cm | K31: =_xlfn.CONCAT(E31," ",G31," ",J31) -> Nệm T&N Foam 200 x 220 x 20 cm | L31: =_xlfn.XLOOKUP(M31,'0. Mã Supplier'!$B:$B,'0. Mã Supplier'!$C:$C,0) -> SUVN0002 | M31: HAPPYTOWN SLEEPTECH | O31: 20 | P31: 200 | Q31: 220 | R31: 0 | S31: 0 | T31: Roll Carton Box | U31: =P31*10+80 -> 2080 | V31: 370 | W31: 370 | Y31: 5 | AA31: 0 | AB31: 0 | AC31: =AB31*1.08 -> 0 | AE31: A | AF31: =U31*V31*W31/10^9 -> 0.284752
B32: =D32&F32 -> MAT002 | C32: =_xlfn.CONCAT(D32,F32,I32) -> MAT002001 | D32: MAT | E32: Nệm | F32: 002 | G32: Hybrid | H32: 41804007802 | I32: 001 | J32: =P32&" x "&Q32&" x "&O32&" cm" -> 80 x 200 x 25 cm | K32: =_xlfn.CONCAT(E32," ",G32," ",J32) -> Nệm Hybrid 80 x 200 x 25 cm | L32: =_xlfn.XLOOKUP(M32,'0. Mã Supplier'!$B:$B,'0. Mã Supplier'!$C:$C,0) -> SUVN0003 | M32: EVERHOME | O32: 25 | P32: 80 | Q32: 200 | R32: 0 | S32: 0 | T32: Roll Carton Box | V32: 0 | Y32: 5 | AA32: 0 | AB32: 0 | AC32: =AB32*1.08 -> 0 | AE32: A
B33: =D33&F33 -> MAT002 | C33: =_xlfn.CONCAT(D33,F33,I33) -> MAT002002 | D33: MAT | E33: Nệm | F33: 002 | G33: Hybrid | H33: 41804007802 | I33: 002 | J33: =P33&" x "&Q33&" x "&O33&" cm" -> 100 x 200 x 25 cm | K33: =_xlfn.CONCAT(E33," ",G33," ",J33) -> Nệm Hybrid 100 x 200 x 25 cm | L33: =_xlfn.XLOOKUP(M33,'0. Mã Supplier'!$B:$B,'0. Mã Supplier'!$C:$C,0) -> SUVN0003 | M33: EVERHOME | O33: 25 | P33: 100 | Q33: 200 | R33: 0 | S33: 0 | T33: Roll Carton Box | V33: 0 | Y33: 5 | AA33: 0 | AB33: 0 | AC33: =AB33*1.08 -> 0 | AE33: A
B34: =D34&F34 -> MAT002 | C34: =_xlfn.CONCAT(D34,F34,I34) -> MAT002003 | D34: MAT | E34: Nệm | F34: 002 | G34: Hybrid | H34: 41804007802 | I34: 003 | J34: =P34&" x "&Q34&" x "&O34&" cm" -> 120 x 200 x 25 cm | K34: =_xlfn.CONCAT(E34," ",G34," ",J34) -> Nệm Hybrid 120 x 200 x 25 cm | L34: =_xlfn.XLOOKUP(M34,'0. Mã Supplier'!$B:$B,'0. Mã Supplier'!$C:$C,0) -> SUVN0003 | M34: EVERHOME | O34: 25 | P34: 120 | Q34: 200 | R34: 0 | S34: 0 | T34: Roll Carton Box | V34: 0 | Y34: 5 | AA34: 0 | AB34: 1641010 | AC34: =AB34*1.08 -> 1772290.8 | AE34: A
B35: =D35&F35 -> MAT002 | C35: =_xlfn.CONCAT(D35,F35,I35) -> MAT002004 | D35: MAT | E35: Nệm | F35: 002 | G35: Hybrid | H35: 41804007802 | I35: 004 | J35: =P35&" x "&Q35&" x "&O35&" cm" -> 140 x 200 x 25 cm | K35: =_xlfn.CONCAT(E35," ",G35," ",J35) -> Nệm Hybrid 140 x 200 x 25 cm | L35: =_xlfn.XLOOKUP(M35,'0. Mã Supplier'!$B:$B,'0. Mã Supplier'!$C:$C,0) -> SUVN0003 | M35: EVERHOME | O35: 25 | P35: 140 | Q35: 200 | R35: 0 | S35: 0 | T35: Roll Carton Box | V35: 0 | Y35: 5 | AA35: 0 | AB35: 0 | AC35: =AB35*1.08 -> 0 | AE35: A
B36: =D36&F36 -> MAT002 | C36: =_xlfn.CONCAT(D36,F36,I36) -> MAT002005 | D36: MAT | E36: Nệm | F36: 002 | G36: Hybrid | H36: 41804007802 | I36: 005 | J36: =P36&" x "&Q36&" x "&O36&" cm" -> 160 x 200 x 25 cm | K36: =_xlfn.CONCAT(E36," ",G36," ",J36) -> Nệm Hybrid 160 x 200 x 25 cm | L36: =_xlfn.XLOOKUP(M36,'0. Mã Supplier'!$B:$B,'0. Mã Supplier'!$C:$C,0) -> SUVN0003 | M36: EVERHOME | O36: 25 | P36: 160 | Q36: 200 | R36: 0 | S36: 0 | T36: Roll Carton Box | V36: 0 | Y36: 5 | AA36: 0 | AB36: 2229010 | AC36: =AB36*1.08 -> 2407330.8 | AE36: A
B37: =D37&F37 -> MAT002 | C37: =_xlfn.CONCAT(D37,F37,I37) -> MAT002006 | D37: MAT | E37: Nệm | F37: 002 | G37: Hybrid | H37: 41804007802 | I37: 006 | J37: =P37&" x "&Q37&" x "&O37&" cm" -> 180 x 200 x 25 cm | K37: =_xlfn.CONCAT(E37," ",G37," ",J37) -> Nệm Hybrid 180 x 200 x 25 cm | L37: =_xlfn.XLOOKUP(M37,'0. Mã Supplier'!$B:$B,'0. Mã Supplier'!$C:$C,0) -> SUVN0003 | M37: EVERHOME | O37: 25 | P37: 180 | Q37: 200 | R37: 0 | S37: 0 | T37: Roll Carton Box | V37: 0 | Y37: 5 | AA37: 0 | AB37: 2425010 | AC37: =AB37*1.08 -> 2619010.8 | AE37: A
B38: =D38&F38 -> MAT002 | C38: =_xlfn.CONCAT(D38,F38,I38) -> MAT002007 | D38: MAT | E38: Nệm | F38: 002 | G38: Hybrid | H38: 41804007802 | I38: 007 | J38: =P38&" x "&Q38&" x "&O38&" cm" -> 200 x 200 x 25 cm | K38: =_xlfn.CONCAT(E38," ",G38," ",J38) -> Nệm Hybrid 200 x 200 x 25 cm | L38: =_xlfn.XLOOKUP(M38,'0. Mã Supplier'!$B:$B,'0. Mã Supplier'!$C:$C,0) -> SUVN0003 | M38: EVERHOME | O38: 25 | P38: 200 | Q38: 200 | R38: 0 | S38: 0 | T38: Roll Carton Box | V38: 0 | Y38: 5 | AA38: 0 | AB38: 0 | AC38: =AB38*1.08 -> 0 | AE38: A
B39: =D39&F39 -> MAT002 | C39: =_xlfn.CONCAT(D39,F39,I39) -> MAT002008 | D39: MAT | E39: Nệm | F39: 002 | G39: Hybrid | H39: 41804007802 | I39: 008 | J39: =P39&" x "&Q39&" x "&O39&" cm" -> 200 x 220 x 25 cm | K39: =_xlfn.CONCAT(E39," ",G39," ",J39) -> Nệm Hybrid 200 x 220 x 25 cm | L39: =_xlfn.XLOOKUP(M39,'0. Mã Supplier'!$B:$B,'0. Mã Supplier'!$C:$C,0) -> SUVN0003 | M39: EVERHOME | O39: 25 | P39: 200 | Q39: 220 | R39: 0 | S39: 0 | T39: Roll Carton Box | V39: 0 | Y39: 5 | AA39: 0 | AB39: 0 | AC39: =AB39*1.08 -> 0 | AE39: A
B40: =D40&F40 -> MAT003 | C40: =_xlfn.CONCAT(D40,F40,I40) -> MAT003001 | D40: MAT | E40: Nệm | F40: 003 | G40: Hybrid Latex | H40: 43654100667 | I40: 001 | J40: =P40&" x "&Q40&" x "&O40&" cm" -> 80 x 200 x 27 cm | K40: =_xlfn.CONCAT(E40," ",G40," ",J40) -> Nệm Hybrid Latex 80 x 200 x 27 cm | L40: =_xlfn.XLOOKUP(M40,'0. Mã Supplier'!$B:$B,'0. Mã Supplier'!$C:$C,0) -> SUVN0003 | M40: EVERHOME | O40: 27 | P40: 80 | Q40: 200 | R40: 0 | S40: 0 | T40: Roll Carton Box | V40: 0 | Y40: 5 | AA40: 0 | AB40: 0 | AC40: =AB40*1.08 -> 0 | AE40: A
B41: =D41&F41 -> MAT003 | C41: =_xlfn.CONCAT(D41,F41,I41) -> MAT003002 | D41: MAT | E41: Nệm | F41: 003 | G41: Hybrid Latex | H41: 43654100667 | I41: 002 | J41: =P41&" x "&Q41&" x "&O41&" cm" -> 100 x 200 x 27 cm | K41: =_xlfn.CONCAT(E41," ",G41," ",J41) -> Nệm Hybrid Latex 100 x 200 x 27 cm | L41: =_xlfn.XLOOKUP(M41,'0. Mã Supplier'!$B:$B,'0. Mã Supplier'!$C:$C,0) -> SUVN0003 | M41: EVERHOME | O41: 27 | P41: 100 | Q41: 200 | R41: 0 | S41: 0 | T41: Roll Carton Box | V41: 0 | Y41: 5 | AA41: 0 | AB41: 0 | AC41: =AB41*1.08 -> 0 | AE41: A
B42: =D42&F42 -> MAT003 | C42: =_xlfn.CONCAT(D42,F42,I42) -> MAT003003 | D42: MAT | E42: Nệm | F42: 003 | G42: Hybrid Latex | H42: 43654100667 | I42: 003 | J42: =P42&" x "&Q42&" x "&O42&" cm" -> 120 x 200 x 27 cm | K42: =_xlfn.CONCAT(E42," ",G42," ",J42) -> Nệm Hybrid Latex 120 x 200 x 27 cm | L42: =_xlfn.XLOOKUP(M42,'0. Mã Supplier'!$B:$B,'0. Mã Supplier'!$C:$C,0) -> SUVN0003 | M42: EVERHOME | O42: 27 | P42: 120 | Q42: 200 | R42: 0 | S42: 0 | T42: Roll Carton Box | V42: 0 | Y42: 5 | AA42: 0 | AB42: 2082010 | AC42: =AB42*1.08 -> 2248570.8 | AE42: A
B43: =D43&F43 -> MAT003 | C43: =_xlfn.CONCAT(D43,F43,I43) -> MAT003004 | D43: MAT | E43: Nệm | F43: 003 | G43: Hybrid Latex | H43: 43654100667 | I43: 004 | J43: =P43&" x "&Q43&" x "&O43&" cm" -> 140 x 200 x 27 cm | K43: =_xlfn.CONCAT(E43," ",G43," ",J43) -> Nệm Hybrid Latex 140 x 200 x 27 cm | L43: =_xlfn.XLOOKUP(M43,'0. Mã Supplier'!$B:$B,'0. Mã Supplier'!$C:$C,0) -> SUVN0003 | M43: EVERHOME | O43: 27 | P43: 140 | Q43: 200 | R43: 0 | S43: 0 | T43: Roll Carton Box | V43: 0 | Y43: 5 | AA43: 0 | AB43: 0 | AC43: =AB43*1.08 -> 0 | AE43: A
... B49: =D49&F49 -> MAT004 | C49: =_xlfn.CONCAT(D49,F49,I49) -> MAT004002 | D49: MAT | E49: Nệm | F49: 004 | G49: Power X Core | H49: 42770983649 | I49: 002 | J49: =P49&" x "&Q49&" x "&O49&" cm" -> 100 x 200 x 15 cm | K49: =_xlfn.CONCAT(E49," ",G49," ",J49) -> Nệm Power X Core 100 x 200 x 15 cm | L49: =_xlfn.XLOOKUP(M49,'0. Mã Supplier'!$B:$B,'0. Mã Supplier'!$C:$C,0) -> SUCN0001 | M49: POWER X | O49: 15 | P49: 100 | Q49: 200 | R49: 0 | S49: 0 | T49: Roll Carton Box | V49: 0 | Y49: 5 | AA49: 0 | AB49: 0 | AC49: =AB49*1.08 -> 0 | AE49: A
B50: =D50&F50 -> MAT004 | C50: =_xlfn.CONCAT(D50,F50,I50) -> MAT004003 | D50: MAT | E50: Nệm | F50: 004 | G50: Power X Core | H50: 42770983649 | I50: 003 | J50: =P50&" x "&Q50&" x "&O50&" cm" -> 120 x 200 x 15 cm | K50: =_xlfn.CONCAT(E50," ",G50," ",J50) -> Nệm Power X Core 120 x 200 x 15 cm | L50: =_xlfn.XLOOKUP(M50,'0. Mã Supplier'!$B:$B,'0. Mã Supplier'!$C:$C,0) -> SUCN0001 | M50: POWER X | O50: 15 | P50: 120 | Q50: 200 | R50: 12 | S50: 13 | T50: Roll Carton Box | U50: 128 | V50: 25 | W50: 25 | Y50: 5 | AA50: 55.2 | AB50: 1527869 | AC50: =AB50*1.08 -> 1650098.5 | AE50: A
B51: =D51&F51 -> MAT004 | C51: =_xlfn.CONCAT(D51,F51,I51) -> MAT004004 | D51: MAT | E51: Nệm | F51: 004 | G51: Power X Core | H51: 42770983649 | I51: 004 | J51: =P51&" x "&Q51&" x "&O51&" cm" -> 140 x 200 x 15 cm | K51: =_xlfn.CONCAT(E51," ",G51," ",J51) -> Nệm Power X Core 140 x 200 x 15 cm | L51: =_xlfn.XLOOKUP(M51,'0. Mã Supplier'!$B:$B,'0. Mã Supplier'!$C:$C,0) -> SUCN0001 | M51: POWER X | O51: 15 | P51: 140 | Q51: 200 | R51: 14 | S51: 15 | T51: Roll Carton Box | U51: 148 | V51: 25 | W51: 25 | Y51: 5 | AA51: 62 | AB51: 1719112 | AC51: =AB51*1.08 -> 1856641 | AE51: A
B52: =D52&F52 -> MAT004 | C52: =_xlfn.CONCAT(D52,F52,I52) -> MAT004005 | D52: MAT | E52: Nệm | F52: 004 | G52: Power X Core | H52: 42770983649 | I52: 005 | J52: =P52&" x "&Q52&" x "&O52&" cm" -> 160 x 200 x 15 cm | K52: =_xlfn.CONCAT(E52," ",G52," ",J52) -> Nệm Power X Core 160 x 200 x 15 cm | L52: =_xlfn.XLOOKUP(M52,'0. Mã Supplier'!$B:$B,'0. Mã Supplier'!$C:$C,0) -> SUCN0001 | M52: POWER X | O52: 15 | P52: 160 | Q52: 200 | R52: 16.982143 | S52: 18 | T52: Roll Carton Box | U52: 168 | V52: 25 | W52: 25 | Y52: 5 | AA52: 68.5 | AB52: 1902549.1 | AC52: =AB52*1.08 -> 2054753 | AE52: A
B53: =D53&F53 -> MAT004 | C53: =_xlfn.CONCAT(D53,F53,I53) -> MAT004006 | D53: MAT | E53: Nệm | F53: 004 | G53: Power X Core | H53: 42770983649 | I53: 006 | J53: =P53&" x "&Q53&" x "&O53&" cm" -> 180 x 200 x 15 cm | K53: =_xlfn.CONCAT(E53," ",G53," ",J53) -> Nệm Power X Core 180 x 200 x 15 cm | L53: =_xlfn.XLOOKUP(M53,'0. Mã Supplier'!$B:$B,'0. Mã Supplier'!$C:$C,0) -> SUCN0001 | M53: POWER X | O53: 15 | P53: 180 | Q53: 200 | R53: 19 | S53: 20.5 | T53: Roll Carton Box | U53: 188 | V53: 25 | W53: 25 | Y53: 5 | AA53: 75 | AB53: 2085986.1 | AC53: =AB53*1.08 -> 2252865 | AE53: A
B54: =D54&F54 -> MAT004 | C54: =_xlfn.CONCAT(D54,F54,I54) -> MAT004007 | D54: MAT | E54: Nệm | F54: 004 | G54: Power X Core | H54: 42770983649 | I54: 007 | J54: =P54&" x "&Q54&" x "&O54&" cm" -> 200 x 200 x 15 cm | K54: =_xlfn.CONCAT(E54," ",G54," ",J54) -> Nệm Power X Core 200 x 200 x 15 cm | L54: =_xlfn.XLOOKUP(M54,'0. Mã Supplier'!$B:$B,'0. Mã Supplier'!$C:$C,0) -> SUCN0001 | M54: POWER X | O54: 15 | P54: 200 | Q54: 200 | R54: 0 | S54: 0 | T54: Roll Carton Box | U54: 208 | V54: 25 | W54: 25 | Y54: 5 | AA54: 0 | AB54: 0 | AC54: =AB54*1.08 -> 0 | AE54: A
B55: =D55&F55 -> MAT004 | C55: =_xlfn.CONCAT(D55,F55,I55) -> MAT004008 | D55: MAT | E55: Nệm | F55: 004 | G55: Power X Core | H55: 42770983649 | I55: 008 | J55: =P55&" x "&Q55&" x "&O55&" cm" -> 200 x 220 x 15 cm | K55: =_xlfn.CONCAT(E55," ",G55," ",J55) -> Nệm Power X Core 200 x 220 x 15 cm | L55: =_xlfn.XLOOKUP(M55,'0. Mã Supplier'!$B:$B,'0. Mã Supplier'!$C:$C,0) -> SUCN0001 | M55: POWER X | O55: 15 | P55: 200 | Q55: 220 | R55: 20 | S55: 22 | T55: Roll Carton Box | U55: 208 | V55: 25 | W55: 25 | Y55: 5 | AA55: 87.13 | AB55: 2415915.7 | AC55: =AB55*1.08 -> 2609189 | AE55: A
B56: =D56&F56 -> MAT005 | C56: =_xlfn.CONCAT(D56,F56,I56) -> MAT005001 | D56: MAT | E56: Nệm | F56: 005 | G56: Power X Flow | H56: 41970997159 | I56: 001 | J56: =P56&" x "&Q56&" x "&O56&" cm" -> 80 x 200 x 22 cm | K56: =_xlfn.CONCAT(E56," ",G56," ",J56) -> Nệm Power X Flow 80 x 200 x 22 cm | L56: =_xlfn.XLOOKUP(M56,'0. Mã Supplier'!$B:$B,'0. Mã Supplier'!$C:$C,0) -> SUCN0001 | M56: POWER X | O56: 22 | P56: 80 | Q56: 200 | R56: 0 | S56: 0 | T56: Roll Carton Box | V56: 0 | Y56: 5 | AA56: 0 | AB56: 0 | AC56: =AB56*1.08 -> 0 | AE56: A
B57: =D57&F57 -> MAT005 | C57: =_xlfn.CONCAT(D57,F57,I57) -> MAT005002 | D57: MAT | E57: Nệm | F57: 005 | G57: Power X Flow | H57: 41970997159 | I57: 002 | J57: =P57&" x "&Q57&" x "&O57&" cm" -> 100 x 200 x 22 cm | K57: =_xlfn.CONCAT(E57," ",G57," ",J57) -> Nệm Power X Flow 100 x 200 x 22 cm | L57: =_xlfn.XLOOKUP(M57,'0. Mã Supplier'!$B:$B,'0. Mã Supplier'!$C:$C,0) -> SUCN0001 | M57: POWER X | O57: 22 | P57: 100 | Q57: 200 | R57: 0 | S57: 0 | T57: Roll Carton Box | V57: 0 | Y57: 5 | AA57: 0 | AB57: 0 | AC57: =AB57*1.08 -> 0 | AE57: A
B58: =D58&F58 -> MAT005 | C58: =_xlfn.CONCAT(D58,F58,I58) -> MAT005003 | D58: MAT | E58: Nệm | F58: 005 | G58: Power X Flow | H58: 41970997159 | I58: 003 | J58: =P58&" x "&Q58&" x "&O58&" cm" -> 120 x 200 x 22 cm | K58: =_xlfn.CONCAT(E58," ",G58," ",J58) -> Nệm Power X Flow 120 x 200 x 22 cm | L58: =_xlfn.XLOOKUP(M58,'0. Mã Supplier'!$B:$B,'0. Mã Supplier'!$C:$C,0) -> SUCN0001 | M58: POWER X | O58: 22 | P58: 120 | Q58: 200 | R58: 14.5 | S58: 16 | T58: Roll Carton Box | U58: 128 | V58: 30 | W58: 30 | Y58: 5 | AA58: 77 | AB58: 2135393.6 | AC58: =AB58*1.08 -> 2306225.1 | AE58: A
B59: =D59&F59 -> MAT005 | C59: =_xlfn.CONCAT(D59,F59,I59) -> MAT005004 | D59: MAT | E59: Nệm | F59: 005 | G59: Power X Flow | H59: 41970997159 | I59: 004 | J59: =P59&" x "&Q59&" x "&O59&" cm" -> 140 x 200 x 22 cm | K59: =_xlfn.CONCAT(E59," ",G59," ",J59) -> Nệm Power X Flow 140 x 200 x 22 cm | L59: =_xlfn.XLOOKUP(M59,'0. Mã Supplier'!$B:$B,'0. Mã Supplier'!$C:$C,0) -> SUCN0001 | M59: POWER X | O59: 22 | P59: 140 | Q59: 200 | R59: 17.4 | S59: 19.1 | T59: Roll Carton Box | U59: 148 | V59: 30 | W59: 30 | Y59: 5 | AA59: 87 | AB59: 2416195.7 | AC59: =AB59*1.08 -> 2609491.4 | AE59: A
B60: =D60&F60 -> MAT005 | C60: =_xlfn.CONCAT(D60,F60,I60) -> MAT005005 | D60: MAT | E60: Nệm | F60: 005 | G60: Power X Flow | H60: 41970997159 | I60: 005 | J60: =P60&" x "&Q60&" x "&O60&" cm" -> 160 x 200 x 22 cm | K60: =_xlfn.CONCAT(E60," ",G60," ",J60) -> Nệm Power X Flow 160 x 200 x 22 cm | L60: =_xlfn.XLOOKUP(M60,'0. Mã Supplier'!$B:$B,'0. Mã Supplier'!$C:$C,0) -> SUCN0001 | M60: POWER X | O60: 22 | P60: 160 | Q60: 200 | R60: 19.910714 | S60: 22.5 | T60: Roll Carton Box | U60: 168 | V60: 30 | W60: 30 | Y60: 5 | AA60: 97 | AB60: 2696997.8 | AC60: =AB60*1.08 -> 2912757.7 | AE60: A
B61: =D61&F61 -> MAT005 | C61: =_xlfn.CONCAT(D61,F61,I61) -> MAT005006 | D61: MAT | E61: Nệm | F61: 005 | G61: Power X Flow | H61: 41970997159 | I61: 006 | J61: =P61&" x "&Q61&" x "&O61&" cm" -> 180 x 200 x 22 cm | K61: =_xlfn.CONCAT(E61," ",G61," ",J61) -> Nệm Power X Flow 180 x 200 x 22 cm | L61: =_xlfn.XLOOKUP(M61,'0. Mã Supplier'!$B:$B,'0. Mã Supplier'!$C:$C,0) -> SUCN0001 | M61: POWER X | O61: 22 | P61: 180 | Q61: 200 | R61: 21.6 | S61: 23.7 | T61: Roll Carton Box | U61: 188 | V61: 30 | W61: 30 | Y61: 5 | AA61: 106 | AB61: 2951780 | AC61: =AB61*1.08 -> 3187922.4 | AE61: A
B62: =D62&F62 -> MAT005 | C62: =_xlfn.CONCAT(D62,F62,I62) -> MAT005007 | D62: MAT | E62: Nệm | F62: 005 | G62: Power X Flow | H62: 41970997159 | I62: 007 | J62: =P62&" x "&Q62&" x "&O62&" cm" -> 200 x 200 x 22 cm | K62: =_xlfn.CONCAT(E62," ",G62," ",J62) -> Nệm Power X Flow 200 x 200 x 22 cm | L62: =_xlfn.XLOOKUP(M62,'0. Mã Supplier'!$B:$B,'0. Mã Supplier'!$C:$C,0) -> SUCN0001 | M62: POWER X | O62: 22 | P62: 200 | Q62: 200 | R62: 0 | S62: 0 | T62: Roll Carton Box | U62: 208 | V62: 30 | W62: 30 | Y62: 5 | AA62: 0 | AB62: 0 | AC62: =AB62*1.08 -> 0 | AE62: A
B63: =D63&F63 -> MAT005 | C63: =_xlfn.CONCAT(D63,F63,I63) -> MAT005008 | D63: MAT | E63: Nệm | F63: 005 | G63: Power X Flow | H63: 41970997159 | I63: 008 | J63: =P63&" x "&Q63&" x "&O63&" cm" -> 200 x 220 x 22 cm | K63: =_xlfn.CONCAT(E63," ",G63," ",J63) -> Nệm Power X Flow 200 x 220 x 22 cm | L63: =_xlfn.XLOOKUP(M63,'0. Mã Supplier'!$B:$B,'0. Mã Supplier'!$C:$C,0) -> SUCN0001 | M63: POWER X | O63: 22 | P63: 200 | Q63: 220 | R63: 25.7 | S63: 27.9 | T63: Roll Carton Box | U63: 208 | V63: 30 | W63: 30 | Y63: 5 | AA63: 121.18 | AB63: 3367365.7 | AC63: =AB63*1.08 -> 3636755 | AE63: A
B64: =D64&F64 -> MAT006 | C64: =_xlfn.CONCAT(D64,F64,I64) -> MAT006001 | D64: MAT | E64: Nệm | F64: 006 | G64: Power X Fusion | H64: 43421001984 | I64: 001 | J64: =P64&" x "&Q64&" x "&O64&" cm" -> 80 x 200 x 27 cm | K64: =_xlfn.CONCAT(E64," ",G64," ",J64) -> Nệm Power X Fusion 80 x 200 x 27 cm | L64: =_xlfn.XLOOKUP(M64,'0. Mã Supplier'!$B:$B,'0. Mã Supplier'!$C:$C,0) -> SUCN0001 | M64: POWER X | O64: 27 | P64: 80 | Q64: 200 | R64: 0 | S64: 0 | T64: Roll Carton Box | V64: 0 | Y64: 5 | AA64: 0 | AB64: 0 | AC64: =AB64*1.08 -> 0 | AE64: A
B65: =D65&F65 -> MAT006 | C65: =_xlfn.CONCAT(D65,F65,I65) -> MAT006002 | D65: MAT | E65: Nệm | F65: 006 | G65: Power X Fusion | H65: 43421001984 | I65: 002 | J65: =P65&" x "&Q65&" x "&O65&" cm" -> 100 x 200 x 27 cm | K65: =_xlfn.CONCAT(E65," ",G65," ",J65) -> Nệm Power X Fusion 100 x 200 x 27 cm | L65: =_xlfn.XLOOKUP(M65,'0. Mã Supplier'!$B:$B,'0. Mã Supplier'!$C:$C,0) -> SUCN0001 | M65: POWER X | O65: 27 | P65: 100 | Q65: 200 | R65: 0 | S65: 0 | T65: Roll Carton Box | V65: 0 | Y65: 5 | AA65: 0 | AB65: 0 | AC65: =AB65*1.08 -> 0 | AE65: A
B66: =D66&F66 -> MAT006 | C66: =_xlfn.CONCAT(D66,F66,I66) -> MAT006003 | D66: MAT | E66: Nệm | F66: 006 | G66: Power X Fusion | H66: 43421001984 | I66: 003 | J66: =P66&" x "&Q66&" x "&O66&" cm" -> 120 x 200 x 27 cm | K66: =_xlfn.CONCAT(E66," ",G66," ",J66) -> Nệm Power X Fusion 120 x 200 x 27 cm | L66: =_xlfn.XLOOKUP(M66,'0. Mã Supplier'!$B:$B,'0. Mã Supplier'!$C:$C,0) -> SUCN0001 | M66: POWER X | O66: 27 | P66: 120 | Q66: 200 | R66: 27.3 | S66: 29.2 | T66: Roll Carton Box | U66: 128 | V66: 36 | W66: 36 | Y66: 5 | AA66: 130 | AB66: 3572469.2 | AC66: =AB66*1.08 -> 3858266.7 | AE66: A
B67: =D67&F67 -> MAT006 | C67: =_xlfn.CONCAT(D67,F67,I67) -> MAT006004 | D67: MAT | E67: Nệm | F67: 006 | G67: Power X Fusion | H67: 43421001984 | I67: 004 | J67: =P67&" x "&Q67&" x "&O67&" cm" -> 140 x 200 x 27 cm | K67: =_xlfn.CONCAT(E67," ",G67," ",J67) -> Nệm Power X Fusion 140 x 200 x 27 cm | L67: =_xlfn.XLOOKUP(M67,'0. Mã Supplier'!$B:$B,'0. Mã Supplier'!$C:$C,0) -> SUCN0001 | M67: POWER X | O67: 27 | P67: 140 | Q67: 200 | R67: 32.6 | S67: 34.7 | T67: Roll Carton Box | U67: 148 | V67: 36 | W67: 36 | Y67: 5 | AA67: 143 | AB67: 3940396.2 | AC67: =AB67*1.08 -> 4255627.9 | AE67: A
B68: =D68&F68 -> MAT006 | C68: =_xlfn.CONCAT(D68,F68,I68) -> MAT006005 | D68: MAT | E68: Nệm | F68: 006 | G68: Power X Fusion | H68: 43421001984 | I68: 005 | J68: =P68&" x "&Q68&" x "&O68&" cm" -> 160 x 200 x 27 cm | K68: =_xlfn.CONCAT(E68," ",G68," ",J68) -> Nệm Power X Fusion 160 x 200 x 27 cm | L68: =_xlfn.XLOOKUP(M68,'0. Mã Supplier'!$B:$B,'0. Mã Supplier'!$C:$C,0) -> SUCN0001 | M68: POWER X | O68: 27 | P68: 160 | Q68: 200 | R68: 36.823846 | S68: 39.285385 | T68: Roll Carton Box | U68: 168 | V68: 36 | W68: 36 | Y68: 5 | AA68: 160 | AB68: 4412403.3 | AC68: =AB68*1.08 -> 4765395.6 | AE68: A
B69: =D69&F69 -> MAT006 | C69: =_xlfn.CONCAT(D69,F69,I69) -> MAT006006 | D69: MAT | E69: Nệm | F69: 006 | G69: Power X Fusion | H69: 43421001984 | I69: 006 | J69: =P69&" x "&Q69&" x "&O69&" cm" -> 180 x 200 x 27 cm | K69: =_xlfn.CONCAT(E69," ",G69," ",J69) -> Nệm Power X Fusion 180 x 200 x 27 cm | L69: =_xlfn.XLOOKUP(M69,'0. Mã Supplier'!$B:$B,'0. Mã Supplier'!$C:$C,0) -> SUCN0001 | M69: POWER X | O69: 27 | P69: 180 | Q69: 200 | R69: 41 | S69: 43.1 | T69: Roll Carton Box | U69: 188 | V69: 36 | W69: 36 | Y69: 5 | AA69: 174 | AB69: 4806350.4 | AC69: =AB69*1.08 -> 5190858.4 | AE69: A
B70: =D70&F70 -> MAT006 | C70: =_xlfn.CONCAT(D70,F70,I70) -> MAT006007 | D70: MAT | E70: Nệm | F70: 006 | G70: Power X Fusion | H70: 43421001984 | I70: 007 | J70: =P70&" x "&Q70&" x "&O70&" cm" -> 200 x 200 x 27 cm | K70: =_xlfn.CONCAT(E70," ",G70," ",J70) -> Nệm Power X Fusion 200 x 200 x 27 cm | L70: =_xlfn.XLOOKUP(M70,'0. Mã Supplier'!$B:$B,'0. Mã Supplier'!$C:$C,0) -> SUCN0001 | M70: POWER X | O70: 27 | P70: 200 | Q70: 200 | R70: 0 | S70: 0 | T70: Roll Carton Box | U70: 208 | V70: 36 | W70: 36 | Y70: 5 | AA70: 0 | AB70: 0 | AC70: =AB70*1.08 -> 0 | AE70: A
B71: =D71&F71 -> MAT006 | C71: =_xlfn.CONCAT(D71,F71,I71) -> MAT006008 | D71: MAT | E71: Nệm | F71: 006 | G71: Power X Fusion | H71: 43421001984 | I71: 008 | J71: =P71&" x "&Q71&" x "&O71&" cm" -> 200 x 220 x 27 cm | K71: =_xlfn.CONCAT(E71," ",G71," ",J71) -> Nệm Power X Fusion 200 x 220 x 27 cm | L71: =_xlfn.XLOOKUP(M71,'0. Mã Supplier'!$B:$B,'0. Mã Supplier'!$C:$C,0) -> SUCN0001 | M71: POWER X | O71: 27 | P71: 200 | Q71: 220 | R71: 49.2 | S71: 52.1 | T71: Roll Carton Box | U71: 208 | V71: 36 | W71: 36 | Y71: 5 | AA71: 194 | AB71: 5356417.4 | AC71: =AB71*1.08 -> 5784930.8 | AE71: A
B72: =D72&F72 -> MAT007 | C72: =_xlfn.CONCAT(D72,F72,I72) -> MAT007001 | D72: MAT | E72: Nệm | F72: 007 | G72: Power X Prime | H72: 43071003412 | I72: 001 | J72: =P72&" x "&Q72&" x "&O72&" cm" -> 80 x 200 x 30 cm | K72: =_xlfn.CONCAT(E72," ",G72," ",J72) -> Nệm Power X Prime 80 x 200 x 30 cm | L72: =_xlfn.XLOOKUP(M72,'0. Mã Supplier'!$B:$B,'0. Mã Supplier'!$C:$C,0) -> SUCN0001 | M72: POWER X | O72: 30 | P72: 80 | Q72: 200 | R72: 0 | S72: 0 | T72: Roll Carton Box | V72: 0 | Y72: 5 | AA72: 0 | AB72: 0 | AC72: =AB72*1.08 -> 0 | AE72: A
B73: =D73&F73 -> MAT007 | C73: =_xlfn.CONCAT(D73,F73,I73) -> MAT007002 | D73: MAT | E73: Nệm | F73: 007 | G73: Power X Prime | H73: 43071003412 | I73: 002 | J73: =P73&" x "&Q73&" x "&O73&" cm" -> 100 x 200 x 30 cm | K73: =_xlfn.CONCAT(E73," ",G73," ",J73) -> Nệm Power X Prime 100 x 200 x 30 cm | L73: =_xlfn.XLOOKUP(M73,'0. Mã Supplier'!$B:$B,'0. Mã Supplier'!$C:$C,0) -> SUCN0001 | M73: POWER X | O73: 30 | P73: 100 | Q73: 200 | R73: 0 | S73: 0 | T73: Roll Carton Box | V73: 0 | Y73: 5 | AA73: 0 | AB73: 0 | AC73: =AB73*1.08 -> 0 | AE73: A
B74: =D74&F74 -> MAT007 | C74: =_xlfn.CONCAT(D74,F74,I74) -> MAT007003 | D74: MAT | E74: Nệm | F74: 007 | G74: Power X Prime | H74: 43071003412 | I74: 003 | J74: =P74&" x "&Q74&" x "&O74&" cm" -> 120 x 200 x 30 cm | K74: =_xlfn.CONCAT(E74," ",G74," ",J74) -> Nệm Power X Prime 120 x 200 x 30 cm | L74: =_xlfn.XLOOKUP(M74,'0. Mã Supplier'!$B:$B,'0. Mã Supplier'!$C:$C,0) -> SUCN0001 | M74: POWER X | O74: 30 | P74: 120 | Q74: 200 | R74: 34.1 | S74: 36.9 | T74: Roll Carton Box | U74: 128 | V74: 40 | W74: 40 | Y74: 5 | AA74: 190 | AB74: 5178206.4 | AC74: =AB74*1.08 -> 5592462.9 | AE74: A
B75: =D75&F75 -> MAT007 | C75: =_xlfn.CONCAT(D75,F75,I75) -> MAT007004 | D75: MAT | E75: Nệm | F75: 007 | G75: Power X Prime | H75: 43071003412 | I75: 004 | J75: =P75&" x "&Q75&" x "&O75&" cm" -> 140 x 200 x 30 cm | K75: =_xlfn.CONCAT(E75," ",G75," ",J75) -> Nệm Power X Prime 140 x 200 x 30 cm | L75: =_xlfn.XLOOKUP(M75,'0. Mã Supplier'!$B:$B,'0. Mã Supplier'!$C:$C,0) -> SUCN0001 | M75: POWER X | O75: 30 | P75: 140 | Q75: 200 | R75: 38.2 | S75: 40.6 | T75: Roll Carton Box | U75: 148 | V75: 40 | W75: 40 | Y75: 5 | AA75: 217 | AB75: 5917372.4 | AC75: =AB75*1.08 -> 6390762.2 | AE75: A
B76: =D76&F76 -> MAT007 | C76: =_xlfn.CONCAT(D76,F76,I76) -> MAT007005 | D76: MAT | E76: Nệm | F76: 007 | G76: Power X Prime | H76: 43071003412 | I76: 005 | J76: =P76&" x "&Q76&" x "&O76&" cm" -> 160 x 200 x 30 cm | K76: =_xlfn.CONCAT(E76," ",G76," ",J76) -> Nệm Power X Prime 160 x 200 x 30 cm | L76: =_xlfn.XLOOKUP(M76,'0. Mã Supplier'!$B:$B,'0. Mã Supplier'!$C:$C,0) -> SUCN0001 | M76: POWER X | O76: 30 | P76: 160 | Q76: 200 | R76: 41.416 | S76: 45.2 | T76: Roll Carton Box | U76: 168 | V76: 40 | W76: 40 | Y76: 5 | AA76: 241 | AB76: 6578478.4 | AC76: =AB76*1.08 -> 7104756.7 | AE76: A
B77: =D77&F77 -> MAT007 | C77: =_xlfn.CONCAT(D77,F77,I77) -> MAT007006 | D77: MAT | E77: Nệm | F77: 007 | G77: Power X Prime | H77: 43071003412 | I77: 006 | J77: =P77&" x "&Q77&" x "&O77&" cm" -> 180 x 200 x 30 cm | K77: =_xlfn.CONCAT(E77," ",G77," ",J77) -> Nệm Power X Prime 180 x 200 x 30 cm | L77: =_xlfn.XLOOKUP(M77,'0. Mã Supplier'!$B:$B,'0. Mã Supplier'!$C:$C,0) -> SUCN0001 | M77: POWER X | O77: 30 | P77: 180 | Q77: 200 | R77: 49 | S77: 51.5 | T77: Roll Carton Box | U77: 188 | V77: 40 | W77: 40 | Y77: 5 | AA77: 267 | AB77: 7291624.4 | AC77: =AB77*1.08 -> 7874954.3 | AE77: A
B78: =D78&F78 -> MAT007 | C78: =_xlfn.CONCAT(D78,F78,I78) -> MAT007007 | D78: MAT | E78: Nệm | F78: 007 | G78: Power X Prime | H78: 43071003412 | I78: 007 | J78: =P78&" x "&Q78&" x "&O78&" cm" -> 200 x 200 x 30 cm | K78: =_xlfn.CONCAT(E78," ",G78," ",J78) -> Nệm Power X Prime 200 x 200 x 30 cm | L78: =_xlfn.XLOOKUP(M78,'0. Mã Supplier'!$B:$B,'0. Mã Supplier'!$C:$C,0) -> SUCN0001 | M78: POWER X | O78: 30 | P78: 200 | Q78: 200 | R78: 0 | S78: 0 | T78: Roll Carton Box | U78: 208 | V78: 40 | W78: 40 | Y78: 5 | AA78: 0 | AB78: 0 | AC78: =AB78*1.08 -> 0 | AE78: A
B79: =D79&F79 -> MAT007 | C79: =_xlfn.CONCAT(D79,F79,I79) -> MAT007008 | D79: MAT | E79: Nệm | F79: 007 | G79: Power X Prime | H79: 43071003412 | I79: 008 | J79: =P79&" x "&Q79&" x "&O79&" cm" -> 200 x 220 x 30 cm | K79: =_xlfn.CONCAT(E79," ",G79," ",J79) -> Nệm Power X Prime 200 x 220 x 30 cm | L79: =_xlfn.XLOOKUP(M79,'0. Mã Supplier'!$B:$B,'0. Mã Supplier'!$C:$C,0) -> SUCN0001 | M79: POWER X | O79: 30 | P79: 200 | Q79: 220 | R79: 61 | S79: 63 | T79: Roll Carton Box | U79: 208 | V79: 40 | W79: 40 | Y79: 5 | AA79: 303.37 | AB79: 8274597.8 | AC79: =AB79*1.08 -> 8936565.6 | AE79: A
B80: =D80&F80 -> PIL001 | C80: =_xlfn.CONCAT(D80,F80,I80) -> PIL001001 | D80: PIL | E80: Gối | F80: 001 | G80: T&N contour (Cứng) | H80: 27781026451 | I80: 001 | J80: =P80&" x "&Q80&" x "&O80&" cm" -> 30 x 50 x 8/10 cm | K80: =_xlfn.CONCAT(E80," ",G80," ",J80) -> Gối T&N contour (Cứng) 30 x 50 x 8/10 cm | L80: =_xlfn.XLOOKUP(M80,'0. Mã Supplier'!$B:$B,'0. Mã Supplier'!$C:$C,0) -> SUVN0002 | M80: HAPPYTOWN SLEEPTECH | O80: 8/10 | P80: 30 | Q80: 50 | R80: 0 | S80: 0 | T80: Roll Carton Box | U80: 40 | V80: 20 | W80: 20 | Y80: 5 | AA80: 0 | AB80: 116100 | AC80: =AB80*1.08 -> 125388
B81: =D81&F81 -> PIL001 | C81: =_xlfn.CONCAT(D81,F81,I81) -> PIL001002 | D81: PIL | E81: Gối | F81: 001 | G81: T&N contour (Cứng) | H81: 27781026451 | I81: 002 | J81: =P81&" x "&Q81&" x "&O81&" cm" -> 40 x 60 x 10/12 cm | K81: =_xlfn.CONCAT(E81," ",G81," ",J81) -> Gối T&N contour (Cứng) 40 x 60 x 10/12 cm | L81: =_xlfn.XLOOKUP(M81,'0. Mã Supplier'!$B:$B,'0. Mã Supplier'!$C:$C,0) -> SUVN0002 | M81: HAPPYTOWN SLEEPTECH | O81: 10/12 | P81: 40 | Q81: 60 | R81: 0 | S81: 0 | T81: Roll Carton Box | U81: 40 | V81: 20 | W81: 20 | Y81: 5 | AA81: 0 | AB81: 143100 | AC81: =AB81*1.08 -> 154548 | AD81: =AB81/(1-0.55) -> 318000
B82: =D82&F82 -> PIL001 | C82: =_xlfn.CONCAT(D82,F82,I82) -> PIL001003 | D82: PIL | E82: Gối | F82: 001 | G82: T&N contour (Mềm) | H82: 27781026451 | I82: 003 | J82: =P82&" x "&Q82&" x "&O82&" cm" -> 30 x 50 x 8/10 cm | K82: =_xlfn.CONCAT(E82," ",G82," ",J82) -> Gối T&N contour (Mềm) 30 x 50 x 8/10 cm | L82: =_xlfn.XLOOKUP(M82,'0. Mã Supplier'!$B:$B,'0. Mã Supplier'!$C:$C,0) -> SUVN0002 | M82: HAPPYTOWN SLEEPTECH | O82: 8/10 | P82: 30 | Q82: 50 | R82: 0 | S82: 0 | T82: Roll Carton Box | U82: 40 | V82: 20 | W82: 20 | Y82: 5 | AA82: 0 | AB82: 139000 | AC82: =AB82*1.08 -> 150120
B83: =D83&F83 -> PIL001 | C83: =_xlfn.CONCAT(D83,F83,I83) -> PIL001004 | D83: PIL | E83: Gối | F83: 001 | G83: T&N contour (Mềm) | H83: 27781026451 | I83: 004 | J83: =P83&" x "&Q83&" x "&O83&" cm" -> 40 x 60 x 10/12 cm | K83: =_xlfn.CONCAT(E83," ",G83," ",J83) -> Gối T&N contour (Mềm) 40 x 60 x 10/12 cm | L83: =_xlfn.XLOOKUP(M83,'0. Mã Supplier'!$B:$B,'0. Mã Supplier'!$C:$C,0) -> SUVN0002 | M83: HAPPYTOWN SLEEPTECH | O83: 10/12 | P83: 40 | Q83: 60 | R83: 0 | S83: 0 | T83: Roll Carton Box | U83: 40 | V83: 20 | W83: 20 | Y83: 5 | AA83: 0 | AB83: 181000 | AC83: =AB83*1.08 -> 195480 | AD83: =AB83/(1-0.55) -> 402222.22
B84: =D84&F84 -> PIL002 | C84: =_xlfn.CONCAT(D84,F84,I84) -> PIL002001 | D84: PIL | E84: Gối | F84: 002 | G84: Power X Ergo | H84: 41271371866 | I84: 001 | J84: =P84&" x "&Q84&" x "&O84&" cm" -> 40 x 60 x 10/12 cm | K84: =_xlfn.CONCAT(E84," ",G84," ",J84) -> Gối Power X Ergo 40 x 60 x 10/12 cm | L84: =_xlfn.XLOOKUP(M84,'0. Mã Supplier'!$B:$B,'0. Mã Supplier'!$C:$C,0) -> SUCN0001 | M84: POWER X | O84: 10/12 | P84: 40 | Q84: 60 | R84: 0.9 | S84: 1.35 | T84: Roll Carton Box | U84: 40 | V84: 15 | W84: 15 | Y84: 5 | AA84: 9.5 | AB84: 259994.45 | AC84: =AB84*1.08 -> 280794.01
B85: =D85&F85 -> PIL003 | C85: =_xlfn.CONCAT(D85,F85,I85) -> PIL003001 | D85: PIL | E85: Gối | F85: 003 | G85: Power X Matrix | H85: 44071363621 | I85: 001 | J85: =P85&" x "&Q85&" x "&O85&" cm" -> 40 x 60 x 12 cm | K85: =_xlfn.CONCAT(E85," ",G85," ",J85) -> Gối Power X Matrix 40 x 60 x 12 cm | L85: =_xlfn.XLOOKUP(M85,'0. Mã Supplier'!$B:$B,'0. Mã Supplier'!$C:$C,0) -> SUCN0001 | M85: POWER X | O85: 12 | P85: 40 | Q85: 60 | R85: 1 | S85: 1.88 | T85: Carton Box | U85: 60 | V85: 40 | W85: 20 | Y85: 5 | AA85: 16.8 | AB85: 473497.38 | AC85: =AB85*1.08 -> 511377.17
B86: =D86&F86 -> PIL004 | C86: =_xlfn.CONCAT(D86,F86,I86) -> PIL004001 | D86: PIL | E86: Gối | F86: 004 | G86: T&N Bean (Thun lạnh) | H86: 0 | I86: 001 | J86: =P86&" x "&Q86&" x "&O86&" cm" -> 30 x 50 x 9/7 cm | K86: =_xlfn.CONCAT(E86," ",G86," ",J86) -> Gối T&N Bean (Thun lạnh) 30 x 50 x 9/7 cm | L86: =_xlfn.XLOOKUP(M86,'0. Mã Supplier'!$B:$B,'0. Mã Supplier'!$C:$C,0) -> SUVN0003 | M86: EVERHOME | O86: 9/7 | P86: 30 | Q86: 50 | T86: Roll Carton Box | V86: 0 | Y86: 5 | AA86: 0 | AC86: =AB86*1.08 -> 0
B87: =D87&F87 -> PIL004 | C87: =_xlfn.CONCAT(D87,F87,I87) -> PIL004002 | D87: PIL | E87: Gối | F87: 004 | G87: T&N Bean (Thun lạnh) | H87: 0 | I87: 002 | J87: =P87&" x "&Q87&" x "&O87&" cm" -> 40 x 60 x 12/10 cm | K87: =_xlfn.CONCAT(E87," ",G87," ",J87) -> Gối T&N Bean (Thun lạnh) 40 x 60 x 12/10 cm | L87: =_xlfn.XLOOKUP(M87,'0. Mã Supplier'!$B:$B,'0. Mã Supplier'!$C:$C,0) -> SUVN0003 | M87: EVERHOME | O87: 12/10 | P87: 40 | Q87: 60 | T87: Roll Carton Box | V87: 0 | Y87: 5 | AA87: 0 | AC87: =AB87*1.08 -> 0
B88: =D88&F88 -> PIL005 | C88: =_xlfn.CONCAT(D88,F88,I88) -> PIL005001 | D88: PIL | E88: Gối | F88: 005 | G88: T&N Oval (Thun lạnh) | H88: 0 | I88: 001 | J88: =P88&" x "&Q88&" x "&O88&" cm" -> 30 x 50 x 10 cm | K88: =_xlfn.CONCAT(E88," ",G88," ",J88) -> Gối T&N Oval (Thun lạnh) 30 x 50 x 10 cm | L88: =_xlfn.XLOOKUP(M88,'0. Mã Supplier'!$B:$B,'0. Mã Supplier'!$C:$C,0) -> SUVN0003 | M88: EVERHOME | O88: 10 | P88: 30 | Q88: 50 | T88: Roll Carton Box | V88: 0 | Y88: 5 | AA88: 0 | AC88: =AB88*1.08 -> 0
B89: =D89&F89 -> PIL005 | C89: =_xlfn.CONCAT(D89,F89,I89) -> PIL005002 | D89: PIL | E89: Gối | F89: 005 | G89: T&N Oval (Thun lạnh) | H89: 0 | I89: 002 | J89: =P89&" x "&Q89&" x "&O89&" cm" -> 40 x 60 x 11 cm | K89: =_xlfn.CONCAT(E89," ",G89," ",J89) -> Gối T&N Oval (Thun lạnh) 40 x 60 x 11 cm | L89: =_xlfn.XLOOKUP(M89,'0. Mã Supplier'!$B:$B,'0. Mã Supplier'!$C:$C,0) -> SUVN0003 | M89: EVERHOME | O89: 11 | P89: 40 | Q89: 60 | T89: Roll Carton Box | V89: 0 | Y89: 5 | AA89: 0 | AC89: =AB89*1.08 -> 0
B90: =D90&F90 -> PIL006 | C90: =_xlfn.CONCAT(D90,F90,I90) -> PIL006001 | D90: PIL | E90: Gối | F90: 006 | G90: T&N Contour (Thun lạnh) | H90: 0 | I90: 001 | J90: =P90&" x "&Q90&" x "&O90&" cm" -> 30 x 50 x 8/6 cm | K90: =_xlfn.CONCAT(E90," ",G90," ",J90) -> Gối T&N Contour (Thun lạnh) 30 x 50 x 8/6 cm | L90: =_xlfn.XLOOKUP(M90,'0. Mã Supplier'!$B:$B,'0. Mã Supplier'!$C:$C,0) -> SUVN0003 | M90: EVERHOME | O90: 8/6 | P90: 30 | Q90: 50 | T90: Roll Carton Box | V90: 0 | Y90: 5 | AA90: 0 | AC90: =AB90*1.08 -> 0
B91: =D91&F91 -> PIL006 | C91: =_xlfn.CONCAT(D91,F91,I91) -> PIL006002 | D91: PIL | E91: Gối | F91: 006 | G91: T&N Contour (Thun lạnh) | H91: 0 | I91: 002 | J91: =P91&" x "&Q91&" x "&O91&" cm" -> 40 x 60 x 11/9 cm | K91: =_xlfn.CONCAT(E91," ",G91," ",J91) -> Gối T&N Contour (Thun lạnh) 40 x 60 x 11/9 cm | L91: =_xlfn.XLOOKUP(M91,'0. Mã Supplier'!$B:$B,'0. Mã Supplier'!$C:$C,0) -> SUVN0003 | M91: EVERHOME | O91: 11/9 | P91: 40 | Q91: 60 | T91: Roll Carton Box | V91: 0 | Y91: 5 | AA91: 0 | AC91: =AB91*1.08 -> 0
B92: =D92&F92 -> SET001 | C92: =_xlfn.CONCAT(D92,F92,I92) -> SET001001 | D92: SET | E92: Bộ Chăn ga | F92: 001 | G92: Xơ đũi 4CT (ga phủ, chăn chần) | H92: 27423542168 | I92: 001 | J92: Trái tim | K92: =_xlfn.CONCAT(E92," ",G92," ",J92) -> Bộ Chăn ga Xơ đũi 4CT (ga phủ, chăn chần) Trái tim | L92: =_xlfn.XLOOKUP(M92,'0. Mã Supplier'!$B:$B,'0. Mã Supplier'!$C:$C,0) -> SUVN0001 | M92: HUY HOÀNG NAM | O92: 0 | P92: 0 | Q92: 0 | R92: 0 | S92: 0 | V92: 0 | Y92: 5 | AA92: 0 | AB92: 207900 | AC92: =AB92*1.08 -> 224532
B93: =D93&F93 -> SET001 | C93: =_xlfn.CONCAT(D93,F93,I93) -> SET001002 | D93: SET | E93: Bộ Chăn ga | F93: 001 | G93: Xơ đũi 4CT (ga phủ, chăn chần) | H93: 27423542168 | I93: 002 | J93: Gấu, lá cây | K93: =_xlfn.CONCAT(E93," ",G93," ",J93) -> Bộ Chăn ga Xơ đũi 4CT (ga phủ, chăn chần) Gấu, lá cây | L93: =_xlfn.XLOOKUP(M93,'0. Mã Supplier'!$B:$B,'0. Mã Supplier'!$C:$C,0) -> SUVN0001 | M93: HUY HOÀNG NAM | O93: 0 | P93: 0 | Q93: 0 | R93: 0 | S93: 0 | V93: 0 | Y93: 5 | AA93: 0 | AB93: 207900 | AC93: =AB93*1.08 -> 224532 | AD93: =AB93/(1-0.55) -> 462000
B94: =D94&F94 -> SET001 | C94: =_xlfn.CONCAT(D94,F94,I94) -> SET001003 | D94: SET | E94: Bộ Chăn ga | F94: 001 | G94: Xơ đũi 4CT (ga phủ, chăn chần) | H94: 27423542168 | I94: 003 | J94: Cừu nâu | K94: =_xlfn.CONCAT(E94," ",G94," ",J94) -> Bộ Chăn ga Xơ đũi 4CT (ga phủ, chăn chần) Cừu nâu | L94: =_xlfn.XLOOKUP(M94,'0. Mã Supplier'!$B:$B,'0. Mã Supplier'!$C:$C,0) -> SUVN0001 | M94: HUY HOÀNG NAM | O94: 0 | P94: 0 | Q94: 0 | R94: 0 | S94: 0 | V94: 0 | Y94: 5 | AA94: 0 | AB94: 207900 | AC94: =AB94*1.08 -> 224532
B95: =D95&F95 -> SET002 | C95: =_xlfn.CONCAT(D95,F95,I95) -> SET002001 | D95: SET | E95: Bộ Chăn ga | F95: 002 | G95: phủ vỏ chăn 4CT | H95: 26173587570 | I95: 001 | J95: Mẫu 1 | K95: =_xlfn.CONCAT(E95," ",G95," ",J95) -> Bộ Chăn ga phủ vỏ chăn 4CT Mẫu 1 | L95: =_xlfn.XLOOKUP(M95,'0. Mã Supplier'!$B:$B,'0. Mã Supplier'!$C:$C,0) -> SUVN0001 | M95: HUY HOÀNG NAM | O95: 0 | P95: 0 | Q95: 0 | R95: 0 | S95: 0 | V95: 0 | Y95: 5 | AA95: 0 | AB95: 199100 | AC95: =AB95*1.08 -> 215028
B96: =D96&F96 -> SET002 | C96: =_xlfn.CONCAT(D96,F96,I96) -> SET002002 | D96: SET | E96: Bộ Chăn ga | F96: 002 | G96: phủ vỏ chăn 4CT | H96: 26173587570 | I96: 002 | J96: Mẫu 2 | K96: =_xlfn.CONCAT(E96," ",G96," ",J96) -> Bộ Chăn ga phủ vỏ chăn 4CT Mẫu 2 | L96: =_xlfn.XLOOKUP(M96,'0. Mã Supplier'!$B:$B,'0. Mã Supplier'!$C:$C,0) -> SUVN0001 | M96: HUY HOÀNG NAM | O96: 0 | P96: 0 | Q96: 0 | R96: 0 | S96: 0 | V96: 0 | Y96: 5 | AA96: 0 | AB96: 199100 | AC96: =AB96*1.08 -> 215028
B97: =D97&F97 -> SET002 | C97: =_xlfn.CONCAT(D97,F97,I97) -> SET002003 | D97: SET | E97: Bộ Chăn ga | F97: 002 | G97: phủ vỏ chăn 4CT | H97: 26173587570 | I97: 003 | J97: Mẫu 3 | K97: =_xlfn.CONCAT(E97," ",G97," ",J97) -> Bộ Chăn ga phủ vỏ chăn 4CT Mẫu 3 | L97: =_xlfn.XLOOKUP(M97,'0. Mã Supplier'!$B:$B,'0. Mã Supplier'!$C:$C,0) -> SUVN0001 | M97: HUY HOÀNG NAM | O97: 0 | P97: 0 | Q97: 0 | R97: 0 | S97: 0 | V97: 0 | Y97: 5 | AA97: 0 | AB97: 199100 | AC97: =AB97*1.08 -> 215028 | AD97: =AB97/(1-0.55) -> 442444.44
B98: =D98&F98 -> SET002 | C98: =_xlfn.CONCAT(D98,F98,I98) -> SET002004 | D98: SET | E98: Bộ Chăn ga | F98: 002 | G98: phủ vỏ chăn 4CT | H98: 26173587570 | I98: 004 | J98: Mẫu 4 | K98: =_xlfn.CONCAT(E98," ",G98," ",J98) -> Bộ Chăn ga phủ vỏ chăn 4CT Mẫu 4 | L98: =_xlfn.XLOOKUP(M98,'0. Mã Supplier'!$B:$B,'0. Mã Supplier'!$C:$C,0) -> SUVN0001 | M98: HUY HOÀNG NAM | O98: 0 | P98: 0 | Q98: 0 | R98: 0 | S98: 0 | V98: 0 | Y98: 5 | AA98: 0 | AB98: 199100 | AC98: =AB98*1.08 -> 215028
B99: =D99&F99 -> SET002 | C99: =_xlfn.CONCAT(D99,F99,I99) -> SET002005 | D99: SET | E99: Bộ Chăn ga | F99: 002 | G99: phủ vỏ chăn 4CT | H99: 26173587570 | I99: 005 | J99: Mẫu 5 | K99: =_xlfn.CONCAT(E99," ",G99," ",J99) -> Bộ Chăn ga phủ vỏ chăn 4CT Mẫu 5 | L99: =_xlfn.XLOOKUP(M99,'0. Mã Supplier'!$B:$B,'0. Mã Supplier'!$C:$C,0) -> SUVN0001 | M99: HUY HOÀNG NAM | O99: 0 | P99: 0 | Q99: 0 | R99: 0 | S99: 0 | V99: 0 | Y99: 5 | AA99: 0 | AB99: 199100 | AC99: =AB99*1.08 -> 215028
B100: =D100&F100 -> SET002 | C100: =_xlfn.CONCAT(D100,F100,I100) -> SET002006 | D100: SET | E100: Bộ Chăn ga | F100: 002 | G100: phủ vỏ chăn 4CT | H100: 26173587570 | I100: 006 | J100: Mẫu 6 | K100: =_xlfn.CONCAT(E100," ",G100," ",J100) -> Bộ Chăn ga phủ vỏ chăn 4CT Mẫu 6 | L100: =_xlfn.XLOOKUP(M100,'0. Mã Supplier'!$B:$B,'0. Mã Supplier'!$C:$C,0) -> SUVN0001 | M100: HUY HOÀNG NAM | O100: 0 | P100: 0 | Q100: 0 | R100: 0 | S100: 0 | V100: 0 | Y100: 5 | AA100: 0 | AB100: 199100 | AC100: =AB100*1.08 -> 215028
B101: =D101&F101 -> SET003 | C101: =_xlfn.CONCAT(D101,F101,I101) -> SET003001 | D101: SET | E101: Bộ Chăn ga | F101: 003 | G101: chun gấu xanh gấu hồng 3CT | H101: 29183296960 | I101: 001 | J101: Gấu xanh 160 x 200 cm | K101: =_xlfn.CONCAT(E101," ",G101," ",J101) -> Bộ Chăn ga chun gấu xanh gấu hồng 3CT Gấu xanh 160 x 200 cm | L101: =_xlfn.XLOOKUP(M101,'0. Mã Supplier'!$B:$B,'0. Mã Supplier'!$C:$C,0) -> SUVN0004 | M101: TEXNAM | O101: 0 | P101: 160 | Q101: 200 | R101: 0 | S101: 0 | V101: 0 | Y101: 5 | AA101: 0 | AB101: 155630 | AC101: =AB101*1.08 -> 168080.4
B102: =D102&F102 -> SET003 | C102: =_xlfn.CONCAT(D102,F102,I102) -> SET003002 | D102: SET | E102: Bộ Chăn ga | F102: 003 | G102: chun gấu xanh gấu hồng 3CT | H102: 29183296960 | I102: 002 | J102: Gấu hồng 160 x 200 cm | K102: =_xlfn.CONCAT(E102," ",G102," ",J102) -> Bộ Chăn ga chun gấu xanh gấu hồng 3CT Gấu hồng 160 x 200 cm | L102: =_xlfn.XLOOKUP(M102,'0. Mã Supplier'!$B:$B,'0. Mã Supplier'!$C:$C,0) -> SUVN0004 | M102: TEXNAM | O102: 0 | P102: 160 | Q102: 200 | R102: 0 | S102: 0 | V102: 0 | Y102: 5 | AA102: 0 | AB102: 155630 | AC102: =AB102*1.08 -> 168080.4 | AD102: =AB102/(1-0.55) -> 345844.44
B103: =D103&F103 -> SET003 | C103: =_xlfn.CONCAT(D103,F103,I103) -> SET003003 | D103: SET | E103: Bộ Chăn ga | F103: 003 | G103: chun gấu xanh gấu hồng 3CT | H103: 29183296960 | I103: 003 | J103: Gấu xanh 180 x 200 cm | K103: =_xlfn.CONCAT(E103," ",G103," ",J103) -> Bộ Chăn ga chun gấu xanh gấu hồng 3CT Gấu xanh 180 x 200 cm | L103: =_xlfn.XLOOKUP(M103,'0. Mã Supplier'!$B:$B,'0. Mã Supplier'!$C:$C,0) -> SUVN0004 | M103: TEXNAM | O103: 0 | P103: 180 | Q103: 200 | R103: 0 | S103: 0 | V103: 0 | Y103: 5 | AA103: 0 | AB103: 163300 | AC103: =AB103*1.08 -> 176364
B104: =D104&F104 -> SET003 | C104: =_xlfn.CONCAT(D104,F104,I104) -> SET003004 | D104: SET | E104: Bộ Chăn ga | F104: 003 | G104: chun gấu xanh gấu hồng 3CT | H104: 29183296960 | I104: 004 | J104: Gấu hồng 180 x 200 cm | K104: =_xlfn.CONCAT(E104," ",G104," ",J104) -> Bộ Chăn ga chun gấu xanh gấu hồng 3CT Gấu hồng 180 x 200 cm | L104: =_xlfn.XLOOKUP(M104,'0. Mã Supplier'!$B:$B,'0. Mã Supplier'!$C:$C,0) -> SUVN0004 | M104: TEXNAM | O104: 0 | P104: 180 | Q104: 200 | R104: 0 | S104: 0 | V104: 0 | Y104: 5 | AA104: 0 | AB104: 163300 | AC104: =AB104*1.08 -> 176364
B105: =D105&F105 -> ACC001 | C105: =_xlfn.CONCAT(D105,F105,I105) -> ACC001001 | D105: ACC | E105: Phụ Kiện | F105: 001 | G105: Everlife Tấm bảo vệ nệm chống thấm | H105: 42956482957 | I105: 001 | J105: Mẫu 1, 80 x 200 cm | K105: =_xlfn.CONCAT(E105," ",G105," ",J105) -> Phụ Kiện Everlife Tấm bảo vệ nệm chống thấm Mẫu 1, 80 x 200 cm | L105: =_xlfn.XLOOKUP(M105,'0. Mã Supplier'!$B:$B,'0. Mã Supplier'!$C:$C,0) -> SUVN0005 | M105: AP WOOD | O105: 0 | P105: 80 | Q105: 200 | R105: 1 | S105: 1.2 | U105: 30 | V105: 30 | W105: 12 | Y105: 5 | AA105: 0 | AB105: 0 | AC105: =AB105*1.08 -> 0
B106: =D106&F106 -> ACC001 | C106: =_xlfn.CONCAT(D106,F106,I106) -> ACC001002 | D106: ACC | E106: Phụ Kiện | F106: 001 | G106: Everlife Tấm bảo vệ nệm chống thấm | H106: 42956482957 | I106: 002 | J106: Mẫu 1, 100 x 200 cm | K106: =_xlfn.CONCAT(E106," ",G106," ",J106) -> Phụ Kiện Everlife Tấm bảo vệ nệm chống thấm Mẫu 1, 100 x 200 cm | L106: =_xlfn.XLOOKUP(M106,'0. Mã Supplier'!$B:$B,'0. Mã Supplier'!$C:$C,0) -> SUVN0005 | M106: AP WOOD | O106: 0 | P106: 100 | Q106: 200 | R106: 1 | S106: 1.2 | U106: 30 | V106: 30 | W106: 12 | Y106: 5 | AA106: 0 | AB106: 0 | AC106: =AB106*1.08 -> 0
B107: =D107&F107 -> ACC001 | C107: =_xlfn.CONCAT(D107,F107,I107) -> ACC001003 | D107: ACC | E107: Phụ Kiện | F107: 001 | G107: Everlife Tấm bảo vệ nệm chống thấm | H107: 42956482957 | I107: 003 | J107: Mẫu 1, 120 x 200 cm | K107: =_xlfn.CONCAT(E107," ",G107," ",J107) -> Phụ Kiện Everlife Tấm bảo vệ nệm chống thấm Mẫu 1, 120 x 200 cm | L107: =_xlfn.XLOOKUP(M107,'0. Mã Supplier'!$B:$B,'0. Mã Supplier'!$C:$C,0) -> SUVN0005 | M107: AP WOOD | O107: 0 | P107: 120 | Q107: 200 | R107: 1 | S107: 1.2 | U107: 30 | V107: 30 | W107: 12 | Y107: 5 | AA107: 0 | AB107: 451000 | AC107: =AB107*1.08 -> 487080
B108: =D108&F108 -> ACC001 | C108: =_xlfn.CONCAT(D108,F108,I108) -> ACC001004 | D108: ACC | E108: Phụ Kiện | F108: 001 | G108: Everlife Tấm bảo vệ nệm chống thấm | H108: 42956482957 | I108: 004 | J108: Mẫu 1, 140 x 200 cm | K108: =_xlfn.CONCAT(E108," ",G108," ",J108) -> Phụ Kiện Everlife Tấm bảo vệ nệm chống thấm Mẫu 1, 140 x 200 cm | L108: =_xlfn.XLOOKUP(M108,'0. Mã Supplier'!$B:$B,'0. Mã Supplier'!$C:$C,0) -> SUVN0005 | M108: AP WOOD | O108: 0 | P108: 140 | Q108: 200 | R108: 1 | S108: 1.2 | U108: 30 | V108: 30 | W108: 12 | Y108: 5 | AA108: 0 | AB108: 0 | AC108: =AB108*1.08 -> 0
B109: =D109&F109 -> ACC001 | C109: =_xlfn.CONCAT(D109,F109,I109) -> ACC001005 | D109: ACC | E109: Phụ Kiện | F109: 001 | G109: Everlife Tấm bảo vệ nệm chống thấm | H109: 42956482957 | I109: 005 | J109: Mẫu 1, 160 x 200 cm | K109: =_xlfn.CONCAT(E109," ",G109," ",J109) -> Phụ Kiện Everlife Tấm bảo vệ nệm chống thấm Mẫu 1, 160 x 200 cm | L109: =_xlfn.XLOOKUP(M109,'0. Mã Supplier'!$B:$B,'0. Mã Supplier'!$C:$C,0) -> SUVN0005 | M109: AP WOOD | O109: 0 | P109: 160 | Q109: 200 | R109: 1 | S109: 1.2 | U109: 30 | V109: 30 | W109: 12 | Y109: 5 | AA109: 0 | AB109: 522500 | AC109: =AB109*1.08 -> 564300 | AD109: =AB109/(1-0.55) -> 1161111.1
B110: =D110&F110 -> ACC001 | C110: =_xlfn.CONCAT(D110,F110,I110) -> ACC001006 | D110: ACC | E110: Phụ Kiện | F110: 001 | G110: Everlife Tấm bảo vệ nệm chống thấm | H110: 42956482957 | I110: 006 | J110: Mẫu 1, 180 x 200 cm | K110: =_xlfn.CONCAT(E110," ",G110," ",J110) -> Phụ Kiện Everlife Tấm bảo vệ nệm chống thấm Mẫu 1, 180 x 200 cm | L110: =_xlfn.XLOOKUP(M110,'0. Mã Supplier'!$B:$B,'0. Mã Supplier'!$C:$C,0) -> SUVN0005 | M110: AP WOOD | O110: 0 | P110: 180 | Q110: 200 | R110: 1 | S110: 1.2 | U110: 30 | V110: 30 | W110: 12 | Y110: 5 | AA110: 0 | AB110: 577500 | AC110: =AB110*1.08 -> 623700
B111: =D111&F111 -> ACC001 | C111: =_xlfn.CONCAT(D111,F111,I111) -> ACC001007 | D111: ACC | E111: Phụ Kiện | F111: 001 | G111: Everlife Tấm bảo vệ nệm chống thấm | H111: 42956482957 | I111: 007 | J111: Mẫu 1, 200 x 200 cm | K111: =_xlfn.CONCAT(E111," ",G111," ",J111) -> Phụ Kiện Everlife Tấm bảo vệ nệm chống thấm Mẫu 1, 200 x 200 cm | L111: =_xlfn.XLOOKUP(M111,'0. Mã Supplier'!$B:$B,'0. Mã Supplier'!$C:$C,0) -> SUVN0005 | M111: AP WOOD | O111: 0 | P111: 200 | Q111: 200 | R111: 1 | S111: 1.2 | U111: 30 | V111: 30 | W111: 12 | Y111: 5 | AA111: 0 | AB111: 0 | AC111: =AB111*1.08 -> 0
B112: =D112&F112 -> ACC001 | C112: =_xlfn.CONCAT(D112,F112,I112) -> ACC001008 | D112: ACC | E112: Phụ Kiện | F112: 001 | G112: Everlife Tấm bảo vệ nệm chống thấm | H112: 42956482957 | I112: 008 | J112: Mẫu 1, 200 x 220 cm | K112: =_xlfn.CONCAT(E112," ",G112," ",J112) -> Phụ Kiện Everlife Tấm bảo vệ nệm chống thấm Mẫu 1, 200 x 220 cm | L112: =_xlfn.XLOOKUP(M112,'0. Mã Supplier'!$B:$B,'0. Mã Supplier'!$C:$C,0) -> SUVN0005 | M112: AP WOOD | O112: 0 | P112: 200 | Q112: 220 | R112: 1 | S112: 1.2 | U112: 30 | V112: 30 | W112: 12 | Y112: 5 | AA112: 0 | AB112: 0 | AC112: =AB112*1.08 -> 0
B113: =D113&F113 -> ACC001 | C113: =_xlfn.CONCAT(D113,F113,I113) -> ACC001009 | D113: ACC | E113: Phụ Kiện | F113: 001 | G113: Everlife Tấm bảo vệ nệm chống thấm | H113: 42956482957 | I113: 009 | J113: Mẫu 2, 80 x 200 cm | K113: =_xlfn.CONCAT(E113," ",G113," ",J113) -> Phụ Kiện Everlife Tấm bảo vệ nệm chống thấm Mẫu 2, 80 x 200 cm | L113: =_xlfn.XLOOKUP(M113,'0. Mã Supplier'!$B:$B,'0. Mã Supplier'!$C:$C,0) -> SUVN0005 | M113: AP WOOD | O113: 0 | P113: 80 | Q113: 200 | R113: 1 | S113: 1.2 | U113: 30 | V113: 30 | W113: 12 | Y113: 5 | AA113: 0 | AB113: 0 | AC113: =AB113*1.08 -> 0
B114: =D114&F114 -> ACC001 | C114: =_xlfn.CONCAT(D114,F114,I114) -> ACC001010 | D114: ACC | E114: Phụ Kiện | F114: 001 | G114: Everlife Tấm bảo vệ nệm chống thấm | H114: 42956482957 | I114: 010 | J114: Mẫu 2, 100 x 200 cm | K114: =_xlfn.CONCAT(E114," ",G114," ",J114) -> Phụ Kiện Everlife Tấm bảo vệ nệm chống thấm Mẫu 2, 100 x 200 cm | L114: =_xlfn.XLOOKUP(M114,'0. Mã Supplier'!$B:$B,'0. Mã Supplier'!$C:$C,0) -> SUVN0005 | M114: AP WOOD | O114: 0 | P114: 100 | Q114: 200 | R114: 1 | S114: 1.2 | U114: 30 | V114: 30 | W114: 12 | Y114: 5 | AA114: 0 | AB114: 0 | AC114: =AB114*1.08 -> 0
B115: =D115&F115 -> ACC001 | C115: =_xlfn.CONCAT(D115,F115,I115) -> ACC001011 | D115: ACC | E115: Phụ Kiện | F115: 001 | G115: Everlife Tấm bảo vệ nệm chống thấm | H115: 42956482957 | I115: 011 | J115: Mẫu 2, 120 x 200 cm | K115: =_xlfn.CONCAT(E115," ",G115," ",J115) -> Phụ Kiện Everlife Tấm bảo vệ nệm chống thấm Mẫu 2, 120 x 200 cm | L115: =_xlfn.XLOOKUP(M115,'0. Mã Supplier'!$B:$B,'0. Mã Supplier'!$C:$C,0) -> SUVN0005 | M115: AP WOOD | O115: 0 | P115: 120 | Q115: 200 | R115: 1 | S115: 1.2 | U115: 30 | V115: 30 | W115: 12 | Y115: 5 | AA115: 0 | AB115: 396000 | AC115: =AB115*1.08 -> 427680
B116: =D116&F116 -> ACC001 | C116: =_xlfn.CONCAT(D116,F116,I116) -> ACC001012 | D116: ACC | E116: Phụ Kiện | F116: 001 | G116: Everlife Tấm bảo vệ nệm chống thấm | H116: 42956482957 | I116: 012 | J116: Mẫu 2, 140 x 200 cm | K116: =_xlfn.CONCAT(E116," ",G116," ",J116) -> Phụ Kiện Everlife Tấm bảo vệ nệm chống thấm Mẫu 2, 140 x 200 cm | L116: =_xlfn.XLOOKUP(M116,'0. Mã Supplier'!$B:$B,'0. Mã Supplier'!$C:$C,0) -> SUVN0005 | M116: AP WOOD | O116: 0 | P116: 140 | Q116: 200 | R116: 1 | S116: 1.2 | U116: 30 | V116: 30 | W116: 12 | Y116: 5 | AA116: 0 | AB116: 0 | AC116: =AB116*1.08 -> 0
...

Sheet 4. Purchasing
A1: PO | B1: Code | C1: Product Description | D1: Supplier code | E1: Supplier | F1: Unit | G1: Qty order | H1: Qty confirm | I1: Cost | J1: Total Cost | K1: Total Cost (VAT) | L1: Date Request | M1: Date Supply confirm | N1: Date Receive | O1: Leadtime | P1: Month | Q1: Year | R1: Goods receipt status | S1: Note | T1: Invoice Date | U1: Payment Terms | V1: Due Date | W1: Due Week | X1: Due Month | Y1: Due Year | Z1: Payment status | AA1: Days Overdue | AB1: Paid Amount | AC1: Payment Date | AD1: Outstanding Amount
A2: PWX-001 | B2: MAT004003 | C2: =VLOOKUP(B2,'1. Master Data'!$C:$K,9,0) -> Nệm Power X Core 120 x 200 x 15 cm | E2: POWER X | F2: Cái | G2: 10 | H2: 10 | I2: =VLOOKUP($B2,'1. Master Data'!$C:$AB,26,0) -> 1527869 | J2: =I2*H2 -> 15278690 | K2: =J2*1.08 -> 16500985 | N2: 45879 | O2: =N2-L2 -> 45879 | P2: =MONTH(N2) -> 8 | Q2: =YEAR(N2) -> 2025 | R2: Nhập kho | T2: 45887 | U2: =VLOOKUP($E2,'0. Mã Supplier'!$B:$F,5,0) -> 180 | V2: =T2+U2 -> 46067 | W2: =WEEKNUM(V2) -> 7 | X2: =IF(V2<>0,MONTH(V2),"") -> 2 | Y2: =YEAR(V2) -> 2026 | AA2: =IF(Z2="yes",0,TODAY()-V2) -> 197 | AB2: =IF(Z2="Yes",K2) -> FALSE | AD2: =IFERROR(K2-AB2,0) -> 16500985
A3: PWX-001 | B3: MAT004004 | C3: =VLOOKUP(B3,'1. Master Data'!$C:$K,9,0) -> Nệm Power X Core 140 x 200 x 15 cm | E3: POWER X | F3: Cái | G3: 4 | H3: 4 | I3: =VLOOKUP($B3,'1. Master Data'!$C:$AB,26,0) -> 1719112 | J3: =I3*H3 -> 6876448.1 | K3: =J3*1.08 -> 7426564 | N3: 45879 | O3: =N3-L3 -> 45879 | P3: =MONTH(N3) -> 8 | Q3: =YEAR(N3) -> 2025 | R3: Nhập kho | T3: 45887 | U3: =VLOOKUP($E3,'0. Mã Supplier'!$B:$F,5,0) -> 180 | V3: =T3+U3 -> 46067 | W3: =WEEKNUM(V3) -> 7 | X3: =IF(V3<>0,MONTH(V3),"") -> 2 | Y3: =YEAR(V3) -> 2026 | AA3: =IF(Z3="yes",0,TODAY()-V3) -> 197 | AB3: =IF(Z3="Yes",K3) -> FALSE | AD3: =IFERROR(K3-AB3,0) -> 7426564
A4: PWX-001 | B4: MAT004005 | C4: =VLOOKUP(B4,'1. Master Data'!$C:$K,9,0) -> Nệm Power X Core 160 x 200 x 15 cm | E4: POWER X | F4: Cái | G4: 56 | H4: 56 | I4: =VLOOKUP($B4,'1. Master Data'!$C:$AB,26,0) -> 1902549.1 | J4: =I4*H4 -> 1.0654275e+08 | K4: =J4*1.08 -> 1.1506617e+08 | N4: 45879 | O4: =N4-L4 -> 45879 | P4: =MONTH(N4) -> 8 | Q4: =YEAR(N4) -> 2025 | R4: Nhập kho | T4: 45887 | U4: =VLOOKUP($E4,'0. Mã Supplier'!$B:$F,5,0) -> 180 | V4: =T4+U4 -> 46067 | W4: =WEEKNUM(V4) -> 7 | X4: =IF(V4<>0,MONTH(V4),"") -> 2 | Y4: =YEAR(V4) -> 2026 | AA4: =IF(Z4="yes",0,TODAY()-V4) -> 197 | AB4: =IF(Z4="Yes",K4) -> FALSE | AD4: =IFERROR(K4-AB4,0) -> 1.1506617e+08
A5: PWX-001 | B5: MAT004006 | C5: =VLOOKUP(B5,'1. Master Data'!$C:$K,9,0) -> Nệm Power X Core 180 x 200 x 15 cm | E5: POWER X | F5: Cái | G5: 44 | H5: 44 | I5: =VLOOKUP($B5,'1. Master Data'!$C:$AB,26,0) -> 2085986.1 | J5: =I5*H5 -> 91783388 | K5: =J5*1.08 -> 99126059 | N5: 45879 | O5: =N5-L5 -> 45879 | P5: =MONTH(N5) -> 8 | Q5: =YEAR(N5) -> 2025 | R5: Nhập kho | T5: 45887 | U5: =VLOOKUP($E5,'0. Mã Supplier'!$B:$F,5,0) -> 180 | V5: =T5+U5 -> 46067 | W5: =WEEKNUM(V5) -> 7 | X5: =IF(V5<>0,MONTH(V5),"") -> 2 | Y5: =YEAR(V5) -> 2026 | AA5: =IF(Z5="yes",0,TODAY()-V5) -> 197 | AB5: =IF(Z5="Yes",K5) -> FALSE | AD5: =IFERROR(K5-AB5,0) -> 99126059
A6: PWX-001 | B6: MAT004008 | C6: =VLOOKUP(B6,'1. Master Data'!$C:$K,9,0) -> Nệm Power X Core 200 x 220 x 15 cm | E6: POWER X | F6: Cái | G6: 6 | H6: 6 | I6: =VLOOKUP($B6,'1. Master Data'!$C:$AB,26,0) -> 2415915.7 | J6: =I6*H6 -> 14495494 | K6: =J6*1.08 -> 15655134 | N6: 45879 | O6: =N6-L6 -> 45879 | P6: =MONTH(N6) -> 8 | Q6: =YEAR(N6) -> 2025 | R6: Nhập kho | T6: 45887 | U6: =VLOOKUP($E6,'0. Mã Supplier'!$B:$F,5,0) -> 180 | V6: =T6+U6 -> 46067 | W6: =WEEKNUM(V6) -> 7 | X6: =IF(V6<>0,MONTH(V6),"") -> 2 | Y6: =YEAR(V6) -> 2026 | AA6: =IF(Z6="yes",0,TODAY()-V6) -> 197 | AB6: =IF(Z6="Yes",K6) -> FALSE | AD6: =IFERROR(K6-AB6,0) -> 15655134
A7: PWX-001 | B7: MAT004005 | C7: =VLOOKUP(B7,'1. Master Data'!$C:$K,9,0) -> Nệm Power X Core 160 x 200 x 15 cm | E7: POWER X | F7: Cái | G7: 1 | H7: 1 | I7: =VLOOKUP($B7,'1. Master Data'!$C:$AB,26,0) -> 1902549.1 | J7: =I7*H7 -> 1902549.1 | K7: =J7*1.08 -> 2054753 | N7: 45879 | O7: =N7-L7 -> 45879 | P7: =MONTH(N7) -> 8 | Q7: =YEAR(N7) -> 2025 | R7: Nhập kho | T7: 45887 | U7: =VLOOKUP($E7,'0. Mã Supplier'!$B:$F,5,0) -> 180 | V7: =T7+U7 -> 46067 | W7: =WEEKNUM(V7) -> 7 | X7: =IF(V7<>0,MONTH(V7),"") -> 2 | Y7: =YEAR(V7) -> 2026 | AA7: =IF(Z7="yes",0,TODAY()-V7) -> 197 | AB7: =IF(Z7="Yes",K7) -> FALSE | AD7: =IFERROR(K7-AB7,0) -> 2054753
A8: PWX-001 | B8: MAT005003 | C8: =VLOOKUP(B8,'1. Master Data'!$C:$K,9,0) -> Nệm Power X Flow 120 x 200 x 22 cm | E8: POWER X | F8: Cái | G8: 1 | H8: 1 | I8: =VLOOKUP($B8,'1. Master Data'!$C:$AB,26,0) -> 2135393.6 | J8: =I8*H8 -> 2135393.6 | K8: =J8*1.08 -> 2306225.1 | N8: 45879 | O8: =N8-L8 -> 45879 | P8: =MONTH(N8) -> 8 | Q8: =YEAR(N8) -> 2025 | R8: Nhập kho | T8: 45887 | U8: =VLOOKUP($E8,'0. Mã Supplier'!$B:$F,5,0) -> 180 | V8: =T8+U8 -> 46067 | W8: =WEEKNUM(V8) -> 7 | X8: =IF(V8<>0,MONTH(V8),"") -> 2 | Y8: =YEAR(V8) -> 2026 | AA8: =IF(Z8="yes",0,TODAY()-V8) -> 197 | AB8: =IF(Z8="Yes",K8) -> FALSE | AD8: =IFERROR(K8-AB8,0) -> 2306225.1
A9: PWX-001 | B9: MAT005004 | C9: =VLOOKUP(B9,'1. Master Data'!$C:$K,9,0) -> Nệm Power X Flow 140 x 200 x 22 cm | E9: POWER X | F9: Cái | G9: 1 | H9: 1 | I9: =VLOOKUP($B9,'1. Master Data'!$C:$AB,26,0) -> 2416195.7 | J9: =I9*H9 -> 2416195.7 | K9: =J9*1.08 -> 2609491.4 | N9: 45879 | O9: =N9-L9 -> 45879 | P9: =MONTH(N9) -> 8 | Q9: =YEAR(N9) -> 2025 | R9: Nhập kho | T9: 45887 | U9: =VLOOKUP($E9,'0. Mã Supplier'!$B:$F,5,0) -> 180 | V9: =T9+U9 -> 46067 | W9: =WEEKNUM(V9) -> 7 | X9: =IF(V9<>0,MONTH(V9),"") -> 2 | Y9: =YEAR(V9) -> 2026 | AA9: =IF(Z9="yes",0,TODAY()-V9) -> 197 | AB9: =IF(Z9="Yes",K9) -> FALSE | AD9: =IFERROR(K9-AB9,0) -> 2609491.4
A10: PWX-001 | B10: MAT005005 | C10: =VLOOKUP(B10,'1. Master Data'!$C:$K,9,0) -> Nệm Power X Flow 160 x 200 x 22 cm | E10: POWER X | F10: Cái | G10: 28 | H10: 28 | I10: =VLOOKUP($B10,'1. Master Data'!$C:$AB,26,0) -> 2696997.8 | J10: =I10*H10 -> 75515940 | K10: =J10*1.08 -> 81557215 | N10: 45879 | O10: =N10-L10 -> 45879 | P10: =MONTH(N10) -> 8 | Q10: =YEAR(N10) -> 2025 | R10: Nhập kho | T10: 45887 | U10: =VLOOKUP($E10,'0. Mã Supplier'!$B:$F,5,0) -> 180 | V10: =T10+U10 -> 46067 | W10: =WEEKNUM(V10) -> 7 | X10: =IF(V10<>0,MONTH(V10),"") -> 2 | Y10: =YEAR(V10) -> 2026 | AA10: =IF(Z10="yes",0,TODAY()-V10) -> 197 | AB10: =IF(Z10="Yes",K10) -> FALSE | AD10: =IFERROR(K10-AB10,0) -> 81557215
A11: PWX-001 | B11: MAT005006 | C11: =VLOOKUP(B11,'1. Master Data'!$C:$K,9,0) -> Nệm Power X Flow 180 x 200 x 22 cm | E11: POWER X | F11: Cái | G11: 25 | H11: 25 | I11: =VLOOKUP($B11,'1. Master Data'!$C:$AB,26,0) -> 2951780 | J11: =I11*H11 -> 73794499 | K11: =J11*1.08 -> 79698059 | N11: 45879 | O11: =N11-L11 -> 45879 | P11: =MONTH(N11) -> 8 | Q11: =YEAR(N11) -> 2025 | R11: Nhập kho | T11: 45887 | U11: =VLOOKUP($E11,'0. Mã Supplier'!$B:$F,5,0) -> 180 | V11: =T11+U11 -> 46067 | W11: =WEEKNUM(V11) -> 7 | X11: =IF(V11<>0,MONTH(V11),"") -> 2 | Y11: =YEAR(V11) -> 2026 | AA11: =IF(Z11="yes",0,TODAY()-V11) -> 197 | AB11: =IF(Z11="Yes",K11) -> FALSE | AD11: =IFERROR(K11-AB11,0) -> 79698059
A12: PWX-001 | B12: MAT005008 | C12: =VLOOKUP(B12,'1. Master Data'!$C:$K,9,0) -> Nệm Power X Flow 200 x 220 x 22 cm | E12: POWER X | F12: Cái | G12: 5 | H12: 5 | I12: =VLOOKUP($B12,'1. Master Data'!$C:$AB,26,0) -> 3367365.7 | J12: =I12*H12 -> 16836828 | K12: =J12*1.08 -> 18183775 | N12: 45879 | O12: =N12-L12 -> 45879 | P12: =MONTH(N12) -> 8 | Q12: =YEAR(N12) -> 2025 | R12: Nhập kho | T12: 45887 | U12: =VLOOKUP($E12,'0. Mã Supplier'!$B:$F,5,0) -> 180 | V12: =T12+U12 -> 46067 | W12: =WEEKNUM(V12) -> 7 | X12: =IF(V12<>0,MONTH(V12),"") -> 2 | Y12: =YEAR(V12) -> 2026 | AA12: =IF(Z12="yes",0,TODAY()-V12) -> 197 | AB12: =IF(Z12="Yes",K12) -> FALSE | AD12: =IFERROR(K12-AB12,0) -> 18183775
A13: PWX-001 | B13: MAT005005 | C13: =VLOOKUP(B13,'1. Master Data'!$C:$K,9,0) -> Nệm Power X Flow 160 x 200 x 22 cm | E13: POWER X | F13: Cái | G13: 1 | H13: 1 | I13: =VLOOKUP($B13,'1. Master Data'!$C:$AB,26,0) -> 2696997.8 | J13: =I13*H13 -> 2696997.8 | K13: =J13*1.08 -> 2912757.7 | N13: 45879 | O13: =N13-L13 -> 45879 | P13: =MONTH(N13) -> 8 | Q13: =YEAR(N13) -> 2025 | R13: Nhập kho | T13: 45887 | U13: =VLOOKUP($E13,'0. Mã Supplier'!$B:$F,5,0) -> 180 | V13: =T13+U13 -> 46067 | W13: =WEEKNUM(V13) -> 7 | X13: =IF(V13<>0,MONTH(V13),"") -> 2 | Y13: =YEAR(V13) -> 2026 | AA13: =IF(Z13="yes",0,TODAY()-V13) -> 197 | AB13: =IF(Z13="Yes",K13) -> FALSE | AD13: =IFERROR(K13-AB13,0) -> 2912757.7
... A27: PWX-001 | B27: PIL003001 | C27: =VLOOKUP(B27,'1. Master Data'!$C:$K,9,0) -> Gối Power X Matrix 40 x 60 x 12 cm | E27: POWER X | F27: Cái | G27: 50 | H27: 50 | I27: =VLOOKUP($B27,'1. Master Data'!$C:$AB,26,0) -> 473497.38 | J27: =I27*H27 -> 23674869 | K27: =J27*1.08 -> 25568858 | N27: 45879 | O27: =N27-L27 -> 45879 | P27: =MONTH(N27) -> 8 | Q27: =YEAR(N27) -> 2025 | R27: Nhập kho | T27: 45887 | U27: =VLOOKUP($E27,'0. Mã Supplier'!$B:$F,5,0) -> 180 | V27: =T27+U27 -> 46067 | W27: =WEEKNUM(V27) -> 7 | X27: =IF(V27<>0,MONTH(V27),"") -> 2 | Y27: =YEAR(V27) -> 2026 | AA27: =IF(Z27="yes",0,TODAY()-V27) -> 197 | AB27: =IF(Z27="Yes",K27) -> FALSE | AD27: =IFERROR(K27-AB27,0) -> 25568858
A28: HHN-001 | B28: BLA002001 | C28: =VLOOKUP(B28,'1. Master Data'!$C:$K,9,0) -> Chăn Tencel 60s Xanh dương pastel 200 x 230 cm | D28: =VLOOKUP(E28,'0. Mã Supplier'!$B:$C,2,0) -> SUVN0001 | E28: HUY HOÀNG NAM | F28: Cái | G28: 4 | H28: 4 | I28: =VLOOKUP($B28,'1. Master Data'!$C:$AB,26,0) -> 429000 | J28: =I28*H28 -> 1716000 | K28: =J28*1.08 -> 1853280 | N28: 45658 | O28: =N28-L28 -> 45658 | P28: =MONTH(N28) -> 1 | Q28: =YEAR(N28) -> 2025 | R28: Nhập kho | T28: 45709 | U28: =VLOOKUP($E28,'0. Mã Supplier'!$B:$F,5,0) -> 0 | V28: =T28+U28 -> 45709 | W28: =WEEKNUM(V28) -> 8 | X28: =IF(V28<>0,MONTH(V28),"") -> 2 | Y28: =YEAR(V28) -> 2025 | Z28: Yes | AA28: =IF(Z28="yes",0,TODAY()-V28) -> 0 | AB28: =IF(Z28="Yes",K28) -> 1853280 | AD28: =IFERROR(K28-AB28,0) -> 0
A29: HHN-001 | B29: BLA002002 | C29: =VLOOKUP(B29,'1. Master Data'!$C:$K,9,0) -> Chăn Tencel 60s Hồng pastel 200 x 230 cm | D29: =VLOOKUP(E29,'0. Mã Supplier'!$B:$C,2,0) -> SUVN0001 | E29: HUY HOÀNG NAM | F29: Cái | G29: 7 | H29: 7 | I29: =VLOOKUP($B29,'1. Master Data'!$C:$AB,26,0) -> 429000 | J29: =I29*H29 -> 3003000 | K29: =J29*1.08 -> 3243240 | N29: 45658 | O29: =N29-L29 -> 45658 | P29: =MONTH(N29) -> 1 | Q29: =YEAR(N29) -> 2025 | R29: Nhập kho | T29: 45709 | U29: =VLOOKUP($E29,'0. Mã Supplier'!$B:$F,5,0) -> 0 | V29: =T29+U29 -> 45709 | W29: =WEEKNUM(V29) -> 8 | X29: =IF(V29<>0,MONTH(V29),"") -> 2 | Y29: =YEAR(V29) -> 2025 | Z29: Yes | AA29: =IF(Z29="yes",0,TODAY()-V29) -> 0 | AB29: =IF(Z29="Yes",K29) -> 3243240 | AD29: =IFERROR(K29-AB29,0) -> 0
A30: HHN-001 | B30: BLA002003 | C30: =VLOOKUP(B30,'1. Master Data'!$C:$K,9,0) -> Chăn Tencel 60s Xanh rêu pastel 200 x 230 cm | D30: =VLOOKUP(E30,'0. Mã Supplier'!$B:$C,2,0) -> SUVN0001 | E30: HUY HOÀNG NAM | F30: Cái | G30: 1 | H30: 1 | I30: =VLOOKUP($B30,'1. Master Data'!$C:$AB,26,0) -> 429000 | J30: =I30*H30 -> 429000 | K30: =J30*1.08 -> 463320 | N30: 45658 | O30: =N30-L30 -> 45658 | P30: =MONTH(N30) -> 1 | Q30: =YEAR(N30) -> 2025 | R30: Nhập kho | T30: 45709 | U30: =VLOOKUP($E30,'0. Mã Supplier'!$B:$F,5,0) -> 0 | V30: =T30+U30 -> 45709 | W30: =WEEKNUM(V30) -> 8 | X30: =IF(V30<>0,MONTH(V30),"") -> 2 | Y30: =YEAR(V30) -> 2025 | Z30: Yes | AA30: =IF(Z30="yes",0,TODAY()-V30) -> 0 | AB30: =IF(Z30="Yes",K30) -> 463320 | AD30: =IFERROR(K30-AB30,0) -> 0
A31: HHN-001 | B31: BLA002004 | C31: =VLOOKUP(B31,'1. Master Data'!$C:$K,9,0) -> Chăn Tencel 60s Hồng trắng pastel 200 x 230 cm | D31: =VLOOKUP(E31,'0. Mã Supplier'!$B:$C,2,0) -> SUVN0001 | E31: HUY HOÀNG NAM | F31: Cái | G31: 1 | H31: 1 | I31: =VLOOKUP($B31,'1. Master Data'!$C:$AB,26,0) -> 429000 | J31: =I31*H31 -> 429000 | K31: =J31*1.08 -> 463320 | N31: 45658 | O31: =N31-L31 -> 45658 | P31: =MONTH(N31) -> 1 | Q31: =YEAR(N31) -> 2025 | R31: Nhập kho | T31: 45709 | U31: =VLOOKUP($E31,'0. Mã Supplier'!$B:$F,5,0) -> 0 | V31: =T31+U31 -> 45709 | W31: =WEEKNUM(V31) -> 8 | X31: =IF(V31<>0,MONTH(V31),"") -> 2 | Y31: =YEAR(V31) -> 2025 | Z31: Yes | AA31: =IF(Z31="yes",0,TODAY()-V31) -> 0 | AB31: =IF(Z31="Yes",K31) -> 463320 | AD31: =IFERROR(K31-AB31,0) -> 0
A32: HHN-001 | B32: BLA002005 | C32: =VLOOKUP(B32,'1. Master Data'!$C:$K,9,0) -> Chăn Tencel 60s Xám lông chuột 200 x 230 cm | D32: =VLOOKUP(E32,'0. Mã Supplier'!$B:$C,2,0) -> SUVN0001 | E32: HUY HOÀNG NAM | F32: Cái | G32: 1 | H32: 1 | I32: =VLOOKUP($B32,'1. Master Data'!$C:$AB,26,0) -> 429000 | J32: =I32*H32 -> 429000 | K32: =J32*1.08 -> 463320 | N32: 45658 | O32: =N32-L32 -> 45658 | P32: =MONTH(N32) -> 1 | Q32: =YEAR(N32) -> 2025 | R32: Nhập kho | T32: 45709 | U32: =VLOOKUP($E32,'0. Mã Supplier'!$B:$F,5,0) -> 0 | V32: =T32+U32 -> 45709 | W32: =WEEKNUM(V32) -> 8 | X32: =IF(V32<>0,MONTH(V32),"") -> 2 | Y32: =YEAR(V32) -> 2025 | Z32: Yes | AA32: =IF(Z32="yes",0,TODAY()-V32) -> 0 | AB32: =IF(Z32="Yes",K32) -> 463320 | AD32: =IFERROR(K32-AB32,0) -> 0
A33: HHN-001 | B33: BLA002006 | C33: =VLOOKUP(B33,'1. Master Data'!$C:$K,9,0) -> Chăn Tencel 60s Xám xanh dương 200 x 230 cm | D33: =VLOOKUP(E33,'0. Mã Supplier'!$B:$C,2,0) -> SUVN0001 | E33: HUY HOÀNG NAM | F33: Cái | G33: 6 | H33: 6 | I33: =VLOOKUP($B33,'1. Master Data'!$C:$AB,26,0) -> 429000 | J33: =I33*H33 -> 2574000 | K33: =J33*1.08 -> 2779920 | N33: 45658 | O33: =N33-L33 -> 45658 | P33: =MONTH(N33) -> 1 | Q33: =YEAR(N33) -> 2025 | R33: Nhập kho | T33: 45709 | U33: =VLOOKUP($E33,'0. Mã Supplier'!$B:$F,5,0) -> 0 | V33: =T33+U33 -> 45709 | W33: =WEEKNUM(V33) -> 8 | X33: =IF(V33<>0,MONTH(V33),"") -> 2 | Y33: =YEAR(V33) -> 2025 | Z33: Yes | AA33: =IF(Z33="yes",0,TODAY()-V33) -> 0 | AB33: =IF(Z33="Yes",K33) -> 2779920 | AD33: =IFERROR(K33-AB33,0) -> 0
A34: HHN-001 | B34: BLA001001 | C34: =VLOOKUP(B34,'1. Master Data'!$C:$K,9,0) -> Chăn Lạnh 4.8 Xanh dương pastel 200 x 230 cm, Vải cooling mát lạnh | D34: =VLOOKUP(E34,'0. Mã Supplier'!$B:$C,2,0) -> SUVN0001 | E34: HUY HOÀNG NAM | F34: Cái | G34: 5 | H34: 5 | I34: =VLOOKUP($B34,'1. Master Data'!$C:$AB,26,0) -> 280000 | J34: =I34*H34 -> 1400000 | K34: =J34*1.08 -> 1512000 | N34: 45658 | O34: =N34-L34 -> 45658 | P34: =MONTH(N34) -> 1 | Q34: =YEAR(N34) -> 2025 | R34: Nhập kho | T34: 45709 | U34: =VLOOKUP($E34,'0. Mã Supplier'!$B:$F,5,0) -> 0 | V34: =T34+U34 -> 45709 | W34: =WEEKNUM(V34) -> 8 | X34: =IF(V34<>0,MONTH(V34),"") -> 2 | Y34: =YEAR(V34) -> 2025 | Z34: Yes | AA34: =IF(Z34="yes",0,TODAY()-V34) -> 0 | AB34: =IF(Z34="Yes",K34) -> 1512000 | AD34: =IFERROR(K34-AB34,0) -> 0
A35: HHN-001 | B35: BLA001002 | C35: =VLOOKUP(B35,'1. Master Data'!$C:$K,9,0) -> Chăn Lạnh 4.8 Xám pastel 200 x 230 cm, Vải cooling mát lạnh | D35: =VLOOKUP(E35,'0. Mã Supplier'!$B:$C,2,0) -> SUVN0001 | E35: HUY HOÀNG NAM | F35: Cái | G35: 3 | H35: 3 | I35: =VLOOKUP($B35,'1. Master Data'!$C:$AB,26,0) -> 280000 | J35: =I35*H35 -> 840000 | K35: =J35*1.08 -> 907200 | N35: 45658 | O35: =N35-L35 -> 45658 | P35: =MONTH(N35) -> 1 | Q35: =YEAR(N35) -> 2025 | R35: Nhập kho | T35: 45709 | U35: =VLOOKUP($E35,'0. Mã Supplier'!$B:$F,5,0) -> 0 | V35: =T35+U35 -> 45709 | W35: =WEEKNUM(V35) -> 8 | X35: =IF(V35<>0,MONTH(V35),"") -> 2 | Y35: =YEAR(V35) -> 2025 | Z35: Yes | AA35: =IF(Z35="yes",0,TODAY()-V35) -> 0 | AB35: =IF(Z35="Yes",K35) -> 907200 | AD35: =IFERROR(K35-AB35,0) -> 0
A36: HHN-001 | B36: BLA001003 | C36: =VLOOKUP(B36,'1. Master Data'!$C:$K,9,0) -> Chăn Lạnh 4.8 Tím hoa cà 200 x 230 cm, Vải cooling mát lạnh | D36: =VLOOKUP(E36,'0. Mã Supplier'!$B:$C,2,0) -> SUVN0001 | E36: HUY HOÀNG NAM | F36: Cái | G36: 7 | H36: 7 | I36: =VLOOKUP($B36,'1. Master Data'!$C:$AB,26,0) -> 280000 | J36: =I36*H36 -> 1960000 | K36: =J36*1.08 -> 2116800 | N36: 45658 | O36: =N36-L36 -> 45658 | P36: =MONTH(N36) -> 1 | Q36: =YEAR(N36) -> 2025 | R36: Nhập kho | T36: 45709 | U36: =VLOOKUP($E36,'0. Mã Supplier'!$B:$F,5,0) -> 0 | V36: =T36+U36 -> 45709 | W36: =WEEKNUM(V36) -> 8 | X36: =IF(V36<>0,MONTH(V36),"") -> 2 | Y36: =YEAR(V36) -> 2025 | Z36: Yes | AA36: =IF(Z36="yes",0,TODAY()-V36) -> 0 | AB36: =IF(Z36="Yes",K36) -> 2116800 | AD36: =IFERROR(K36-AB36,0) -> 0
A37: HHN-001 | B37: BLA001005 | C37: =VLOOKUP(B37,'1. Master Data'!$C:$K,9,0) -> Chăn Lạnh 4.8 Xanh dương xám 200 x 230 cm, Vải cooling mát lạnh | D37: =VLOOKUP(E37,'0. Mã Supplier'!$B:$C,2,0) -> SUVN0001 | E37: HUY HOÀNG NAM | F37: Cái | G37: 1 | H37: 1 | I37: =VLOOKUP($B37,'1. Master Data'!$C:$AB,26,0) -> 280000 | J37: =I37*H37 -> 280000 | K37: =J37*1.08 -> 302400 | N37: 45658 | O37: =N37-L37 -> 45658 | P37: =MONTH(N37) -> 1 | Q37: =YEAR(N37) -> 2025 | R37: Nhập kho | T37: 45709 | U37: =VLOOKUP($E37,'0. Mã Supplier'!$B:$F,5,0) -> 0 | V37: =T37+U37 -> 45709 | W37: =WEEKNUM(V37) -> 8 | X37: =IF(V37<>0,MONTH(V37),"") -> 2 | Y37: =YEAR(V37) -> 2025 | Z37: Yes | AA37: =IF(Z37="yes",0,TODAY()-V37) -> 0 | AB37: =IF(Z37="Yes",K37) -> 302400 | AD37: =IFERROR(K37-AB37,0) -> 0
A38: HHN-001 | B38: BLA001004 | C38: =VLOOKUP(B38,'1. Master Data'!$C:$K,9,0) -> Chăn Lạnh 4.8 Xanh lá pastel 200 x 230 cm, Vải cooling mát lạnh | D38: =VLOOKUP(E38,'0. Mã Supplier'!$B:$C,2,0) -> SUVN0001 | E38: HUY HOÀNG NAM | F38: Cái | G38: 4 | H38: 4 | I38: =VLOOKUP($B38,'1. Master Data'!$C:$AB,26,0) -> 280000 | J38: =I38*H38 -> 1120000 | K38: =J38*1.08 -> 1209600 | N38: 45658 | O38: =N38-L38 -> 45658 | P38: =MONTH(N38) -> 1 | Q38: =YEAR(N38) -> 2025 | R38: Nhập kho | T38: 45709 | U38: =VLOOKUP($E38,'0. Mã Supplier'!$B:$F,5,0) -> 0 | V38: =T38+U38 -> 45709 | W38: =WEEKNUM(V38) -> 8 | X38: =IF(V38<>0,MONTH(V38),"") -> 2 | Y38: =YEAR(V38) -> 2025 | Z38: Yes | AA38: =IF(Z38="yes",0,TODAY()-V38) -> 0 | AB38: =IF(Z38="Yes",K38) -> 1209600 | AD38: =IFERROR(K38-AB38,0) -> 0
A39: HHN-001 | B39: SET001001 | C39: =VLOOKUP(B39,'1. Master Data'!$C:$K,9,0) -> Bộ Chăn ga Xơ đũi 4CT (ga phủ, chăn chần) Trái tim | D39: =VLOOKUP(E39,'0. Mã Supplier'!$B:$C,2,0) -> SUVN0001 | E39: HUY HOÀNG NAM | F39: Bộ | G39: 13 | H39: 13 | I39: =VLOOKUP($B39,'1. Master Data'!$C:$AB,26,0) -> 207900 | J39: =I39*H39 -> 2702700 | K39: =J39*1.08 -> 2918916 | N39: 45658 | O39: =N39-L39 -> 45658 | P39: =MONTH(N39) -> 1 | Q39: =YEAR(N39) -> 2025 | R39: Nhập kho | T39: 45709 | U39: =VLOOKUP($E39,'0. Mã Supplier'!$B:$F,5,0) -> 0 | V39: =T39+U39 -> 45709 | W39: =WEEKNUM(V39) -> 8 | X39: =IF(V39<>0,MONTH(V39),"") -> 2 | Y39: =YEAR(V39) -> 2025 | Z39: Yes | AA39: =IF(Z39="yes",0,TODAY()-V39) -> 0 | AB39: =IF(Z39="Yes",K39) -> 2918916 | AD39: =IFERROR(K39-AB39,0) -> 0
... A69: HHN-003 | B69: SET002002 | C69: =VLOOKUP(B69,'1. Master Data'!$C:$K,9,0) -> Bộ Chăn ga phủ vỏ chăn 4CT Mẫu 2 | D69: =VLOOKUP(E69,'0. Mã Supplier'!$B:$C,2,0) -> SUVN0001 | E69: HUY HOÀNG NAM | F69: Bộ | G69: 3 | H69: 3 | I69: =VLOOKUP($B69,'1. Master Data'!$C:$AB,26,0) -> 199100 | J69: =I69*H69 -> 597300 | K69: =J69*1.08 -> 645084 | N69: 45717 | O69: =N69-L69 -> 45717 | P69: =MONTH(N69) -> 3 | Q69: =YEAR(N69) -> 2025 | R69: Nhập kho | T69: 45734 | U69: =VLOOKUP($E69,'0. Mã Supplier'!$B:$F,5,0) -> 0 | V69: =T69+U69 -> 45734 | W69: =WEEKNUM(V69) -> 12 | X69: =IF(V69<>0,MONTH(V69),"") -> 3 | Y69: =YEAR(V69) -> 2025 | Z69: Yes | AA69: =IF(Z69="yes",0,TODAY()-V69) -> 0 | AB69: =IF(Z69="Yes",K69) -> 645084 | AD69: =IFERROR(K69-AB69,0) -> 0
A70: HHN-004 | B70: BLA001001 | C70: =VLOOKUP(B70,'1. Master Data'!$C:$K,9,0) -> Chăn Lạnh 4.8 Xanh dương pastel 200 x 230 cm, Vải cooling mát lạnh | D70: =VLOOKUP(E70,'0. Mã Supplier'!$B:$C,2,0) -> SUVN0001 | E70: HUY HOÀNG NAM | F70: Cái | G70: 10 | H70: 10 | I70: =VLOOKUP($B70,'1. Master Data'!$C:$AB,26,0) -> 280000 | J70: =I70*H70 -> 2800000 | N70: 45748 | O70: =N70-L70 -> 45748 | P70: =MONTH(N70) -> 4 | Q70: =YEAR(N70) -> 2025 | R70: Nhập kho | T70: 45889 | U70: =VLOOKUP($E70,'0. Mã Supplier'!$B:$F,5,0) -> 0 | V70: =T70+U70 -> 45889 | W70: =WEEKNUM(V70) -> 34 | X70: =IF(V70<>0,MONTH(V70),"") -> 8 | Y70: =YEAR(V70) -> 2025 | AA70: =IF(Z70="yes",0,TODAY()-V70) -> 375 | AB70: =IF(Z70="Yes",K70) -> FALSE | AD70: =IFERROR(K70-AB70,0) -> 0
A71: HHN-004 | B71: BLA001002 | C71: =VLOOKUP(B71,'1. Master Data'!$C:$K,9,0) -> Chăn Lạnh 4.8 Xám pastel 200 x 230 cm, Vải cooling mát lạnh | D71: =VLOOKUP(E71,'0. Mã Supplier'!$B:$C,2,0) -> SUVN0001 | E71: HUY HOÀNG NAM | F71: Cái | G71: 10 | H71: 10 | I71: =VLOOKUP($B71,'1. Master Data'!$C:$AB,26,0) -> 280000 | J71: =I71*H71 -> 2800000 | N71: 45748 | O71: =N71-L71 -> 45748 | P71: =MONTH(N71) -> 4 | Q71: =YEAR(N71) -> 2025 | R71: Nhập kho | T71: 45889 | U71: =VLOOKUP($E71,'0. Mã Supplier'!$B:$F,5,0) -> 0 | V71: =T71+U71 -> 45889 | W71: =WEEKNUM(V71) -> 34 | X71: =IF(V71<>0,MONTH(V71),"") -> 8 | Y71: =YEAR(V71) -> 2025 | AA71: =IF(Z71="yes",0,TODAY()-V71) -> 375 | AB71: =IF(Z71="Yes",K71) -> FALSE | AD71: =IFERROR(K71-AB71,0) -> 0
A72: HHN-004 | B72: BLA001002 | C72: =VLOOKUP(B72,'1. Master Data'!$C:$K,9,0) -> Chăn Lạnh 4.8 Xám pastel 200 x 230 cm, Vải cooling mát lạnh | D72: =VLOOKUP(E72,'0. Mã Supplier'!$B:$C,2,0) -> SUVN0001 | E72: HUY HOÀNG NAM | F72: Cái | G72: 20 | H72: 20 | I72: =VLOOKUP($B72,'1. Master Data'!$C:$AB,26,0) -> 280000 | J72: =I72*H72 -> 5600000 | N72: 45748 | O72: =N72-L72 -> 45748 | P72: =MONTH(N72) -> 4 | Q72: =YEAR(N72) -> 2025 | R72: Nhập kho | T72: 45889 | U72: =VLOOKUP($E72,'0. Mã Supplier'!$B:$F,5,0) -> 0 | V72: =T72+U72 -> 45889 | W72: =WEEKNUM(V72) -> 34 | X72: =IF(V72<>0,MONTH(V72),"") -> 8 | Y72: =YEAR(V72) -> 2025 | AA72: =IF(Z72="yes",0,TODAY()-V72) -> 375 | AB72: =IF(Z72="Yes",K72) -> FALSE | AD72: =IFERROR(K72-AB72,0) -> 0
A73: HHN-004 | B73: BLA001003 | C73: =VLOOKUP(B73,'1. Master Data'!$C:$K,9,0) -> Chăn Lạnh 4.8 Tím hoa cà 200 x 230 cm, Vải cooling mát lạnh | D73: =VLOOKUP(E73,'0. Mã Supplier'!$B:$C,2,0) -> SUVN0001 | E73: HUY HOÀNG NAM | F73: Cái | G73: 5 | H73: 5 | I73: =VLOOKUP($B73,'1. Master Data'!$C:$AB,26,0) -> 280000 | J73: =I73*H73 -> 1400000 | N73: 45748 | O73: =N73-L73 -> 45748 | P73: =MONTH(N73) -> 4 | Q73: =YEAR(N73) -> 2025 | R73: Nhập kho | T73: 45889 | U73: =VLOOKUP($E73,'0. Mã Supplier'!$B:$F,5,0) -> 0 | V73: =T73+U73 -> 45889 | W73: =WEEKNUM(V73) -> 34 | X73: =IF(V73<>0,MONTH(V73),"") -> 8 | Y73: =YEAR(V73) -> 2025 | AA73: =IF(Z73="yes",0,TODAY()-V73) -> 375 | AB73: =IF(Z73="Yes",K73) -> FALSE | AD73: =IFERROR(K73-AB73,0) -> 0
A74: HHN-004 | B74: BLA001004 | C74: =VLOOKUP(B74,'1. Master Data'!$C:$K,9,0) -> Chăn Lạnh 4.8 Xanh lá pastel 200 x 230 cm, Vải cooling mát lạnh | D74: =VLOOKUP(E74,'0. Mã Supplier'!$B:$C,2,0) -> SUVN0001 | E74: HUY HOÀNG NAM | F74: Cái | G74: 5 | H74: 5 | I74: =VLOOKUP($B74,'1. Master Data'!$C:$AB,26,0) -> 280000 | J74: =I74*H74 -> 1400000 | N74: 45748 | O74: =N74-L74 -> 45748 | P74: =MONTH(N74) -> 4 | Q74: =YEAR(N74) -> 2025 | R74: Nhập kho | T74: 45889 | U74: =VLOOKUP($E74,'0. Mã Supplier'!$B:$F,5,0) -> 0 | V74: =T74+U74 -> 45889 | W74: =WEEKNUM(V74) -> 34 | X74: =IF(V74<>0,MONTH(V74),"") -> 8 | Y74: =YEAR(V74) -> 2025 | AA74: =IF(Z74="yes",0,TODAY()-V74) -> 375 | AB74: =IF(Z74="Yes",K74) -> FALSE | AD74: =IFERROR(K74-AB74,0) -> 0
A75: HHN-004 | B75: SET001001 | C75: =VLOOKUP(B75,'1. Master Data'!$C:$K,9,0) -> Bộ Chăn ga Xơ đũi 4CT (ga phủ, chăn chần) Trái tim | D75: =VLOOKUP(E75,'0. Mã Supplier'!$B:$C,2,0) -> SUVN0001 | E75: HUY HOÀNG NAM | F75: Bộ | G75: 10 | H75: 10 | I75: =VLOOKUP($B75,'1. Master Data'!$C:$AB,26,0) -> 207900 | J75: =I75*H75 -> 2079000 | N75: 45748 | O75: =N75-L75 -> 45748 | P75: =MONTH(N75) -> 4 | Q75: =YEAR(N75) -> 2025 | R75: Nhập kho | T75: 45889 | U75: =VLOOKUP($E75,'0. Mã Supplier'!$B:$F,5,0) -> 0 | V75: =T75+U75 -> 45889 | W75: =WEEKNUM(V75) -> 34 | X75: =IF(V75<>0,MONTH(V75),"") -> 8 | Y75: =YEAR(V75) -> 2025 | AA75: =IF(Z75="yes",0,TODAY()-V75) -> 375 | AB75: =IF(Z75="Yes",K75) -> FALSE | AD75: =IFERROR(K75-AB75,0) -> 0
A76: HHN-004 | B76: SET002001 | C76: =VLOOKUP(B76,'1. Master Data'!$C:$K,9,0) -> Bộ Chăn ga phủ vỏ chăn 4CT Mẫu 1 | D76: =VLOOKUP(E76,'0. Mã Supplier'!$B:$C,2,0) -> SUVN0001 | E76: HUY HOÀNG NAM | F76: Bộ | G76: 2 | H76: 2 | I76: =VLOOKUP($B76,'1. Master Data'!$C:$AB,26,0) -> 199100 | J76: =I76*H76 -> 398200 | N76: 45748 | O76: =N76-L76 -> 45748 | P76: =MONTH(N76) -> 4 | Q76: =YEAR(N76) -> 2025 | R76: Nhập kho | T76: 45889 | U76: =VLOOKUP($E76,'0. Mã Supplier'!$B:$F,5,0) -> 0 | V76: =T76+U76 -> 45889 | W76: =WEEKNUM(V76) -> 34 | X76: =IF(V76<>0,MONTH(V76),"") -> 8 | Y76: =YEAR(V76) -> 2025 | AA76: =IF(Z76="yes",0,TODAY()-V76) -> 375 | AB76: =IF(Z76="Yes",K76) -> FALSE | AD76: =IFERROR(K76-AB76,0) -> 0
A77: HHN-004 | B77: SET002002 | C77: =VLOOKUP(B77,'1. Master Data'!$C:$K,9,0) -> Bộ Chăn ga phủ vỏ chăn 4CT Mẫu 2 | D77: =VLOOKUP(E77,'0. Mã Supplier'!$B:$C,2,0) -> SUVN0001 | E77: HUY HOÀNG NAM | F77: Bộ | G77: 3 | H77: 3 | I77: =VLOOKUP($B77,'1. Master Data'!$C:$AB,26,0) -> 199100 | J77: =I77*H77 -> 597300 | N77: 45748 | O77: =N77-L77 -> 45748 | P77: =MONTH(N77) -> 4 | Q77: =YEAR(N77) -> 2025 | R77: Nhập kho | T77: 45889 | U77: =VLOOKUP($E77,'0. Mã Supplier'!$B:$F,5,0) -> 0 | V77: =T77+U77 -> 45889 | W77: =WEEKNUM(V77) -> 34 | X77: =IF(V77<>0,MONTH(V77),"") -> 8 | Y77: =YEAR(V77) -> 2025 | AA77: =IF(Z77="yes",0,TODAY()-V77) -> 375 | AB77: =IF(Z77="Yes",K77) -> FALSE | AD77: =IFERROR(K77-AB77,0) -> 0
A78: HHN-004 | B78: SET002003 | C78: =VLOOKUP(B78,'1. Master Data'!$C:$K,9,0) -> Bộ Chăn ga phủ vỏ chăn 4CT Mẫu 3 | D78: =VLOOKUP(E78,'0. Mã Supplier'!$B:$C,2,0) -> SUVN0001 | E78: HUY HOÀNG NAM | F78: Bộ | G78: 3 | H78: 3 | I78: =VLOOKUP($B78,'1. Master Data'!$C:$AB,26,0) -> 199100 | J78: =I78*H78 -> 597300 | N78: 45748 | O78: =N78-L78 -> 45748 | P78: =MONTH(N78) -> 4 | Q78: =YEAR(N78) -> 2025 | R78: Nhập kho | T78: 45889 | U78: =VLOOKUP($E78,'0. Mã Supplier'!$B:$F,5,0) -> 0 | V78: =T78+U78 -> 45889 | W78: =WEEKNUM(V78) -> 34 | X78: =IF(V78<>0,MONTH(V78),"") -> 8 | Y78: =YEAR(V78) -> 2025 | AA78: =IF(Z78="yes",0,TODAY()-V78) -> 375 | AB78: =IF(Z78="Yes",K78) -> FALSE | AD78: =IFERROR(K78-AB78,0) -> 0
A79: HHN-004 | B79: SET002004 | C79: =VLOOKUP(B79,'1. Master Data'!$C:$K,9,0) -> Bộ Chăn ga phủ vỏ chăn 4CT Mẫu 4 | D79: =VLOOKUP(E79,'0. Mã Supplier'!$B:$C,2,0) -> SUVN0001 | E79: HUY HOÀNG NAM | F79: Bộ | G79: 2 | H79: 2 | I79: =VLOOKUP($B79,'1. Master Data'!$C:$AB,26,0) -> 199100 | J79: =I79*H79 -> 398200 | N79: 45748 | O79: =N79-L79 -> 45748 | P79: =MONTH(N79) -> 4 | Q79: =YEAR(N79) -> 2025 | R79: Nhập kho | T79: 45889 | U79: =VLOOKUP($E79,'0. Mã Supplier'!$B:$F,5,0) -> 0 | V79: =T79+U79 -> 45889 | W79: =WEEKNUM(V79) -> 34 | X79: =IF(V79<>0,MONTH(V79),"") -> 8 | Y79: =YEAR(V79) -> 2025 | AA79: =IF(Z79="yes",0,TODAY()-V79) -> 375 | AB79: =IF(Z79="Yes",K79) -> FALSE | AD79: =IFERROR(K79-AB79,0) -> 0
A80: HHN-004 | B80: SET002006 | C80: =VLOOKUP(B80,'1. Master Data'!$C:$K,9,0) -> Bộ Chăn ga phủ vỏ chăn 4CT Mẫu 6 | D80: =VLOOKUP(E80,'0. Mã Supplier'!$B:$C,2,0) -> SUVN0001 | E80: HUY HOÀNG NAM | F80: Bộ | G80: 5 | H80: 5 | I80: =VLOOKUP($B80,'1. Master Data'!$C:$AB,26,0) -> 199100 | J80: =I80*H80 -> 995500 | N80: 45748 | O80: =N80-L80 -> 45748 | P80: =MONTH(N80) -> 4 | Q80: =YEAR(N80) -> 2025 | R80: Nhập kho | T80: 45889 | U80: =VLOOKUP($E80,'0. Mã Supplier'!$B:$F,5,0) -> 0 | V80: =T80+U80 -> 45889 | W80: =WEEKNUM(V80) -> 34 | X80: =IF(V80<>0,MONTH(V80),"") -> 8 | Y80: =YEAR(V80) -> 2025 | AA80: =IF(Z80="yes",0,TODAY()-V80) -> 375 | AB80: =IF(Z80="Yes",K80) -> FALSE | AD80: =IFERROR(K80-AB80,0) -> 0
A81: HHN-005 | B81: BLA001001 | C81: =VLOOKUP(B81,'1. Master Data'!$C:$K,9,0) -> Chăn Lạnh 4.8 Xanh dương pastel 200 x 230 cm, Vải cooling mát lạnh | D81: =VLOOKUP(E81,'0. Mã Supplier'!$B:$C,2,0) -> SUVN0001 | E81: HUY HOÀNG NAM | F81: Cái | G81: 50 | H81: 50 | I81: =VLOOKUP($B81,'1. Master Data'!$C:$AB,26,0) -> 280000 | J81: =I81*H81 -> 14000000 | N81: 45778 | O81: =N81-L81 -> 45778 | P81: =MONTH(N81) -> 5 | Q81: =YEAR(N81) -> 2025 | R81: Nhập kho | T81: 45889 | U81: =VLOOKUP($E81,'0. Mã Supplier'!$B:$F,5,0) -> 0 | V81: =T81+U81 -> 45889 | W81: =WEEKNUM(V81) -> 34 | X81: =IF(V81<>0,MONTH(V81),"") -> 8 | Y81: =YEAR(V81) -> 2025 | AA81: =IF(Z81="yes",0,TODAY()-V81) -> 375 | AB81: =IF(Z81="Yes",K81) -> FALSE | AD81: =IFERROR(K81-AB81,0) -> 0
... A90: HHN-006 | B90: BLA002001 | C90: =VLOOKUP(B90,'1. Master Data'!$C:$K,9,0) -> Chăn Tencel 60s Xanh dương pastel 200 x 230 cm | D90: =VLOOKUP(E90,'0. Mã Supplier'!$B:$C,2,0) -> SUVN0001 | E90: HUY HOÀNG NAM | F90: Cái | G90: 7 | H90: 7 | I90: =VLOOKUP($B90,'1. Master Data'!$C:$AB,26,0) -> 429000 | J90: =I90*H90 -> 3003000 | N90: 45809 | O90: =N90-L90 -> 45809 | P90: =MONTH(N90) -> 6 | Q90: =YEAR(N90) -> 2025 | R90: Nhập kho | T90: 45889 | U90: =VLOOKUP($E90,'0. Mã Supplier'!$B:$F,5,0) -> 0 | V90: =T90+U90 -> 45889 | W90: =WEEKNUM(V90) -> 34 | X90: =IF(V90<>0,MONTH(V90),"") -> 8 | Y90: =YEAR(V90) -> 2025 | AA90: =IF(Z90="yes",0,TODAY()-V90) -> 375 | AB90: =IF(Z90="Yes",K90) -> FALSE | AD90: =IFERROR(K90-AB90,0) -> 0
A91: HHN-006 | B91: BLA002002 | C91: =VLOOKUP(B91,'1. Master Data'!$C:$K,9,0) -> Chăn Tencel 60s Hồng pastel 200 x 230 cm | D91: =VLOOKUP(E91,'0. Mã Supplier'!$B:$C,2,0) -> SUVN0001 | E91: HUY HOÀNG NAM | F91: Cái | G91: 9 | H91: 9 | I91: =VLOOKUP($B91,'1. Master Data'!$C:$AB,26,0) -> 429000 | J91: =I91*H91 -> 3861000 | K91: 52788200 | N91: 45809 | O91: =N91-L91 -> 45809 | P91: =MONTH(N91) -> 6 | Q91: =YEAR(N91) -> 2025 | R91: Nhập kho | T91: 45889 | U91: =VLOOKUP($E91,'0. Mã Supplier'!$B:$F,5,0) -> 0 | V91: =T91+U91 -> 45889 | W91: =WEEKNUM(V91) -> 34 | X91: =IF(V91<>0,MONTH(V91),"") -> 8 | Y91: =YEAR(V91) -> 2025 | AA91: =IF(Z91="yes",0,TODAY()-V91) -> 375 | AB91: 52788200 | AD91: =IFERROR(K91-AB91,0) -> 0
A92: HHN-006 | B92: BLA002003 | C92: =VLOOKUP(B92,'1. Master Data'!$C:$K,9,0) -> Chăn Tencel 60s Xanh rêu pastel 200 x 230 cm | D92: =VLOOKUP(E92,'0. Mã Supplier'!$B:$C,2,0) -> SUVN0001 | E92: HUY HOÀNG NAM | F92: Cái | G92: 15 | H92: 15 | I92: =VLOOKUP($B92,'1. Master Data'!$C:$AB,26,0) -> 429000 | J92: =I92*H92 -> 6435000 | N92: 45809 | O92: =N92-L92 -> 45809 | P92: =MONTH(N92) -> 6 | Q92: =YEAR(N92) -> 2025 | R92: Nhập kho | T92: 45889 | U92: =VLOOKUP($E92,'0. Mã Supplier'!$B:$F,5,0) -> 0 | V92: =T92+U92 -> 45889 | W92: =WEEKNUM(V92) -> 34 | X92: =IF(V92<>0,MONTH(V92),"") -> 8 | Y92: =YEAR(V92) -> 2025 | AA92: =IF(Z92="yes",0,TODAY()-V92) -> 375 | AB92: =IF(Z92="Yes",K92) -> FALSE | AD92: =IFERROR(K92-AB92,0) -> 0
A93: HHN-006 | B93: BLA002004 | C93: =VLOOKUP(B93,'1. Master Data'!$C:$K,9,0) -> Chăn Tencel 60s Hồng trắng pastel 200 x 230 cm | D93: =VLOOKUP(E93,'0. Mã Supplier'!$B:$C,2,0) -> SUVN0001 | E93: HUY HOÀNG NAM | F93: Cái | G93: 22 | H93: 22 | I93: =VLOOKUP($B93,'1. Master Data'!$C:$AB,26,0) -> 429000 | J93: =I93*H93 -> 9438000 | N93: 45809 | O93: =N93-L93 -> 45809 | P93: =MONTH(N93) -> 6 | Q93: =YEAR(N93) -> 2025 | R93: Nhập kho | T93: 45889 | U93: =VLOOKUP($E93,'0. Mã Supplier'!$B:$F,5,0) -> 0 | V93: =T93+U93 -> 45889 | W93: =WEEKNUM(V93) -> 34 | X93: =IF(V93<>0,MONTH(V93),"") -> 8 | Y93: =YEAR(V93) -> 2025 | AA93: =IF(Z93="yes",0,TODAY()-V93) -> 375 | AB93: =IF(Z93="Yes",K93) -> FALSE | AD93: =IFERROR(K93-AB93,0) -> 0
A94: HHN-006 | B94: BLA002005 | C94: =VLOOKUP(B94,'1. Master Data'!$C:$K,9,0) -> Chăn Tencel 60s Xám lông chuột 200 x 230 cm | D94: =VLOOKUP(E94,'0. Mã Supplier'!$B:$C,2,0) -> SUVN0001 | E94: HUY HOÀNG NAM | F94: Cái | G94: 6 | H94: 6 | I94: =VLOOKUP($B94,'1. Master Data'!$C:$AB,26,0) -> 429000 | J94: =I94*H94 -> 2574000 | N94: 45809 | O94: =N94-L94 -> 45809 | P94: =MONTH(N94) -> 6 | Q94: =YEAR(N94) -> 2025 | R94: Nhập kho | T94: 45889 | U94: =VLOOKUP($E94,'0. Mã Supplier'!$B:$F,5,0) -> 0 | V94: =T94+U94 -> 45889 | W94: =WEEKNUM(V94) -> 34 | X94: =IF(V94<>0,MONTH(V94),"") -> 8 | Y94: =YEAR(V94) -> 2025 | AA94: =IF(Z94="yes",0,TODAY()-V94) -> 375 | AB94: =IF(Z94="Yes",K94) -> FALSE | AD94: =IFERROR(K94-AB94,0) -> 0
A95: HHN-006 | B95: BLA002006 | C95: =VLOOKUP(B95,'1. Master Data'!$C:$K,9,0) -> Chăn Tencel 60s Xám xanh dương 200 x 230 cm | D95: =VLOOKUP(E95,'0. Mã Supplier'!$B:$C,2,0) -> SUVN0001 | E95: HUY HOÀNG NAM | F95: Cái | G95: 45 | H95: 45 | I95: =VLOOKUP($B95,'1. Master Data'!$C:$AB,26,0) -> 429000 | J95: =I95*H95 -> 19305000 | N95: 45809 | O95: =N95-L95 -> 45809 | P95: =MONTH(N95) -> 6 | Q95: =YEAR(N95) -> 2025 | R95: Nhập kho | T95: 45889 | U95: =VLOOKUP($E95,'0. Mã Supplier'!$B:$F,5,0) -> 0 | V95: =T95+U95 -> 45889 | W95: =WEEKNUM(V95) -> 34 | X95: =IF(V95<>0,MONTH(V95),"") -> 8 | Y95: =YEAR(V95) -> 2025 | AA95: =IF(Z95="yes",0,TODAY()-V95) -> 375 | AB95: =IF(Z95="Yes",K95) -> FALSE | AD95: =IFERROR(K95-AB95,0) -> 0
A96: HHN-006 | B96: BLA002007 | C96: =VLOOKUP(B96,'1. Master Data'!$C:$K,9,0) -> Chăn Tencel 60s Xám trắng 200 x 230 cm | D96: =VLOOKUP(E96,'0. Mã Supplier'!$B:$C,2,0) -> SUVN0001 | E96: HUY HOÀNG NAM | F96: Cái | G96: 26 | H96: 26 | I96: =VLOOKUP($B96,'1. Master Data'!$C:$AB,26,0) -> 429000 | J96: =I96*H96 -> 11154000 | N96: 45809 | O96: =N96-L96 -> 45809 | P96: =MONTH(N96) -> 6 | Q96: =YEAR(N96) -> 2025 | R96: Nhập kho | T96: 45889 | U96: =VLOOKUP($E96,'0. Mã Supplier'!$B:$F,5,0) -> 0 | V96: =T96+U96 -> 45889 | W96: =WEEKNUM(V96) -> 34 | X96: =IF(V96<>0,MONTH(V96),"") -> 8 | Y96: =YEAR(V96) -> 2025 | AA96: =IF(Z96="yes",0,TODAY()-V96) -> 375 | AB96: =IF(Z96="Yes",K96) -> FALSE | AD96: =IFERROR(K96-AB96,0) -> 0
A97: HHN-006 | B97: BLA002008 | C97: =VLOOKUP(B97,'1. Master Data'!$C:$K,9,0) -> Chăn Tencel 60s Xám xanh lá 200 x 230 cm | D97: =VLOOKUP(E97,'0. Mã Supplier'!$B:$C,2,0) -> SUVN0001 | E97: HUY HOÀNG NAM | F97: Cái | G97: 17 | H97: 17 | I97: =VLOOKUP($B97,'1. Master Data'!$C:$AB,26,0) -> 429000 | J97: =I97*H97 -> 7293000 | K97: 75374604 | N97: 45809 | O97: =N97-L97 -> 45809 | P97: =MONTH(N97) -> 6 | Q97: =YEAR(N97) -> 2025 | R97: Nhập kho | T97: 45889 | U97: =VLOOKUP($E97,'0. Mã Supplier'!$B:$F,5,0) -> 0 | V97: =T97+U97 -> 45889 | W97: =WEEKNUM(V97) -> 34 | X97: =IF(V97<>0,MONTH(V97),"") -> 8 | Y97: =YEAR(V97) -> 2025 | AA97: =IF(Z97="yes",0,TODAY()-V97) -> 375 | AB97: 75374604 | AD97: =IFERROR(K97-AB97,0) -> 0
A98: HHN-006 | B98: BLA002009 | C98: =VLOOKUP(B98,'1. Master Data'!$C:$K,9,0) -> Chăn Tencel 60s Màu không phân loại 200 x 230 cm | D98: =VLOOKUP(E98,'0. Mã Supplier'!$B:$C,2,0) -> SUVN0001 | E98: HUY HOÀNG NAM | F98: Cái | G98: 7 | H98: 7 | I98: =VLOOKUP($B98,'1. Master Data'!$C:$AB,26,0) -> 429000 | J98: =I98*H98 -> 3003000 | N98: 45809 | O98: =N98-L98 -> 45809 | P98: =MONTH(N98) -> 6 | Q98: =YEAR(N98) -> 2025 | R98: Nhập kho | T98: 45889 | U98: =VLOOKUP($E98,'0. Mã Supplier'!$B:$F,5,0) -> 0 | V98: =T98+U98 -> 45889 | W98: =WEEKNUM(V98) -> 34 | X98: =IF(V98<>0,MONTH(V98),"") -> 8 | Y98: =YEAR(V98) -> 2025 | AA98: =IF(Z98="yes",0,TODAY()-V98) -> 375 | AB98: =IF(Z98="Yes",K98) -> FALSE | AD98: =IFERROR(K98-AB98,0) -> 0
A99: HHN-006 | B99: BLA001002 | C99: =VLOOKUP(B99,'1. Master Data'!$C:$K,9,0) -> Chăn Lạnh 4.8 Xám pastel 200 x 230 cm, Vải cooling mát lạnh | D99: =VLOOKUP(E99,'0. Mã Supplier'!$B:$C,2,0) -> SUVN0001 | E99: HUY HOÀNG NAM | F99: Cái | G99: 2 | H99: 2 | I99: =VLOOKUP($B99,'1. Master Data'!$C:$AB,26,0) -> 280000 | J99: =I99*H99 -> 560000 | N99: 45809 | O99: =N99-L99 -> 45809 | P99: =MONTH(N99) -> 6 | Q99: =YEAR(N99) -> 2025 | R99: Nhập kho | T99: 45889 | U99: =VLOOKUP($E99,'0. Mã Supplier'!$B:$F,5,0) -> 0 | V99: =T99+U99 -> 45889 | W99: =WEEKNUM(V99) -> 34 | X99: =IF(V99<>0,MONTH(V99),"") -> 8 | Y99: =YEAR(V99) -> 2025 | AA99: =IF(Z99="yes",0,TODAY()-V99) -> 375 | AB99: =IF(Z99="Yes",K99) -> FALSE | AD99: =IFERROR(K99-AB99,0) -> 0
A100: HHN-006 | B100: BLA001003 | C100: =VLOOKUP(B100,'1. Master Data'!$C:$K,9,0) -> Chăn Lạnh 4.8 Tím hoa cà 200 x 230 cm, Vải cooling mát lạnh | D100: =VLOOKUP(E100,'0. Mã Supplier'!$B:$C,2,0) -> SUVN0001 | E100: HUY HOÀNG NAM | F100: Cái | G100: 2 | H100: 2 | I100: =VLOOKUP($B100,'1. Master Data'!$C:$AB,26,0) -> 280000 | J100: =I100*H100 -> 560000 | N100: 45809 | O100: =N100-L100 -> 45809 | P100: =MONTH(N100) -> 6 | Q100: =YEAR(N100) -> 2025 | R100: Nhập kho | T100: 45889 | U100: =VLOOKUP($E100,'0. Mã Supplier'!$B:$F,5,0) -> 0 | V100: =T100+U100 -> 45889 | W100: =WEEKNUM(V100) -> 34 | X100: =IF(V100<>0,MONTH(V100),"") -> 8 | Y100: =YEAR(V100) -> 2025 | AA100: =IF(Z100="yes",0,TODAY()-V100) -> 375 | AB100: =IF(Z100="Yes",K100) -> FALSE | AD100: =IFERROR(K100-AB100,0) -> 0
A101: HTS-001 | B101: MAT001013 | C101: =VLOOKUP(B101,'1. Master Data'!$C:$K,9,0) -> Nệm T&N Foam 160 x 200 x 15 cm | D101: =VLOOKUP(E101,'0. Mã Supplier'!$B:$C,2,0) -> SUVN0002 | E101: HAPPYTOWN SLEEPTECH | F101: Cái | G101: 5 | H101: 5 | I101: =VLOOKUP($B101,'1. Master Data'!$C:$AB,26,0) -> 1772300 | J101: =I101*H101 -> 8861500 | K101: =J101*1.08 -> 9570420 | N101: 45741 | O101: =N101-L101 -> 45741 | P101: =MONTH(N101) -> 3 | Q101: =YEAR(N101) -> 2025 | R101: Nhập kho | T101: 45741 | U101: =VLOOKUP($E101,'0. Mã Supplier'!$B:$F,5,0) -> 30 | V101: =T101+U101 -> 45771 | W101: =WEEKNUM(V101) -> 17 | X101: =IF(V101<>0,MONTH(V101),"") -> 4 | Y101: =YEAR(V101) -> 2025 | Z101: Yes | AA101: =IF(Z101="yes",0,TODAY()-V101) -> 0 | AB101: =IF(Z101="Yes",K101) -> 9570420 | AD101: =IFERROR(K101-AB101,0) -> 0
A102: HTS-001 | B102: MAT001014 | C102: =VLOOKUP(B102,'1. Master Data'!$C:$K,9,0) -> Nệm T&N Foam 180 x 200 x 15 cm | D102: =VLOOKUP(E102,'0. Mã Supplier'!$B:$C,2,0) -> SUVN0002 | E102: HAPPYTOWN SLEEPTECH | F102: Cái | G102: 5 | H102: 5 | I102: =VLOOKUP($B102,'1. Master Data'!$C:$AB,26,0) -> 1979600 | J102: =I102*H102 -> 9898000 | K102: =J102*1.08 -> 10689840 | N102: 45741 | O102: =N102-L102 -> 45741 | P102: =MONTH(N102) -> 3 | Q102: =YEAR(N102) -> 2025 | R102: Nhập kho | T102: 45741 | U102: =VLOOKUP($E102,'0. Mã Supplier'!$B:$F,5,0) -> 30 | V102: =T102+U102 -> 45771 | W102: =WEEKNUM(V102) -> 17 | X102: =IF(V102<>0,MONTH(V102),"") -> 4 | Y102: =YEAR(V102) -> 2025 | Z102: Yes | AA102: =IF(Z102="yes",0,TODAY()-V102) -> 0 | AB102: =IF(Z102="Yes",K102) -> 10689840 | AD102: =IFERROR(K102-AB102,0) -> 0
A103: HTS-001 | B103: MAT001021 | C103: =VLOOKUP(B103,'1. Master Data'!$C:$K,9,0) -> Nệm T&N Foam 160 x 200 x 20 cm | D103: =VLOOKUP(E103,'0. Mã Supplier'!$B:$C,2,0) -> SUVN0002 | E103: HAPPYTOWN SLEEPTECH | F103: Cái | G103: 5 | H103: 5 | I103: =VLOOKUP($B103,'1. Master Data'!$C:$AB,26,0) -> 2265800 | J103: =I103*H103 -> 11329000 | K103: =J103*1.08 -> 12235320 | N103: 45741 | O103: =N103-L103 -> 45741 | P103: =MONTH(N103) -> 3 | Q103: =YEAR(N103) -> 2025 | R103: Nhập kho | T103: 45741 | U103: =VLOOKUP($E103,'0. Mã Supplier'!$B:$F,5,0) -> 30 | V103: =T103+U103 -> 45771 | W103: =WEEKNUM(V103) -> 17 | X103: =IF(V103<>0,MONTH(V103),"") -> 4 | Y103: =YEAR(V103) -> 2025 | Z103: Yes | AA103: =IF(Z103="yes",0,TODAY()-V103) -> 0 | AB103: =IF(Z103="Yes",K103) -> 12235320 | AD103: =IFERROR(K103-AB103,0) -> 0
A104: HTS-001 | B104: MAT001022 | C104: =VLOOKUP(B104,'1. Master Data'!$C:$K,9,0) -> Nệm T&N Foam 180 x 200 x 20 cm | D104: =VLOOKUP(E104,'0. Mã Supplier'!$B:$C,2,0) -> SUVN0002 | E104: HAPPYTOWN SLEEPTECH | F104: Cái | G104: 5 | H104: 5 | I104: =VLOOKUP($B104,'1. Master Data'!$C:$AB,26,0) -> 2531500 | J104: =I104*H104 -> 12657500 | K104: =J104*1.08 -> 13670100 | N104: 45741 | O104: =N104-L104 -> 45741 | P104: =MONTH(N104) -> 3 | Q104: =YEAR(N104) -> 2025 | R104: Nhập kho | T104: 45741 | U104: =VLOOKUP($E104,'0. Mã Supplier'!$B:$F,5,0) -> 30 | V104: =T104+U104 -> 45771 | W104: =WEEKNUM(V104) -> 17 | X104: =IF(V104<>0,MONTH(V104),"") -> 4 | Y104: =YEAR(V104) -> 2025 | Z104: Yes | AA104: =IF(Z104="yes",0,TODAY()-V104) -> 0 | AB104: =IF(Z104="Yes",K104) -> 13670100 | AD104: =IFERROR(K104-AB104,0) -> 0
A105: HTS-001 | B105: PIL001001 | C105: =VLOOKUP(B105,'1. Master Data'!$C:$K,9,0) -> Gối T&N contour (Cứng) 30 x 50 x 8/10 cm | D105: =VLOOKUP(E105,'0. Mã Supplier'!$B:$C,2,0) -> SUVN0002 | E105: HAPPYTOWN SLEEPTECH | F105: Cái | G105: 25 | H105: 25 | I105: =VLOOKUP($B105,'1. Master Data'!$C:$AB,26,0) -> 116100 | J105: =I105*H105 -> 2902500 | K105: =J105*1.08 -> 3134700 | N105: 45741 | O105: =N105-L105 -> 45741 | P105: =MONTH(N105) -> 3 | Q105: =YEAR(N105) -> 2025 | R105: Nhập kho | T105: 45741 | U105: =VLOOKUP($E105,'0. Mã Supplier'!$B:$F,5,0) -> 30 | V105: =T105+U105 -> 45771 | W105: =WEEKNUM(V105) -> 17 | X105: =IF(V105<>0,MONTH(V105),"") -> 4 | Y105: =YEAR(V105) -> 2025 | Z105: Yes | AA105: =IF(Z105="yes",0,TODAY()-V105) -> 0 | AB105: =IF(Z105="Yes",K105) -> 3134700 | AD105: =IFERROR(K105-AB105,0) -> 0
A106: HTS-001 | B106: PIL001002 | C106: =VLOOKUP(B106,'1. Master Data'!$C:$K,9,0) -> Gối T&N contour (Cứng) 40 x 60 x 10/12 cm | D106: =VLOOKUP(E106,'0. Mã Supplier'!$B:$C,2,0) -> SUVN0002 | E106: HAPPYTOWN SLEEPTECH | F106: Cái | G106: 25 | H106: 25 | I106: =VLOOKUP($B106,'1. Master Data'!$C:$AB,26,0) -> 143100 | J106: =I106*H106 -> 3577500 | K106: =J106*1.08 -> 3863700 | N106: 45741 | O106: =N106-L106 -> 45741 | P106: =MONTH(N106) -> 3 | Q106: =YEAR(N106) -> 2025 | R106: Nhập kho | T106: 45741 | U106: =VLOOKUP($E106,'0. Mã Supplier'!$B:$F,5,0) -> 30 | V106: =T106+U106 -> 45771 | W106: =WEEKNUM(V106) -> 17 | X106: =IF(V106<>0,MONTH(V106),"") -> 4 | Y106: =YEAR(V106) -> 2025 | Z106: Yes | AA106: =IF(Z106="yes",0,TODAY()-V106) -> 0 | AB106: =IF(Z106="Yes",K106) -> 3863700 | AD106: =IFERROR(K106-AB106,0) -> 0
A107: HTS-002 | B107: MAT001003 | C107: =VLOOKUP(B107,'1. Master Data'!$C:$K,9,0) -> Nệm T&N Foam 120 x 200 x 10 cm | D107: =VLOOKUP(E107,'0. Mã Supplier'!$B:$C,2,0) -> SUVN0002 | E107: HAPPYTOWN SLEEPTECH | F107: Cái | G107: 5 | H107: 5 | I107: =VLOOKUP($B107,'1. Master Data'!$C:$AB,26,0) -> 1073100 | J107: =I107*H107 -> 5365500 | K107: =J107*1.08 -> 5794740 | N107: 45792 | O107: =N107-L107 -> 45792 | P107: =MONTH(N107) -> 5 | Q107: =YEAR(N107) -> 2025 | R107: Nhập kho | T107: 45792 | U107: =VLOOKUP($E107,'0. Mã Supplier'!$B:$F,5,0) -> 30 | V107: =T107+U107 -> 45822 | W107: =WEEKNUM(V107) -> 24 | X107: =IF(V107<>0,MONTH(V107),"") -> 6 | Y107: =YEAR(V107) -> 2025 | Z107: Yes | AA107: =IF(Z107="yes",0,TODAY()-V107) -> 0 | AB107: =IF(Z107="Yes",K107) -> 5794740 | AD107: =IFERROR(K107-AB107,0) -> 0
A108: HTS-002 | B108: MAT001005 | C108: =VLOOKUP(B108,'1. Master Data'!$C:$K,9,0) -> Nệm T&N Foam 160 x 200 x 10 cm | D108: =VLOOKUP(E108,'0. Mã Supplier'!$B:$C,2,0) -> SUVN0002 | E108: HAPPYTOWN SLEEPTECH | F108: Cái | G108: 10 | H108: 10 | I108: =VLOOKUP($B108,'1. Master Data'!$C:$AB,26,0) -> 1421300 | J108: =I108*H108 -> 14213000 | K108: =J108*1.08 -> 15350040 | N108: 45792 | O108: =N108-L108 -> 45792 | P108: =MONTH(N108) -> 5 | Q108: =YEAR(N108) -> 2025 | R108: Nhập kho | T108: 45792 | U108: =VLOOKUP($E108,'0. Mã Supplier'!$B:$F,5,0) -> 30 | V108: =T108+U108 -> 45822 | W108: =WEEKNUM(V108) -> 24 | X108: =IF(V108<>0,MONTH(V108),"") -> 6 | Y108: =YEAR(V108) -> 2025 | Z108: Yes | AA108: =IF(Z108="yes",0,TODAY()-V108) -> 0 | AB108: =IF(Z108="Yes",K108) -> 15350040 | AD108: =IFERROR(K108-AB108,0) -> 0
A109: HTS-002 | B109: MAT001006 | C109: =VLOOKUP(B109,'1. Master Data'!$C:$K,9,0) -> Nệm T&N Foam 180 x 200 x 10 cm | D109: =VLOOKUP(E109,'0. Mã Supplier'!$B:$C,2,0) -> SUVN0002 | E109: HAPPYTOWN SLEEPTECH | F109: Cái | G109: 9 | H109: 9 | I109: =VLOOKUP($B109,'1. Master Data'!$C:$AB,26,0) -> 1585400 | J109: =I109*H109 -> 14268600 | K109: =J109*1.08 -> 15410088 | N109: 45792 | O109: =N109-L109 -> 45792 | P109: =MONTH(N109) -> 5 | Q109: =YEAR(N109) -> 2025 | R109: Nhập kho | T109: 45792 | U109: =VLOOKUP($E109,'0. Mã Supplier'!$B:$F,5,0) -> 30 | V109: =T109+U109 -> 45822 | W109: =WEEKNUM(V109) -> 24 | X109: =IF(V109<>0,MONTH(V109),"") -> 6 | Y109: =YEAR(V109) -> 2025 | Z109: Yes | AA109: =IF(Z109="yes",0,TODAY()-V109) -> 0 | AB109: =IF(Z109="Yes",K109) -> 15410088 | AD109: =IFERROR(K109-AB109,0) -> 0
A110: HTS-002 | B110: MAT001013 | C110: =VLOOKUP(B110,'1. Master Data'!$C:$K,9,0) -> Nệm T&N Foam 160 x 200 x 15 cm | D110: =VLOOKUP(E110,'0. Mã Supplier'!$B:$C,2,0) -> SUVN0002 | E110: HAPPYTOWN SLEEPTECH | F110: Cái | G110: 10 | H110: 10 | I110: =VLOOKUP($B110,'1. Master Data'!$C:$AB,26,0) -> 1772300 | J110: =I110*H110 -> 17723000 | K110: =J110*1.08 -> 19140840 | N110: 45792 | O110: =N110-L110 -> 45792 | P110: =MONTH(N110) -> 5 | Q110: =YEAR(N110) -> 2025 | R110: Nhập kho | T110: 45792 | U110: =VLOOKUP($E110,'0. Mã Supplier'!$B:$F,5,0) -> 30 | V110: =T110+U110 -> 45822 | W110: =WEEKNUM(V110) -> 24 | X110: =IF(V110<>0,MONTH(V110),"") -> 6 | Y110: =YEAR(V110) -> 2025 | Z110: Yes | AA110: =IF(Z110="yes",0,TODAY()-V110) -> 0 | AB110: =IF(Z110="Yes",K110) -> 19140840 | AD110: =IFERROR(K110-AB110,0) -> 0
A111: HTS-002 | B111: MAT001014 | C111: =VLOOKUP(B111,'1. Master Data'!$C:$K,9,0) -> Nệm T&N Foam 180 x 200 x 15 cm | D111: =VLOOKUP(E111,'0. Mã Supplier'!$B:$C,2,0) -> SUVN0002 | E111: HAPPYTOWN SLEEPTECH | F111: Cái | G111: 5 | H111: 5 | I111: =VLOOKUP($B111,'1. Master Data'!$C:$AB,26,0) -> 1979600 | J111: =I111*H111 -> 9898000 | K111: =J111*1.08 -> 10689840 | N111: 45792 | O111: =N111-L111 -> 45792 | P111: =MONTH(N111) -> 5 | Q111: =YEAR(N111) -> 2025 | R111: Nhập kho | T111: 45792 | U111: =VLOOKUP($E111,'0. Mã Supplier'!$B:$F,5,0) -> 30 | V111: =T111+U111 -> 45822 | W111: =WEEKNUM(V111) -> 24 | X111: =IF(V111<>0,MONTH(V111),"") -> 6 | Y111: =YEAR(V111) -> 2025 | Z111: Yes | AA111: =IF(Z111="yes",0,TODAY()-V111) -> 0 | AB111: =IF(Z111="Yes",K111) -> 10689840 | AD111: =IFERROR(K111-AB111,0) -> 0
A112: HTS-002 | B112: MAT001021 | C112: =VLOOKUP(B112,'1. Master Data'!$C:$K,9,0) -> Nệm T&N Foam 160 x 200 x 20 cm | D112: =VLOOKUP(E112,'0. Mã Supplier'!$B:$C,2,0) -> SUVN0002 | E112: HAPPYTOWN SLEEPTECH | F112: Cái | G112: 4 | H112: 4 | I112: =VLOOKUP($B112,'1. Master Data'!$C:$AB,26,0) -> 2265800 | J112: =I112*H112 -> 9063200 | K112: =J112*1.08 -> 9788256 | N112: 45792 | O112: =N112-L112 -> 45792 | P112: =MONTH(N112) -> 5 | Q112: =YEAR(N112) -> 2025 | R112: Nhập kho | T112: 45792 | U112: =VLOOKUP($E112,'0. Mã Supplier'!$B:$F,5,0) -> 30 | V112: =T112+U112 -> 45822 | W112: =WEEKNUM(V112) -> 24 | X112: =IF(V112<>0,MONTH(V112),"") -> 6 | Y112: =YEAR(V112) -> 2025 | Z112: Yes | AA112: =IF(Z112="yes",0,TODAY()-V112) -> 0 | AB112: =IF(Z112="Yes",K112) -> 9788256 | AD112: =IFERROR(K112-AB112,0) -> 0
... A129: HTS-003#2 | B129: PIL001004 | C129: =VLOOKUP(B129,'1. Master Data'!$C:$K,9,0) -> Gối T&N contour (Mềm) 40 x 60 x 10/12 cm | D129: =VLOOKUP(E129,'0. Mã Supplier'!$B:$C,2,0) -> SUVN0002 | E129: HAPPYTOWN SLEEPTECH | F129: Cái | G129: 25 | H129: 25 | I129: =VLOOKUP($B129,'1. Master Data'!$C:$AB,26,0) -> 181000 | J129: =I129*H129 -> 4525000 | K129: =J129*1.08 -> 4887000 | N129: 45840 | O129: =N129-L129 -> 45840 | P129: =MONTH(N129) -> 7 | Q129: =YEAR(N129) -> 2025 | R129: Nhập kho | T129: 45840 | U129: =VLOOKUP($E129,'0. Mã Supplier'!$B:$F,5,0) -> 30 | V129: =T129+U129 -> 45870 | W129: =WEEKNUM(V129) -> 31 | X129: =IF(V129<>0,MONTH(V129),"") -> 8 | Y129: =YEAR(V129) -> 2025 | Z129: Yes | AA129: =IF(Z129="yes",0,TODAY()-V129) -> 0 | AB129: =IF(Z129="Yes",K129) -> 4887000 | AD129: =IFERROR(K129-AB129,0) -> 0
A130: HTS-004 | B130: MAT001003 | C130: =VLOOKUP(B130,'1. Master Data'!$C:$K,9,0) -> Nệm T&N Foam 120 x 200 x 10 cm | D130: =VLOOKUP(E130,'0. Mã Supplier'!$B:$C,2,0) -> SUVN0002 | E130: HAPPYTOWN SLEEPTECH | F130: Cái | G130: 30 | H130: 30 | I130: =VLOOKUP($B130,'1. Master Data'!$C:$AB,26,0) -> 1073100 | J130: =I130*H130 -> 32193000 | K130: =J130*1.08 -> 34768440 | L130: 45853 | M130: 45878 | N130: 45878 | O130: =N130-L130 -> 25 | P130: =MONTH(N130) -> 8 | Q130: =YEAR(N130) -> 2025 | R130: Nhập kho | T130: =N130 -> 45878 | U130: =VLOOKUP($E130,'0. Mã Supplier'!$B:$F,5,0) -> 30 | V130: =T130+U130 -> 45908 | W130: =WEEKNUM(V130) -> 37 | X130: =IF(V130<>0,MONTH(V130),"") -> 9 | Y130: =YEAR(V130) -> 2025 | AA130: =IF(Z130="yes",0,TODAY()-V130) -> 356 | AB130: 50000000 | AD130: =IFERROR(K130-AB130,0) -> -15231560
A131: HTS-004 | B131: MAT001005 | C131: =VLOOKUP(B131,'1. Master Data'!$C:$K,9,0) -> Nệm T&N Foam 160 x 200 x 10 cm | D131: =VLOOKUP(E131,'0. Mã Supplier'!$B:$C,2,0) -> SUVN0002 | E131: HAPPYTOWN SLEEPTECH | F131: Cái | G131: 30 | H131: 30 | I131: =VLOOKUP($B131,'1. Master Data'!$C:$AB,26,0) -> 1421300 | J131: =I131*H131 -> 42639000 | K131: =J131*1.08 -> 46050120 | L131: 45853 | M131: 45878 | N131: 45878 | O131: =N131-L131 -> 25 | P131: =MONTH(N131) -> 8 | Q131: =YEAR(N131) -> 2025 | R131: Nhập kho | T131: =N131 -> 45878 | U131: =VLOOKUP($E131,'0. Mã Supplier'!$B:$F,5,0) -> 30 | V131: =T131+U131 -> 45908 | W131: =WEEKNUM(V131) -> 37 | X131: =IF(V131<>0,MONTH(V131),"") -> 9 | Y131: =YEAR(V131) -> 2025 | AA131: =IF(Z131="yes",0,TODAY()-V131) -> 356 | AB131: 35000000 | AD131: =IFERROR(K131-AB131,0) -> 11050120
A132: HTS-004 | B132: MAT001006 | C132: =VLOOKUP(B132,'1. Master Data'!$C:$K,9,0) -> Nệm T&N Foam 180 x 200 x 10 cm | D132: =VLOOKUP(E132,'0. Mã Supplier'!$B:$C,2,0) -> SUVN0002 | E132: HAPPYTOWN SLEEPTECH | F132: Cái | G132: 30 | H132: 30 | I132: =VLOOKUP($B132,'1. Master Data'!$C:$AB,26,0) -> 1585400 | J132: =I132*H132 -> 47562000 | K132: =J132*1.08 -> 51366960 | L132: 45853 | M132: 45878 | N132: 45878 | O132: =N132-L132 -> 25 | P132: =MONTH(N132) -> 8 | Q132: =YEAR(N132) -> 2025 | R132: Nhập kho | T132: =N132 -> 45878 | U132: =VLOOKUP($E132,'0. Mã Supplier'!$B:$F,5,0) -> 30 | V132: =T132+U132 -> 45908 | W132: =WEEKNUM(V132) -> 37 | X132: =IF(V132<>0,MONTH(V132),"") -> 9 | Y132: =YEAR(V132) -> 2025 | AA132: =IF(Z132="yes",0,TODAY()-V132) -> 356 | AB132: 50000000 | AD132: =IFERROR(K132-AB132,0) -> 1366960
A133: HTS-004 | B133: MAT001013 | C133: =VLOOKUP(B133,'1. Master Data'!$C:$K,9,0) -> Nệm T&N Foam 160 x 200 x 15 cm | D133: =VLOOKUP(E133,'0. Mã Supplier'!$B:$C,2,0) -> SUVN0002 | E133: HAPPYTOWN SLEEPTECH | F133: Cái | G133: 30 | H133: 30 | I133: =VLOOKUP($B133,'1. Master Data'!$C:$AB,26,0) -> 1772300 | J133: =I133*H133 -> 53169000 | K133: =J133*1.08 -> 57422520 | L133: 45853 | M133: 45878 | N133: 45878 | O133: =N133-L133 -> 25 | P133: =MONTH(N133) -> 8 | Q133: =YEAR(N133) -> 2025 | R133: Nhập kho | T133: =N133 -> 45878 | U133: =VLOOKUP($E133,'0. Mã Supplier'!$B:$F,5,0) -> 30 | V133: =T133+U133 -> 45908 | W133: =WEEKNUM(V133) -> 37 | X133: =IF(V133<>0,MONTH(V133),"") -> 9 | Y133: =YEAR(V133) -> 2025 | AA133: =IF(Z133="yes",0,TODAY()-V133) -> 356 | AB133: 50000000 | AD133: =IFERROR(K133-AB133,0) -> 7422520
A134: HTS-004 | B134: MAT001014 | C134: =VLOOKUP(B134,'1. Master Data'!$C:$K,9,0) -> Nệm T&N Foam 180 x 200 x 15 cm | D134: =VLOOKUP(E134,'0. Mã Supplier'!$B:$C,2,0) -> SUVN0002 | E134: HAPPYTOWN SLEEPTECH | F134: Cái | G134: 30 | H134: 30 | I134: =VLOOKUP($B134,'1. Master Data'!$C:$AB,26,0) -> 1979600 | J134: =I134*H134 -> 59388000 | K134: =J134*1.08 -> 64139040 | L134: 45853 | M134: 45878 | N134: 45878 | O134: =N134-L134 -> 25 | P134: =MONTH(N134) -> 8 | Q134: =YEAR(N134) -> 2025 | R134: Nhập kho | T134: =N134 -> 45878 | U134: =VLOOKUP($E134,'0. Mã Supplier'!$B:$F,5,0) -> 30 | V134: =T134+U134 -> 45908 | W134: =WEEKNUM(V134) -> 37 | X134: =IF(V134<>0,MONTH(V134),"") -> 9 | Y134: =YEAR(V134) -> 2025 | AA134: =IF(Z134="yes",0,TODAY()-V134) -> 356 | AB134: 15000000 | AC134: 46010 | AD134: =IFERROR(K134-AB134,0) -> 49139040
A135: HTS-004 | B135: MAT001021 | C135: =VLOOKUP(B135,'1. Master Data'!$C:$K,9,0) -> Nệm T&N Foam 160 x 200 x 20 cm | D135: =VLOOKUP(E135,'0. Mã Supplier'!$B:$C,2,0) -> SUVN0002 | E135: HAPPYTOWN SLEEPTECH | F135: Cái | G135: 30 | H135: 30 | I135: =VLOOKUP($B135,'1. Master Data'!$C:$AB,26,0) -> 2265800 | J135: =I135*H135 -> 67974000 | K135: =J135*1.08 -> 73411920 | L135: 45853 | M135: 45878 | N135: 45878 | O135: =N135-L135 -> 25 | P135: =MONTH(N135) -> 8 | Q135: =YEAR(N135) -> 2025 | R135: Nhập kho | T135: =N135 -> 45878 | U135: =VLOOKUP($E135,'0. Mã Supplier'!$B:$F,5,0) -> 30 | V135: =T135+U135 -> 45908 | W135: =WEEKNUM(V135) -> 37 | X135: =IF(V135<>0,MONTH(V135),"") -> 9 | Y135: =YEAR(V135) -> 2025 | AA135: =IF(Z135="yes",0,TODAY()-V135) -> 356 | AB135: 10000000 | AC135: 46024 | AD135: =IFERROR(K135-AB135,0) -> 63411920
A136: HTS-004 | B136: MAT001022 | C136: =VLOOKUP(B136,'1. Master Data'!$C:$K,9,0) -> Nệm T&N Foam 180 x 200 x 20 cm | D136: =VLOOKUP(E136,'0. Mã Supplier'!$B:$C,2,0) -> SUVN0002 | E136: HAPPYTOWN SLEEPTECH | F136: Cái | G136: 20 | H136: 20 | I136: =VLOOKUP($B136,'1. Master Data'!$C:$AB,26,0) -> 2531500 | J136: =I136*H136 -> 50630000 | K136: =J136*1.08 -> 54680400 | L136: 45853 | M136: 45878 | N136: 45878 | O136: =N136-L136 -> 25 | P136: =MONTH(N136) -> 8 | Q136: =YEAR(N136) -> 2025 | R136: Nhập kho | T136: =N136 -> 45878 | U136: =VLOOKUP($E136,'0. Mã Supplier'!$B:$F,5,0) -> 30 | V136: =T136+U136 -> 45908 | W136: =WEEKNUM(V136) -> 37 | X136: =IF(V136<>0,MONTH(V136),"") -> 9 | Y136: =YEAR(V136) -> 2025 | AA136: =IF(Z136="yes",0,TODAY()-V136) -> 356 | AB136: 10000000 | AD136: =IFERROR(K136-AB136,0) -> 44680400
A137: HTS-004 | B137: PIL001003 | C137: =VLOOKUP(B137,'1. Master Data'!$C:$K,9,0) -> Gối T&N contour (Mềm) 30 x 50 x 8/10 cm | D137: =VLOOKUP(E137,'0. Mã Supplier'!$B:$C,2,0) -> SUVN0002 | E137: HAPPYTOWN SLEEPTECH | F137: Cái | G137: 20 | H137: 20 | I137: =VLOOKUP($B137,'1. Master Data'!$C:$AB,26,0) -> 139000 | J137: =I137*H137 -> 2780000 | K137: =J137*1.08 -> 3002400 | L137: 45853 | M137: 45878 | N137: 45878 | O137: =N137-L137 -> 25 | P137: =MONTH(N137) -> 8 | Q137: =YEAR(N137) -> 2025 | R137: Nhập kho | T137: =N137 -> 45878 | U137: =VLOOKUP($E137,'0. Mã Supplier'!$B:$F,5,0) -> 30 | V137: =T137+U137 -> 45908 | W137: =WEEKNUM(V137) -> 37 | X137: =IF(V137<>0,MONTH(V137),"") -> 9 | Y137: =YEAR(V137) -> 2025 | AA137: =IF(Z137="yes",0,TODAY()-V137) -> 356 | AB137: =IF(Z137="Yes",K137) -> FALSE | AD137: =IFERROR(K137-AB137,0) -> 3002400
A138: HTS-004 | B138: PIL001004 | C138: =VLOOKUP(B138,'1. Master Data'!$C:$K,9,0) -> Gối T&N contour (Mềm) 40 x 60 x 10/12 cm | D138: =VLOOKUP(E138,'0. Mã Supplier'!$B:$C,2,0) -> SUVN0002 | E138: HAPPYTOWN SLEEPTECH | F138: Cái | G138: 20 | H138: 20 | I138: =VLOOKUP($B138,'1. Master Data'!$C:$AB,26,0) -> 181000 | J138: =I138*H138 -> 3620000 | K138: =J138*1.08 -> 3909600 | L138: 45853 | M138: 45878 | N138: 45878 | O138: =N138-L138 -> 25 | P138: =MONTH(N138) -> 8 | Q138: =YEAR(N138) -> 2025 | R138: Nhập kho | T138: =N138 -> 45878 | U138: =VLOOKUP($E138,'0. Mã Supplier'!$B:$F,5,0) -> 30 | V138: =T138+U138 -> 45908 | W138: =WEEKNUM(V138) -> 37 | X138: =IF(V138<>0,MONTH(V138),"") -> 9 | Y138: =YEAR(V138) -> 2025 | AA138: =IF(Z138="yes",0,TODAY()-V138) -> 356 | AB138: =IF(Z138="Yes",K138) -> FALSE | AD138: =IFERROR(K138-AB138,0) -> 3909600
A139: HTS-004 | B139: PIL001001 | C139: =VLOOKUP(B139,'1. Master Data'!$C:$K,9,0) -> Gối T&N contour (Cứng) 30 x 50 x 8/10 cm | D139: =VLOOKUP(E139,'0. Mã Supplier'!$B:$C,2,0) -> SUVN0002 | E139: HAPPYTOWN SLEEPTECH | F139: Cái | G139: 20 | H139: 20 | I139: =VLOOKUP($B139,'1. Master Data'!$C:$AB,26,0) -> 116100 | J139: =I139*H139 -> 2322000 | K139: =J139*1.08 -> 2507760 | L139: 45853 | M139: 45878 | N139: 45878 | O139: =N139-L139 -> 25 | P139: =MONTH(N139) -> 8 | Q139: =YEAR(N139) -> 2025 | R139: Nhập kho | T139: =N139 -> 45878 | U139: =VLOOKUP($E139,'0. Mã Supplier'!$B:$F,5,0) -> 30 | V139: =T139+U139 -> 45908 | W139: =WEEKNUM(V139) -> 37 | X139: =IF(V139<>0,MONTH(V139),"") -> 9 | Y139: =YEAR(V139) -> 2025 | AA139: =IF(Z139="yes",0,TODAY()-V139) -> 356 | AB139: =IF(Z139="Yes",K139) -> FALSE | AD139: =IFERROR(K139-AB139,0) -> 2507760
A140: EVH-001 | B140: MAT002005 | C140: =VLOOKUP(B140,'1. Master Data'!$C:$K,9,0) -> Nệm Hybrid 160 x 200 x 25 cm | D140: =VLOOKUP(E140,'0. Mã Supplier'!$B:$C,2,0) -> SUVN0003 | E140: EVERHOME | F140: Cái | G140: 10 | H140: 10 | I140: =VLOOKUP($B140,'1. Master Data'!$C:$AB,26,0) -> 2229010 | J140: =I140*H140 -> 22290100 | K140: =J140*1.08 -> 24073308 | L140: 45819 | N140: =L140+20 -> 45839 | O140: =N140-L140 -> 20 | P140: =MONTH(N140) -> 7 | Q140: =YEAR(N140) -> 2025 | R140: Nhập kho | T140: 45847 | U140: =VLOOKUP($E140,'0. Mã Supplier'!$B:$F,5,0) -> 60 | V140: =T140+U140 -> 45907 | W140: =WEEKNUM(V140) -> 37 | X140: =IF(V140<>0,MONTH(V140),"") -> 9 | Y140: =YEAR(V140) -> 2025 | AA140: =IF(Z140="yes",0,TODAY()-V140) -> 357 | AB140: =IF(Z140="Yes",K140) -> FALSE | AD140: =IFERROR(K140-AB140,0) -> 24073308
A141: EVH-001 | B141: MAT002006 | C141: =VLOOKUP(B141,'1. Master Data'!$C:$K,9,0) -> Nệm Hybrid 180 x 200 x 25 cm | D141: =VLOOKUP(E141,'0. Mã Supplier'!$B:$C,2,0) -> SUVN0003 | E141: EVERHOME | F141: Cái | G141: 10 | H141: 10 | I141: =VLOOKUP($B141,'1. Master Data'!$C:$AB,26,0) -> 2425010 | J141: =I141*H141 -> 24250100 | K141: =J141*1.08 -> 26190108 | L141: 45819 | N141: =L141+20 -> 45839 | O141: =N141-L141 -> 20 | P141: =MONTH(N141) -> 7 | Q141: =YEAR(N141) -> 2025 | R141: Nhập kho | T141: 45847 | U141: =VLOOKUP($E141,'0. Mã Supplier'!$B:$F,5,0) -> 60 | V141: =T141+U141 -> 45907 | W141: =WEEKNUM(V141) -> 37 | X141: =IF(V141<>0,MONTH(V141),"") -> 9 | Y141: =YEAR(V141) -> 2025 | AA141: =IF(Z141="yes",0,TODAY()-V141) -> 357 | AB141: 50000000 | AD141: =IFERROR(K141-AB141,0) -> -23809892
A142: EVH-001 | B142: MAT003005 | C142: =VLOOKUP(B142,'1. Master Data'!$C:$K,9,0) -> Nệm Hybrid Latex 160 x 200 x 27 cm | D142: =VLOOKUP(E142,'0. Mã Supplier'!$B:$C,2,0) -> SUVN0003 | E142: EVERHOME | F142: Cái | G142: 10 | H142: 10 | I142: =VLOOKUP($B142,'1. Master Data'!$C:$AB,26,0) -> 2572010 | J142: =I142*H142 -> 25720100 | K142: =J142*1.08 -> 27777708 | L142: 45819 | N142: =L142+20 -> 45839 | O142: =N142-L142 -> 20 | P142: =MONTH(N142) -> 7 | Q142: =YEAR(N142) -> 2025 | R142: Nhập kho | T142: 45847 | U142: =VLOOKUP($E142,'0. Mã Supplier'!$B:$F,5,0) -> 60 | V142: =T142+U142 -> 45907 | W142: =WEEKNUM(V142) -> 37 | X142: =IF(V142<>0,MONTH(V142),"") -> 9 | Y142: =YEAR(V142) -> 2025 | AA142: =IF(Z142="yes",0,TODAY()-V142) -> 357 | AB142: 30000000 | AD142: =IFERROR(K142-AB142,0) -> -2222292
A143: EVH-001 | B143: MAT003006 | C143: =VLOOKUP(B143,'1. Master Data'!$C:$K,9,0) -> Nệm Hybrid Latex 180 x 200 x 27 cm | D143: =VLOOKUP(E143,'0. Mã Supplier'!$B:$C,2,0) -> SUVN0003 | E143: EVERHOME | F143: Cái | G143: 10 | H143: 10 | I143: =VLOOKUP($B143,'1. Master Data'!$C:$AB,26,0) -> 2866010 | J143: =I143*H143 -> 28660100 | K143: =J143*1.08 -> 30952908 | L143: 45819 | N143: =L143+20 -> 45839 | O143: =N143-L143 -> 20 | P143: =MONTH(N143) -> 7 | Q143: =YEAR(N143) -> 2025 | R143: Nhập kho | T143: 45847 | U143: =VLOOKUP($E143,'0. Mã Supplier'!$B:$F,5,0) -> 60 | V143: =T143+U143 -> 45907 | W143: =WEEKNUM(V143) -> 37 | X143: =IF(V143<>0,MONTH(V143),"") -> 9 | Y143: =YEAR(V143) -> 2025 | AA143: =IF(Z143="yes",0,TODAY()-V143) -> 357 | AB143: 28994032 | AD143: =IFERROR(K143-AB143,0) -> 1958876
A144: EVH-002#1 | B144: MAT002005 | C144: =VLOOKUP(B144,'1. Master Data'!$C:$K,9,0) -> Nệm Hybrid 160 x 200 x 25 cm | D144: =VLOOKUP(E144,'0. Mã Supplier'!$B:$C,2,0) -> SUVN0003 | E144: EVERHOME | F144: Cái | G144: 5 | H144: 5 | I144: =VLOOKUP($B144,'1. Master Data'!$C:$AB,26,0) -> 2229010 | J144: =I144*H144 -> 11145050 | K144: =J144*1.08 -> 12036654 | L144: 45860 | N144: 45906 | O144: =N144-L144 -> 46 | P144: =MONTH(N144) -> 9 | Q144: =YEAR(N144) -> 2025 | R144: Nhập kho | T144: =N144 -> 45906 | U144: =VLOOKUP($E144,'0. Mã Supplier'!$B:$F,5,0) -> 60 | V144: =T144+U144 -> 45966 | W144: =WEEKNUM(V144) -> 45 | X144: =IF(V144<>0,MONTH(V144),"") -> 11 | Y144: =YEAR(V144) -> 2025 | AA144: =IF(Z144="yes",0,TODAY()-V144) -> 298 | AB144: 15000000 | AD144: =IFERROR(K144-AB144,0) -> -2963346
A145: EVH-002#1 | B145: MAT002006 | C145: =VLOOKUP(B145,'1. Master Data'!$C:$K,9,0) -> Nệm Hybrid 180 x 200 x 25 cm | D145: =VLOOKUP(E145,'0. Mã Supplier'!$B:$C,2,0) -> SUVN0003 | E145: EVERHOME | F145: Cái | G145: 5 | H145: 5 | I145: =VLOOKUP($B145,'1. Master Data'!$C:$AB,26,0) -> 2425010 | J145: =I145*H145 -> 12125050 | K145: =J145*1.08 -> 13095054 | L145: 45860 | N145: 45906 | O145: =N145-L145 -> 46 | P145: =MONTH(N145) -> 9 | Q145: =YEAR(N145) -> 2025 | R145: Nhập kho | T145: =N145 -> 45906 | U145: =VLOOKUP($E145,'0. Mã Supplier'!$B:$F,5,0) -> 60 | V145: =T145+U145 -> 45966 | W145: =WEEKNUM(V145) -> 45 | X145: =IF(V145<>0,MONTH(V145),"") -> 11 | Y145: =YEAR(V145) -> 2025 | AA145: =IF(Z145="yes",0,TODAY()-V145) -> 298 | AB145: 20000000 | AD145: =IFERROR(K145-AB145,0) -> -6904946
A146: EVH-002#1 | B146: MAT003005 | C146: =VLOOKUP(B146,'1. Master Data'!$C:$K,9,0) -> Nệm Hybrid Latex 160 x 200 x 27 cm | D146: =VLOOKUP(E146,'0. Mã Supplier'!$B:$C,2,0) -> SUVN0003 | E146: EVERHOME | F146: Cái | G146: 5 | H146: 4 | I146: =VLOOKUP($B146,'1. Master Data'!$C:$AB,26,0) -> 2572010 | J146: =I146*H146 -> 10288040 | K146: =J146*1.08 -> 11111083 | L146: 45860 | N146: 45906 | O146: =N146-L146 -> 46 | P146: =MONTH(N146) -> 9 | Q146: =YEAR(N146) -> 2025 | R146: Nhập kho | T146: =N146 -> 45906 | U146: =VLOOKUP($E146,'0. Mã Supplier'!$B:$F,5,0) -> 60 | V146: =T146+U146 -> 45966 | W146: =WEEKNUM(V146) -> 45 | X146: =IF(V146<>0,MONTH(V146),"") -> 11 | Y146: =YEAR(V146) -> 2025 | AA146: =IF(Z146="yes",0,TODAY()-V146) -> 298 | AB146: 20000000 | AD146: =IFERROR(K146-AB146,0) -> -8888916.8
A147: EVH-002#1 | B147: MAT003006 | C147: =VLOOKUP(B147,'1. Master Data'!$C:$K,9,0) -> Nệm Hybrid Latex 180 x 200 x 27 cm | D147: =VLOOKUP(E147,'0. Mã Supplier'!$B:$C,2,0) -> SUVN0003 | E147: EVERHOME | F147: Cái | G147: 5 | H147: 5 | I147: =VLOOKUP($B147,'1. Master Data'!$C:$AB,26,0) -> 2866010 | J147: =I147*H147 -> 14330050 | K147: =J147*1.08 -> 15476454 | L147: 45860 | N147: 45906 | O147: =N147-L147 -> 46 | P147: =MONTH(N147) -> 9 | Q147: =YEAR(N147) -> 2025 | R147: Nhập kho | T147: =N147 -> 45906 | U147: =VLOOKUP($E147,'0. Mã Supplier'!$B:$F,5,0) -> 60 | V147: =T147+U147 -> 45966 | W147: =WEEKNUM(V147) -> 45 | X147: =IF(V147<>0,MONTH(V147),"") -> 11 | Y147: =YEAR(V147) -> 2025 | AA147: =IF(Z147="yes",0,TODAY()-V147) -> 298 | AB147: 20000000 | AD147: =IFERROR(K147-AB147,0) -> -4523546
A148: EVH-002#2 | B148: MAT002003 | C148: =VLOOKUP(B148,'1. Master Data'!$C:$K,9,0) -> Nệm Hybrid 120 x 200 x 25 cm | D148: =VLOOKUP(E148,'0. Mã Supplier'!$B:$C,2,0) -> SUVN0003 | E148: EVERHOME | F148: Cái | G148: 5 | H148: 5 | I148: =VLOOKUP($B148,'1. Master Data'!$C:$AB,26,0) -> 1641010 | J148: =I148*H148 -> 8205050 | K148: =J148*1.08 -> 8861454 | L148: 45860 | N148: 45923 | O148: =N148-L148 -> 63 | P148: =MONTH(N148) -> 9 | Q148: =YEAR(N148) -> 2025 | R148: Nhập kho | T148: =N148 -> 45923 | U148: =VLOOKUP($E148,'0. Mã Supplier'!$B:$F,5,0) -> 60 | V148: =T148+U148 -> 45983 | W148: =WEEKNUM(V148) -> 47 | X148: =IF(V148<>0,MONTH(V148),"") -> 11 | Y148: =YEAR(V148) -> 2025 | AA148: =IF(Z148="yes",0,TODAY()-V148) -> 281 | AB148: 15000000 | AC148: 46024 | AD148: =IFERROR(K148-AB148,0) -> -6138546
A149: EVH-002#2 | B149: MAT002005 | C149: =VLOOKUP(B149,'1. Master Data'!$C:$K,9,0) -> Nệm Hybrid 160 x 200 x 25 cm | D149: =VLOOKUP(E149,'0. Mã Supplier'!$B:$C,2,0) -> SUVN0003 | E149: EVERHOME | F149: Cái | G149: 30 | H149: 30 | I149: =VLOOKUP($B149,'1. Master Data'!$C:$AB,26,0) -> 2229010 | J149: =I149*H149 -> 66870300 | K149: =J149*1.08 -> 72219924 | L149: 45860 | N149: 45923 | O149: =N149-L149 -> 63 | P149: =MONTH(N149) -> 9 | Q149: =YEAR(N149) -> 2025 | R149: Nhập kho | T149: =N149 -> 45923 | U149: =VLOOKUP($E149,'0. Mã Supplier'!$B:$F,5,0) -> 60 | V149: =T149+U149 -> 45983 | W149: =WEEKNUM(V149) -> 47 | X149: =IF(V149<>0,MONTH(V149),"") -> 11 | Y149: =YEAR(V149) -> 2025 | AA149: =IF(Z149="yes",0,TODAY()-V149) -> 281 | AB149: 15000000 | AD149: =IFERROR(K149-AB149,0) -> 57219924
A150: EVH-002#2 | B150: MAT002006 | C150: =VLOOKUP(B150,'1. Master Data'!$C:$K,9,0) -> Nệm Hybrid 180 x 200 x 25 cm | D150: =VLOOKUP(E150,'0. Mã Supplier'!$B:$C,2,0) -> SUVN0003 | E150: EVERHOME | F150: Cái | G150: 10 | H150: 10 | I150: =VLOOKUP($B150,'1. Master Data'!$C:$AB,26,0) -> 2425010 | J150: =I150*H150 -> 24250100 | K150: =J150*1.08 -> 26190108 | L150: 45860 | N150: 45923 | O150: =N150-L150 -> 63 | P150: =MONTH(N150) -> 9 | Q150: =YEAR(N150) -> 2025 | R150: Nhập kho | T150: =N150 -> 45923 | U150: =VLOOKUP($E150,'0. Mã Supplier'!$B:$F,5,0) -> 60 | V150: =T150+U150 -> 45983 | W150: =WEEKNUM(V150) -> 47 | X150: =IF(V150<>0,MONTH(V150),"") -> 11 | Y150: =YEAR(V150) -> 2025 | AA150: =IF(Z150="yes",0,TODAY()-V150) -> 281 | AB150: =IF(Z150="Yes",K150) -> FALSE | AD150: =IFERROR(K150-AB150,0) -> 26190108
A151: EVH-002#2 | B151: MAT003003 | C151: =VLOOKUP(B151,'1. Master Data'!$C:$K,9,0) -> Nệm Hybrid Latex 120 x 200 x 27 cm | D151: =VLOOKUP(E151,'0. Mã Supplier'!$B:$C,2,0) -> SUVN0003 | E151: EVERHOME | F151: Cái | G151: 5 | H151: 5 | I151: =VLOOKUP($B151,'1. Master Data'!$C:$AB,26,0) -> 2082010 | J151: =I151*H151 -> 10410050 | K151: =J151*1.08 -> 11242854 | L151: 45860 | N151: 45923 | O151: =N151-L151 -> 63 | P151: =MONTH(N151) -> 9 | Q151: =YEAR(N151) -> 2025 | R151: Nhập kho | T151: =N151 -> 45923 | U151: =VLOOKUP($E151,'0. Mã Supplier'!$B:$F,5,0) -> 60 | V151: =T151+U151 -> 45983 | W151: =WEEKNUM(V151) -> 47 | X151: =IF(V151<>0,MONTH(V151),"") -> 11 | Y151: =YEAR(V151) -> 2025 | AA151: =IF(Z151="yes",0,TODAY()-V151) -> 281 | AB151: =IF(Z151="Yes",K151) -> FALSE | AD151: =IFERROR(K151-AB151,0) -> 11242854
A152: EVH-002#2 | B152: MAT003005 | C152: =VLOOKUP(B152,'1. Master Data'!$C:$K,9,0) -> Nệm Hybrid Latex 160 x 200 x 27 cm | D152: =VLOOKUP(E152,'0. Mã Supplier'!$B:$C,2,0) -> SUVN0003 | E152: EVERHOME | F152: Cái | G152: 6 | H152: 6 | I152: =VLOOKUP($B152,'1. Master Data'!$C:$AB,26,0) -> 2572010 | J152: =I152*H152 -> 15432060 | K152: =J152*1.08 -> 16666625 | L152: 45860 | N152: 45923 | O152: =N152-L152 -> 63 | P152: =MONTH(N152) -> 9 | Q152: =YEAR(N152) -> 2025 | R152: Nhập kho | T152: =N152 -> 45923 | U152: =VLOOKUP($E152,'0. Mã Supplier'!$B:$F,5,0) -> 60 | V152: =T152+U152 -> 45983 | W152: =WEEKNUM(V152) -> 47 | X152: =IF(V152<>0,MONTH(V152),"") -> 11 | Y152: =YEAR(V152) -> 2025 | AA152: =IF(Z152="yes",0,TODAY()-V152) -> 281 | AB152: =IF(Z152="Yes",K152) -> FALSE | AD152: =IFERROR(K152-AB152,0) -> 16666625
A153: EVH-002#2 | B153: MAT003006 | C153: =VLOOKUP(B153,'1. Master Data'!$C:$K,9,0) -> Nệm Hybrid Latex 180 x 200 x 27 cm | D153: =VLOOKUP(E153,'0. Mã Supplier'!$B:$C,2,0) -> SUVN0003 | E153: EVERHOME | F153: Cái | G153: 5 | H153: 5 | I153: =VLOOKUP($B153,'1. Master Data'!$C:$AB,26,0) -> 2866010 | J153: =I153*H153 -> 14330050 | K153: =J153*1.08 -> 15476454 | L153: 45860 | N153: 45923 | O153: =N153-L153 -> 63 | P153: =MONTH(N153) -> 9 | Q153: =YEAR(N153) -> 2025 | R153: Nhập kho | T153: =N153 -> 45923 | U153: =VLOOKUP($E153,'0. Mã Supplier'!$B:$F,5,0) -> 60 | V153: =T153+U153 -> 45983 | W153: =WEEKNUM(V153) -> 47 | X153: =IF(V153<>0,MONTH(V153),"") -> 11 | Y153: =YEAR(V153) -> 2025 | AA153: =IF(Z153="yes",0,TODAY()-V153) -> 281 | AB153: =IF(Z153="Yes",K153) -> FALSE | AD153: =IFERROR(K153-AB153,0) -> 15476454
A154: EVH-003 | B154: MAT002006 | C154: =VLOOKUP(B154,'1. Master Data'!$C:$K,9,0) -> Nệm Hybrid 180 x 200 x 25 cm | D154: =VLOOKUP(E154,'0. Mã Supplier'!$B:$C,2,0) -> SUVN0003 | E154: EVERHOME | F154: Cái | G154: 10 | H154: 10 | I154: =VLOOKUP($B154,'1. Master Data'!$C:$AB,26,0) -> 2425010 | J154: =I154*H154 -> 24250100 | K154: =J154*1.08 -> 26190108 | L154: 45929 | N154: 45968 | O154: =N154-L154 -> 39 | P154: =MONTH(N154) -> 11 | Q154: =YEAR(N154) -> 2025 | R154: Nhập kho | T154: =N154 -> 45968 | U154: =VLOOKUP($E154,'0. Mã Supplier'!$B:$F,5,0) -> 60 | V154: =T154+U154 -> 46028 | W154: =WEEKNUM(V154) -> 2 | X154: =IF(V154<>0,MONTH(V154),"") -> 1 | Y154: =YEAR(V154) -> 2026 | AA154: =IF(Z154="yes",0,TODAY()-V154) -> 236 | AB154: =IF(Z154="Yes",K154) -> FALSE | AD154: =IFERROR(K154-AB154,0) -> 26190108
A155: EVH-003 | B155: MAT003005 | C155: =VLOOKUP(B155,'1. Master Data'!$C:$K,9,0) -> Nệm Hybrid Latex 160 x 200 x 27 cm | D155: =VLOOKUP(E155,'0. Mã Supplier'!$B:$C,2,0) -> SUVN0003 | E155: EVERHOME | F155: Cái | G155: 10 | H155: 10 | I155: =VLOOKUP($B155,'1. Master Data'!$C:$AB,26,0) -> 2572010 | J155: =I155*H155 -> 25720100 | K155: =J155*1.08 -> 27777708 | L155: 45929 | N155: 45968 | O155: =N155-L155 -> 39 | P155: =MONTH(N155) -> 11 | Q155: =YEAR(N155) -> 2025 | R155: Nhập kho | T155: =N155 -> 45968 | U155: =VLOOKUP($E155,'0. Mã Supplier'!$B:$F,5,0) -> 60 | V155: =T155+U155 -> 46028 | W155: =WEEKNUM(V155) -> 2 | X155: =IF(V155<>0,MONTH(V155),"") -> 1 | Y155: =YEAR(V155) -> 2026 | AA155: =IF(Z155="yes",0,TODAY()-V155) -> 236 | AB155: =IF(Z155="Yes",K155) -> FALSE | AD155: =IFERROR(K155-AB155,0) -> 27777708
A156: EVH-003 | B156: MAT003006 | C156: =VLOOKUP(B156,'1. Master Data'!$C:$K,9,0) -> Nệm Hybrid Latex 180 x 200 x 27 cm | D156: =VLOOKUP(E156,'0. Mã Supplier'!$B:$C,2,0) -> SUVN0003 | E156: EVERHOME | F156: Cái | G156: 10 | H156: 10 | I156: =VLOOKUP($B156,'1. Master Data'!$C:$AB,26,0) -> 2866010 | J156: =I156*H156 -> 28660100 | K156: =J156*1.08 -> 30952908 | L156: 45929 | N156: 45968 | O156: =N156-L156 -> 39 | P156: =MONTH(N156) -> 11 | Q156: =YEAR(N156) -> 2025 | R156: Nhập kho | T156: =N156 -> 45968 | U156: =VLOOKUP($E156,'0. Mã Supplier'!$B:$F,5,0) -> 60 | V156: =T156+U156 -> 46028 | W156: =WEEKNUM(V156) -> 2 | X156: =IF(V156<>0,MONTH(V156),"") -> 1 | Y156: =YEAR(V156) -> 2026 | AA156: =IF(Z156="yes",0,TODAY()-V156) -> 236 | AB156: =IF(Z156="Yes",K156) -> FALSE | AD156: =IFERROR(K156-AB156,0) -> 30952908
A157: TXN-001 | B157: SET003001 | C157: =VLOOKUP(B157,'1. Master Data'!$C:$K,9,0) -> Bộ Chăn ga chun gấu xanh gấu hồng 3CT Gấu xanh 160 x 200 cm | D157: =VLOOKUP(E157,'0. Mã Supplier'!$B:$C,2,0) -> SUVN0004 | E157: TEXNAM | F157: Bộ | G157: 50 | H157: 50 | I157: =VLOOKUP($B157,'1. Master Data'!$C:$AB,26,0) -> 155630 | J157: =I157*H157 -> 7781500 | K157: =J157*1.08 -> 8404020 | N157: 45727 | O157: =N157-L157 -> 45727 | P157: =MONTH(N157) -> 3 | Q157: =YEAR(N157) -> 2025 | R157: Nhập kho | T157: 45782 | U157: =VLOOKUP($E157,'0. Mã Supplier'!$B:$F,5,0) -> 60 | V157: =T157+U157 -> 45842 | W157: =WEEKNUM(V157) -> 27 | X157: =IF(V157<>0,MONTH(V157),"") -> 7 | Y157: =YEAR(V157) -> 2025 | AA157: =IF(Z157="yes",0,TODAY()-V157) -> 422 | AB157: 20000000 | AD157: =IFERROR(K157-AB157,0) -> -11595980
A158: TXN-001 | B158: SET003002 | C158: =VLOOKUP(B158,'1. Master Data'!$C:$K,9,0) -> Bộ Chăn ga chun gấu xanh gấu hồng 3CT Gấu hồng 160 x 200 cm | D158: =VLOOKUP(E158,'0. Mã Supplier'!$B:$C,2,0) -> SUVN0004 | E158: TEXNAM | F158: Bộ | G158: 50 | H158: 50 | I158: =VLOOKUP($B158,'1. Master Data'!$C:$AB,26,0) -> 155630 | J158: =I158*H158 -> 7781500 | K158: =J158*1.08 -> 8404020 | N158: 45727 | O158: =N158-L158 -> 45727 | P158: =MONTH(N158) -> 3 | Q158: =YEAR(N158) -> 2025 | R158: Nhập kho | T158: 45782 | U158: =VLOOKUP($E158,'0. Mã Supplier'!$B:$F,5,0) -> 60 | V158: =T158+U158 -> 45842 | W158: =WEEKNUM(V158) -> 27 | X158: =IF(V158<>0,MONTH(V158),"") -> 7 | Y158: =YEAR(V158) -> 2025 | AA158: =IF(Z158="yes",0,TODAY()-V158) -> 422 | AB158: 20000000 | AD158: =IFERROR(K158-AB158,0) -> -11595980
A159: TXN-001 | B159: SET003003 | C159: =VLOOKUP(B159,'1. Master Data'!$C:$K,9,0) -> Bộ Chăn ga chun gấu xanh gấu hồng 3CT Gấu xanh 180 x 200 cm | D159: =VLOOKUP(E159,'0. Mã Supplier'!$B:$C,2,0) -> SUVN0004 | E159: TEXNAM | F159: Bộ | G159: 50 | H159: 50 | I159: =VLOOKUP($B159,'1. Master Data'!$C:$AB,26,0) -> 163300 | J159: =I159*H159 -> 8165000 | K159: =J159*1.08 -> 8818200 | N159: 45727 | O159: =N159-L159 -> 45727 | P159: =MONTH(N159) -> 3 | Q159: =YEAR(N159) -> 2025 | R159: Nhập kho | T159: 45782 | U159: =VLOOKUP($E159,'0. Mã Supplier'!$B:$F,5,0) -> 60 | V159: =T159+U159 -> 45842 | W159: =WEEKNUM(V159) -> 27 | X159: =IF(V159<>0,MONTH(V159),"") -> 7 | Y159: =YEAR(V159) -> 2025 | AA159: =IF(Z159="yes",0,TODAY()-V159) -> 422 | AB159: 10000000 | AC159: 46024 | AD159: =IFERROR(K159-AB159,0) -> -1181800
A160: TXN-001 | B160: SET003004 | C160: =VLOOKUP(B160,'1. Master Data'!$C:$K,9,0) -> Bộ Chăn ga chun gấu xanh gấu hồng 3CT Gấu hồng 180 x 200 cm | D160: =VLOOKUP(E160,'0. Mã Supplier'!$B:$C,2,0) -> SUVN0004 | E160: TEXNAM | F160: Bộ | G160: 50 | H160: 50 | I160: =VLOOKUP($B160,'1. Master Data'!$C:$AB,26,0) -> 163300 | J160: =I160*H160 -> 8165000 | K160: =J160*1.08 -> 8818200 | N160: 45727 | O160: =N160-L160 -> 45727 | P160: =MONTH(N160) -> 3 | Q160: =YEAR(N160) -> 2025 | R160: Nhập kho | T160: 45782 | U160: =VLOOKUP($E160,'0. Mã Supplier'!$B:$F,5,0) -> 60 | V160: =T160+U160 -> 45842 | W160: =WEEKNUM(V160) -> 27 | X160: =IF(V160<>0,MONTH(V160),"") -> 7 | Y160: =YEAR(V160) -> 2025 | AA160: =IF(Z160="yes",0,TODAY()-V160) -> 422 | AB160: =IF(Z160="Yes",K160) -> FALSE | AD160: =IFERROR(K160-AB160,0) -> 8818200
A161: TXN-001 | B161: BLA003001 | C161: =VLOOKUP(B161,'1. Master Data'!$C:$K,9,0) -> Chăn T&N Polyester HQ (chần) Gấu xanh 200 x 230 cm | D161: =VLOOKUP(E161,'0. Mã Supplier'!$B:$C,2,0) -> SUVN0004 | E161: TEXNAM | F161: Cái | G161: 50 | H161: 50 | I161: =VLOOKUP($B161,'1. Master Data'!$C:$AB,26,0) -> 204190 | J161: =I161*H161 -> 10209500 | K161: =J161*1.08 -> 11026260 | N161: 45727 | O161: =N161-L161 -> 45727 | P161: =MONTH(N161) -> 3 | Q161: =YEAR(N161) -> 2025 | R161: Nhập kho | T161: 45782 | U161: =VLOOKUP($E161,'0. Mã Supplier'!$B:$F,5,0) -> 60 | V161: =T161+U161 -> 45842 | W161: =WEEKNUM(V161) -> 27 | X161: =IF(V161<>0,MONTH(V161),"") -> 7 | Y161: =YEAR(V161) -> 2025 | AA161: =IF(Z161="yes",0,TODAY()-V161) -> 422 | AB161: =IF(Z161="Yes",K161) -> FALSE | AD161: =IFERROR(K161-AB161,0) -> 11026260
A162: TXN-001 | B162: BLA003002 | C162: =VLOOKUP(B162,'1. Master Data'!$C:$K,9,0) -> Chăn T&N Polyester HQ (chần) Gấu hồng 200 x 230 cm | D162: =VLOOKUP(E162,'0. Mã Supplier'!$B:$C,2,0) -> SUVN0004 | E162: TEXNAM | F162: Cái | G162: 50 | H162: 50 | I162: =VLOOKUP($B162,'1. Master Data'!$C:$AB,26,0) -> 204190 | J162: =I162*H162 -> 10209500 | K162: =J162*1.08 -> 11026260 | N162: 45727 | O162: =N162-L162 -> 45727 | P162: =MONTH(N162) -> 3 | Q162: =YEAR(N162) -> 2025 | R162: Nhập kho | T162: 45782 | U162: =VLOOKUP($E162,'0. Mã Supplier'!$B:$F,5,0) -> 60 | V162: =T162+U162 -> 45842 | W162: =WEEKNUM(V162) -> 27 | X162: =IF(V162<>0,MONTH(V162),"") -> 7 | Y162: =YEAR(V162) -> 2025 | AA162: =IF(Z162="yes",0,TODAY()-V162) -> 422 | AB162: =IF(Z162="Yes",K162) -> FALSE | AD162: =IFERROR(K162-AB162,0) -> 11026260
A163: APW-001 | B163: ACC001003 | C163: =VLOOKUP(B163,'1. Master Data'!$C:$K,9,0) -> Phụ Kiện Everlife Tấm bảo vệ nệm chống thấm Mẫu 1, 120 x 200 cm | D163: =VLOOKUP(E163,'0. Mã Supplier'!$B:$C,2,0) -> SUVN0005 | E163: AP WOOD | F163: Bộ | G163: 2 | H163: 2 | I163: =VLOOKUP($B163,'1. Master Data'!$C:$AB,26,0) -> 451000 | J163: =I163*H163 -> 902000 | K163: =J163*1.08 -> 974160 | N163: 45807 | O163: =N163-L163 -> 45807 | P163: =MONTH(N163) -> 5 | Q163: =YEAR(N163) -> 2025 | R163: Nhập kho | T163: 45813 | U163: =VLOOKUP($E163,'0. Mã Supplier'!$B:$F,5,0) -> 60 | V163: =T163+U163 -> 45873 | W163: =WEEKNUM(V163) -> 32 | X163: =IF(V163<>0,MONTH(V163),"") -> 8 | Y163: =YEAR(V163) -> 2025 | Z163: Yes | AA163: =IF(Z163="yes",0,TODAY()-V163) -> 0 | AB163: =IF(Z163="Yes",K163) -> 974160 | AD163: =IFERROR(K163-AB163,0) -> 0
A164: APW-001 | B164: ACC001005 | C164: =VLOOKUP(B164,'1. Master Data'!$C:$K,9,0) -> Phụ Kiện Everlife Tấm bảo vệ nệm chống thấm Mẫu 1, 160 x 200 cm | D164: =VLOOKUP(E164,'0. Mã Supplier'!$B:$C,2,0) -> SUVN0005 | E164: AP WOOD | F164: Bộ | G164: 5 | H164: 5 | I164: =VLOOKUP($B164,'1. Master Data'!$C:$AB,26,0) -> 522500 | J164: =I164*H164 -> 2612500 | K164: =J164*1.08 -> 2821500 | N164: 45807 | O164: =N164-L164 -> 45807 | P164: =MONTH(N164) -> 5 | Q164: =YEAR(N164) -> 2025 | R164: Nhập kho | T164: 45813 | U164: =VLOOKUP($E164,'0. Mã Supplier'!$B:$F,5,0) -> 60 | V164: =T164+U164 -> 45873 | W164: =WEEKNUM(V164) -> 32 | X164: =IF(V164<>0,MONTH(V164),"") -> 8 | Y164: =YEAR(V164) -> 2025 | Z164: Yes | AA164: =IF(Z164="yes",0,TODAY()-V164) -> 0 | AB164: =IF(Z164="Yes",K164) -> 2821500 | AD164: =IFERROR(K164-AB164,0) -> 0
A165: APW-001 | B165: ACC001006 | C165: =VLOOKUP(B165,'1. Master Data'!$C:$K,9,0) -> Phụ Kiện Everlife Tấm bảo vệ nệm chống thấm Mẫu 1, 180 x 200 cm | D165: =VLOOKUP(E165,'0. Mã Supplier'!$B:$C,2,0) -> SUVN0005 | E165: AP WOOD | F165: Bộ | G165: 5 | H165: 5 | I165: =VLOOKUP($B165,'1. Master Data'!$C:$AB,26,0) -> 577500 | J165: =I165*H165 -> 2887500 | K165: =J165*1.08 -> 3118500 | N165: 45807 | O165: =N165-L165 -> 45807 | P165: =MONTH(N165) -> 5 | Q165: =YEAR(N165) -> 2025 | R165: Nhập kho | T165: 45813 | U165: =VLOOKUP($E165,'0. Mã Supplier'!$B:$F,5,0) -> 60 | V165: =T165+U165 -> 45873 | W165: =WEEKNUM(V165) -> 32 | X165: =IF(V165<>0,MONTH(V165),"") -> 8 | Y165: =YEAR(V165) -> 2025 | Z165: Yes | AA165: =IF(Z165="yes",0,TODAY()-V165) -> 0 | AB165: =IF(Z165="Yes",K165) -> 3118500 | AD165: =IFERROR(K165-AB165,0) -> 0
A166: APW-001 | B166: ACC001011 | C166: =VLOOKUP(B166,'1. Master Data'!$C:$K,9,0) -> Phụ Kiện Everlife Tấm bảo vệ nệm chống thấm Mẫu 2, 120 x 200 cm | D166: =VLOOKUP(E166,'0. Mã Supplier'!$B:$C,2,0) -> SUVN0005 | E166: AP WOOD | F166: Bộ | G166: 2 | H166: 2 | I166: =VLOOKUP($B166,'1. Master Data'!$C:$AB,26,0) -> 396000 | J166: =I166*H166 -> 792000 | K166: =J166*1.08 -> 855360 | N166: 45807 | O166: =N166-L166 -> 45807 | P166: =MONTH(N166) -> 5 | Q166: =YEAR(N166) -> 2025 | R166: Nhập kho | T166: 45813 | U166: =VLOOKUP($E166,'0. Mã Supplier'!$B:$F,5,0) -> 60 | V166: =T166+U166 -> 45873 | W166: =WEEKNUM(V166) -> 32 | X166: =IF(V166<>0,MONTH(V166),"") -> 8 | Y166: =YEAR(V166) -> 2025 | Z166: Yes | AA166: =IF(Z166="yes",0,TODAY()-V166) -> 0 | AB166: =IF(Z166="Yes",K166) -> 855360 | AD166: =IFERROR(K166-AB166,0) -> 0
...

Sheet Mã Kho
A1: Mã kho | B1: Tên kho | C1: Loại kho | D1: Địa chỉ
A2: WH01 | B2: Kho thuê-ACE HOME | C2: Kho bán hàng | D2: Thành phố Hồ Chí Minh Phường Bình Đông Kho 14 kim hằng, số 1 Ba Tơ ( Trịnh Quang Nghị),(VN)
A3: WH02 | B3: Kho Cửa Hàng D9 | C3: Kho bán hàng | D3: Tỉnh Đồng Nai Phường Trấn Biên E97, Đường D 9 Võ Thị Sáu, Phường Trấn Biên, Tỉnh Đồng Nai, Việt Nam,(VN)
A4: WH03 | B4: Kho Everhome | C4: Kho bán hàng | D4: Thành phố Hà Nội Xã Hòa Lạc Công Ty Cổ Phàn Quốc Tế Everhome, Thôn 1, Xã Hòa Lạc, Thành phố Hà Nội, Việt Nam,(VN)
A5: WH04 | B5: Kho hàng lỗi | C5: Kho lưu trữ | D5: Tỉnh Đồng Nai Phường Trấn Biên E97, Đường D 9 Võ Thị Sáu, Phường Trấn Biên, Tỉnh Đồng Nai, Việt Nam,(VN)
